Workbook
Name Level: 'Character Sheet'!$AZ$13

Sheet Home
B2: PF2E Autocalculating Character Sheet Exhanced v1
B4: By /u/AshenCombatant
B6: Make your own copy to edit here: | E6: For latest version, check out my reddit post:
B7: =HYPERLINK("https://docs.google.com/spreadsheets/d/1avX2bXuYo4bWDjGbZWIYBR6QClLWRN55iCIM_KX4WD0/copy#gid=1535919198","CLICK HERE") -> CLICK HERE | E7: This is not the latest version
B11: Colour Legend | E11: Tips
B12: Auto-calculated (useful) | C12: DO NOT EDIT THESE CELLS | E12: - Check out the setting at the top right to fade details
B13: Auto-calculated (less useful) | E13: - You can change the ability used for a calculation by changing the three-letter abbreviation above the box.
B14: User-provided (numbers) | C14: EDIT THESE CELLS
B15: User-provided (free-form) | E15: - If you have more than one proficiency selected (i.e. for TEML), the sheet will simply use the highest one.
E17: - You can use L (light) as the Bulk value for equipment.
B18: Credits | E18: - HIDE any sheets you are not using
B19: Creation | C19: Reddit user
B20: =HYPERLINK("https://docs.google.com/spreadsheets/d/1V6l7A0kaPkPUjNlwFEqziMnE5NWnCELZ42yW4ePbexE/edit#gid=757414001","Original PF1E AutoSheet") -> Original PF1E AutoSheet | C20: =HYPERLINK("https://www.reddit.com/user/darthmarth28","/u/darthmarth28") -> /u/darthmarth28 | E20: Author's Note
B21: =HYPERLINK("https://www.reddit.com/r/Pathfinder_RPG/comments/944tip/i_made_a_google_sheets_autosheet_for_2e_based_on/","PF2E Playtest AutoSheet") -> PF2E Playtest AutoSheet | C21: =HYPERLINK("https://www.reddit.com/user/galacticArtificer","/u/galacticArtificer") -> /u/galacticArtificer | E21: This character sheet is as up to date as Dark Achives, and includes the formatting for spells and classes from the expansion, but with the inevitable addition of more content I have done what I can with adding a "Other" to the Data tab, allowing quick changes for any homebrew or new classes that may be added. Good luck using this sheet, its as fool proof as I could make it. With a potential influx of new members to the pathfinder community, I am releasing this ahead of schedule, but will continue to work on it.
B22: =HYPERLINK("http://knowdirectionpodcast.com/2019/08/perrams-landscape-character-sheet-for-pathfinder-second-edition/","PF2E Sheet Design") -> PF2E Sheet Design | C22: =HYPERLINK("https://www.reddit.com/user/perram","/u/perram") -> /u/perram
B23: =HYPERLINK("https://www.reddit.com/r/Pathfinder2e/comments/cpc3yz/pathfinder_2e_autosheet_on_google_docs/","PF2E AutoSheet (Color)") -> PF2E AutoSheet (Color) | C23: =HYPERLINK("https://www.reddit.com/user/FireandStone/","/u/FireandStone") -> /u/FireandStone
B24: =HYPERLINK("https://www.reddit.com/r/Pathfinder2e/comments/cqzg14/autocharacter_sheet_for_players_using_google/","PF2E AutoSheet (B/W)") -> PF2E AutoSheet (B/W) | C24: =HYPERLINK("https://www.reddit.com/user/selfconfessedcynic","/u/selfconfessedcynic") -> /u/selfconfessedcynic
B25: PF2E Simplified | C25: =HYPERLINK("https://www.reddit.com/user/scientificbruno/","/u/scientificbruno") -> /u/scientificbruno
B26: PF2E Simplified 2.0 | C26: =HYPERLINK("https://www.reddit.com/user/scientificbruno/","/u/scientificbruno") -> /u/scientificbruno
B27: Current Version | C27: /u/AshenCombatant

Sheet Character Sheet
Q2: Character Name | U2: Jeff | AM2: Ancestry | AQ2: Gnome | AX2: Heritage
AM4: Background | AX4: Size
Q6: Player | U6: Jerry | AM6: Class | AQ6: Druid | AX6: Key Ability | BB6: Wis
B7: Action/Activity Icon Legend
B8: 1, 2, or 3 actions | H8: Free | K8: Reaction | N8: Variable | Q8: Alignment | AB8: Deity | AM8: Experience | AU8: XP | AX8: Spellcasting Tradition | BB8: Primal
B11: PORTRAIT | L11: ABILITY SCORES | AA11: ARMOR CLASS | AS11: HIT POINTS | AZ11: Level | BD11: Hero Points
B12: >:D | N12: Score | P12: Modifier | U12: Score | W12: Modifier | AA12: AC | AD12: Dex | AF12: Prof | AH12: Item | AJ12: Shield | AM12: HP | AO12: Hard | AP12: BT | AQ12: Max | AS12: Current | AW12: Max
M13: STR | O13: 10 | P13: =MODIFIER(ROUNDDOWN((O13-10)/2,0)) -> +0 | T13: INT | V13: 10 | W13: =MODIFIER(ROUNDDOWN((V13-10)/2,0)) -> +0 | AA13: =10+AD13+AH13+AF13 -> 14 | AC13: = | AD13: =MIN(vlookup(AD12,Data!$B$14:$C$19,2,0), Inventory!$P$6) -> 0 | AE13: + | AF13: =SWITCH(Inventory!$B$8, AA15, if(AD17,8+Level,if(AC17,6+Level,if(AB17,4+Level,if(AA17,2+Level,0)))), AE15, if(AH17,8+Level,if(AG17,6+Level,if(AF17,4+Level,if(AE17,2+Level,0)))), AJ15, if(AM17,8+Level,if(AL17,6+Level,if(AK17,4+Level,if(AJ17,2+Level,0)))), AN15, if(AQ17,8+Level,if(AP17,6+Level,if(AO17,4+Level,if(AN17,2+Level,0))))) -> 3 | AG13: + | AH13: =Inventory!$M$6+Inventory!$M$8 -> 1 | AJ13: =MODIFIER(Inventory!$M$12) -> +1 | AO13: =Inventory!$S$12 -> 3 | AP13: =Inventory!$Y$12 -> 3 | AQ13: =Inventory!$V$12 -> 6 | AV13: / | AW13: =VLOOKUP($AQ$2,Data!B23:C33,2, FALSE) + (VLOOKUP($AQ$6,Data!B37:C58,2, FALSE) + VLOOKUP("Con", Data!$B$14:$C$19, 2, FALSE)) * $AZ$13 + $AW$15 -> 16 | AZ13: 1 | BD13: FALSE | BE13: FALSE | BF13: FALSE
AW14: Bonus HP
M15: DEX | O15: 10 | P15: =MODIFIER(ROUNDDOWN((O15-10)/2,0)) -> +0 | T15: WIS | V15: 10 | W15: =MODIFIER(ROUNDDOWN((V15-10)/2,0)) -> +0 | AA15: Unarmored | AE15: Light Armor | AJ15: Medium Armor | AN15: Heavy Armor | AW15: 0
AA16: T | AB16: E | AC16: M | AD16: L | AE16: T | AF16: E | AG16: M | AH16: L | AJ16: T | AK16: E | AL16: M | AM16: L | AN16: T | AO16: E | AP16: M | AQ16: L | AS16: Dying | AU16: Wounded | AW16: Temp HP | BA16: Settings
M17: CON | O17: 10 | P17: =MODIFIER(ROUNDDOWN((O17-10)/2,0)) -> +0 | T17: CHA | V17: 10 | W17: =MODIFIER(ROUNDDOWN((V17-10)/2,0)) -> +0 | AA17: TRUE | AB17: FALSE | AC17: FALSE | AD17: FALSE | AE17: TRUE | AF17: FALSE | AG17: FALSE | AH17: FALSE | AJ17: FALSE | AK17: FALSE | AL17: FALSE | AM17: FALSE | AN17: FALSE | AO17: FALSE | AP17: FALSE | AQ17: FALSE | AT17: /
BA18: FALSE | BB18: Untrained Improv.
L19: CLASS DC | AA19: SAVING THROWS | AS19: PERCEPTION
M20: Total | P20: Base | R20: =BB6 -> Wis | T20: Prof. | U20: T | V20: E | W20: M | X20: L | AF20: Total | AI20: Con | AK20: Prof. | AL20: T | AM20: E | AN20: M | AO20: L | AQ20: Item | AS20: Total | AV20: Wis | AX20: Item | BA20: FALSE | BB20: W. Specialization
M21: =P21+R21+T21 -> 13 | O21: = | P21: 10 | Q21: + | R21: =vlookup(R20,Data!$B$14:$C$19,2,0) -> 0 | S21: + | T21: =if(X21,8+$AZ$13,if(W21,6+$AZ$13,if(V21,4+$AZ$13,if(U21,2+$AZ$13,0)))) -> 3 | U21: TRUE | V21: FALSE | W21: FALSE | X21: FALSE | AA21: Fortitude | AF21: =MODIFIER(AI21+AK21+AQ21) -> +3 | AH21: = | AI21: =vlookup(AI20,Data!$B$14:$C$19,2,0) -> 0 | AJ21: + | AK21: =if(AO21,8+Level,if(AN21,6+Level,if(AM21,4+Level,if(AL21,2+Level,0)))) -> 3 | AL21: TRUE | AM21: FALSE | AN21: FALSE | AO21: FALSE | AP21: + | AQ21: 0 | AS21: =MODIFIER(AT23+AV21+AX21) -> +3 | AU21: = | AV21: =vlookup(AV20,Data!$B$14:$C$19,2,0) -> 0 | AW21: + | AX21: 0
AF22: Total | AI22: Dex | AK22: Prof. | AL22: T | AM22: E | AN22: M | AO22: L | AQ22: Item | AT22: Prof. | AU22: T | AV22: E | AW22: M | AX22: L | BA22: FALSE | BB22: Fade Calculations
L23: SPEED | AA23: Reflex | AF23: =MODIFIER(AI23+AK23+AQ23) -> +3 | AH23: = | AI23: =vlookup(AI22,Data!$B$14:$C$19,2,0) -> 0 | AJ23: + | AK23: =if(AO23,8+$AZ$13,if(AN23,6+$AZ$13,if(AM23,4+$AZ$13,if(AL23,2+$AZ$13,0)))) -> 3 | AL23: TRUE | AM23: FALSE | AN23: FALSE | AO23: FALSE | AP23: + | AQ23: 0 | AS23: + | AT23: =if(AX23,8+$AZ$13,if(AW23,6+$AZ$13,if(AV23,4+$AZ$13,if(AU23,2+$AZ$13,0)))) -> 3 | AU23: TRUE | AV23: FALSE | AW23: FALSE | AX23: FALSE
M24: Speed | P24: Base | R24: Penalties | T24: Movement Types & Notes | AF24: Total | AI24: Wis | AK24: Prof. | AL24: T | AM24: E | AN24: M | AO24: L | AQ24: Item | AS24: Notes
M25: =P25-R25 -> 25 | O25: = | P25: 25 | Q25: – | R25: =ABS(if(Inventory!$Y$6>$O$13,Inventory!$V$6,max(Inventory!$V$6-5,0))) + ABS(Inventory!$P$12) -> 0 | AA25: Will | AF25: =MODIFIER(AI25+AK25+AQ25) -> +3 | AH25: = | AI25: =vlookup(AI24,Data!$B$14:$C$19,2,0) -> 0 | AJ25: + | AK25: =if(AO25,8+$AZ$13,if(AN25,6+$AZ$13,if(AM25,4+$AZ$13,if(AL25,2+$AZ$13,0)))) -> 3 | AL25: TRUE | AM25: FALSE | AN25: FALSE | AO25: FALSE | AP25: + | AQ25: 0 | AZ25: LANGUAGES
AZ26: Common (Taldane), [Racial, +1 for each INT mod]
B27: WEAPON PROFICIENCIES | AA27: SPELL ATTACK ROLL AND DC
B28: Simple/Unarmed | G28: Martial | AB28: Attack | AE28: =IF(OR($BB$6 = "Int", $BB$6 = "Wis"), $BB$6, "Cha") -> Wis | AG28: Prof. | AH28: T | AI28: E | AJ28: M | AK28: L | AM28: Item | AP28: DC | AS28: Base | AU28: =AE28 -> Wis | AW28: Prof.
B29: TRUE | C29: FALSE | D29: FALSE | E29: FALSE | G29: FALSE | H29: FALSE | I29: FALSE | J29: FALSE | L29: FALSE | M29: FALSE | N29: FALSE | O29: FALSE | Q29: FALSE | R29: FALSE | S29: FALSE | T29: FALSE | V29: FALSE | W29: FALSE | X29: FALSE | Y29: FALSE | AB29: =MODIFIER(AE29+AG29+AM29) -> +0 | AD29: = | AE29: =vlookup(AE28,Data!$B$14:$C$19,2,0) -> 0 | AF29: + | AG29: =if(AK29,8+$AZ$13,if(AJ29,6+$AZ$13,if(AI29,4+$AZ$13,if(AH29,2+$AZ$13,0)))) -> 0 | AH29: FALSE | AI29: FALSE | AJ29: FALSE | AK29: FALSE | AL29: + | AM29: 0 | AP29: =AS29+AU29+AW29 -> 10 | AR29: = | AS29: 10 | AT29: + | AU29: =vlookup(AU28,Data!$B$14:$C$19,2,0) -> 0 | AV29: + | AW29: =AG29 -> 0
B30: T | C30: E | D30: M | E30: L | G30: T | H30: E | I30: M | J30: L | L30: T | M30: E | N30: M | O30: L | Q30: T | R30: E | S30: M | T30: L | V30: T | W30: E | X30: M | Y30: L
B31: MELEE STRIKES | AA31: RANGED STRIKES
B32: Weapon | N32: Attack | Q32: =IF(K35,"Dex","Str") -> Str | S32: Prof. | T32: T | U32: E | V32: M | W32: L | Y32: Item | AA32: Weapon | AM32: Attack | AP32: Dex | AR32: Prof. | AS32: T | AT32: E | AU32: M | AV32: L | AX32: Item
N33: =MODIFIER(Q33+S33+Y33) -> +0 | P33: = | Q33: =vlookup(Q32,Data!$B$14:$C$19,2,0) -> 0 | R33: + | S33: =if(W33,8+$AZ$13,if(V33,6+$AZ$13,if(U33,4+$AZ$13,if(T33,2+$AZ$13,0)))) -> 0 | T33: FALSE | U33: FALSE | V33: FALSE | W33: FALSE | X33: + | Y33: 0 | AM33: =MODIFIER(AP33+AR33+AX33) -> +0 | AO33: = | AP33: =vlookup(AP32,Data!$B$14:$C$19,2,0) -> 0 | AQ33: + | AR33: =if(AV33,8+$AZ$13,if(AU33,6+$AZ$13,if(AT33,4+$AZ$13,if(AS33,2+$AZ$13,0)))) -> 0 | AS33: FALSE | AT33: FALSE | AU33: FALSE | AV33: FALSE | AW33: + | AX33: 0 | AZ33: STANDARD ACTIONS
K35: FALSE | L35: FALSE | N35: =MODIFIER(Q33+S33+Y33-ABS(Q35)) -> –5 | O35: =MODIFIER(Q33+S33+Y33-2*ABS(Q35)) -> –10 | Q35: =IF(L35,-4,-5) -> -5 | V35: + | W35: =vlookup(W36,Data!$B$14:$C$19,2,0) -> 0 | X35: + | Y35: =if($BA$20, if(W33,4, if(V33,3 ,if(U33,2, 0))), 0) -> 0 | AK35: FALSE | AM35: =MODIFIER(AP33+AR33+AX33-ABS(AP35)) -> –5 | AN35: =MODIFIER(AP33+AR33+AX33-2*ABS(AP35)) -> –10 | AP35: =IF(AK35,-4,-5) -> -5 | AU35: + | AV35: 0 | AW35: + | AX35: =if($BA$20, if(AV33,4, if(AU33,3 ,if(AT33,2, 0))), 0) -> 0 | AZ35: Stride (Movement)
B36: Traits | K36: Fin. | L36: Agile | N36: Additional | Q36: MAP | S36: Damage | W36: Str | Y36: W.Spec | AA36: Traits | AG36: Reload | AI36: Range | AK36: Agile | AM36: Additional | AP36: MAP | AR36: Damage | AV36: Misc. | AX36: W.Spec
AZ37: Step (5ft, no reactions)
B38: Weapon | N38: Attack | Q38: =IF(K41,"Dex","Str") -> Str | S38: Prof. | T38: T | U38: E | V38: M | W38: L | Y38: Item | AA38: Weapon | AM38: Attack | AP38: Dex | AR38: Prof. | AS38: T | AT38: E | AU38: M | AV38: L | AX38: Item
N39: =MODIFIER(Q39+S39+Y39) -> +0 | P39: = | Q39: =vlookup(Q38,Data!$B$14:$C$19,2,0) -> 0 | R39: + | S39: =if(W39,8+$AZ$13,if(V39,6+$AZ$13,if(U39,4+$AZ$13,if(T39,2+$AZ$13,0)))) -> 0 | T39: FALSE | U39: FALSE | V39: FALSE | W39: FALSE | X39: + | Y39: 0 | AM39: =MODIFIER(AP39+AR39+AX39) -> +0 | AO39: = | AP39: =vlookup(AP38,Data!$B$14:$C$19,2,0) -> 0 | AQ39: + | AR39: =if(AV39,8+$AZ$13,if(AU39,6+$AZ$13,if(AT39,4+$AZ$13,if(AS39,2+$AZ$13,0)))) -> 0 | AS39: FALSE | AT39: FALSE | AU39: FALSE | AV39: FALSE | AW39: + | AX39: 0 | AZ39: Strike (Attack)
K41: FALSE | L41: FALSE | N41: =MODIFIER(Q39+S39+Y39-ABS(Q41)) -> –5 | O41: =MODIFIER(Q39+S39+Y39-2*ABS(Q41)) -> –10 | Q41: =IF(L41,-4,-5) -> -5 | V41: + | W41: =vlookup(W42,Data!$B$14:$C$19,2,0) -> 0 | X41: + | Y41: =if($BA$20, if(W39,4, if(V39,3 ,if(U39,2, 0))), 0) -> 0 | AK41: FALSE | AM41: =MODIFIER(AP39+AR39+AX39-ABS(AP41)) -> –5 | AN41: =MODIFIER(AP39+AR39+AX39-2*ABS(AP41)) -> –10 | AP41: =IF(AK41,-4,-5) -> -5 | AU41: + | AV41: 0 | AW41: + | AX41: =if($BA$20, if(AV39,4, if(AU39,3 ,if(AT39,2, 0))), 0) -> 0 | AZ41: Cast a (Standard) Spell
B42: Traits | K42: Fin. | L42: Agile | N42: Additional | Q42: MAP | S42: Damage | W42: Str | Y42: W.Spec | AA42: Traits | AG42: Reload | AI42: Range | AK42: Agile | AM42: Additional | AP42: MAP | AR42: Damage | AV42: Misc. | AX42: W.Spec
AZ43: Raise Shield (AC bonus)
B44: Weapon | N44: Attack | Q44: =IF(K47,"Dex","Str") -> Str | S44: Prof. | T44: T | U44: E | V44: M | W44: L | Y44: Item | AA44: Weapon | AM44: Attack | AP44: Dex | AR44: Prof. | AS44: T | AT44: E | AU44: M | AV44: L | AX44: Item
N45: =MODIFIER(Q45+S45+Y45) -> +0 | P45: = | Q45: =vlookup(Q44,Data!$B$14:$C$19,2,0) -> 0 | R45: + | S45: =if(W45,8+$AZ$13,if(V45,6+$AZ$13,if(U45,4+$AZ$13,if(T45,2+$AZ$13,0)))) -> 0 | T45: FALSE | U45: FALSE | V45: FALSE | W45: FALSE | X45: + | Y45: 0 | AM45: =MODIFIER(AP45+AR45+AX45) -> +0 | AO45: = | AP45: =vlookup(AP44,Data!$B$14:$C$19,2,0) -> 0 | AQ45: + | AR45: =if(AV45,8+$AZ$13,if(AU45,6+$AZ$13,if(AT45,4+$AZ$13,if(AS45,2+$AZ$13,0)))) -> 0 | AS45: FALSE | AT45: FALSE | AU45: FALSE | AV45: FALSE | AW45: + | AX45: 0 | AZ45: Interact
K47: FALSE | L47: FALSE | N47: =MODIFIER(Q45+S45+Y45-ABS(Q47)) -> –5 | O47: =MODIFIER(Q45+S45+Y45-2*ABS(Q47)) -> –10 | Q47: =IF(L47,-4,-5) -> -5 | V47: + | W47: =vlookup(W48,Data!$B$14:$C$19,2,0) -> 0 | X47: + | Y47: =if($BA$20, if(W45,4, if(V45,3 ,if(U45,2, 0))), 0) -> 0 | AK47: FALSE | AM47: =MODIFIER(AP45+AR45+AX45-ABS(AP47)) -> –5 | AN47: =MODIFIER(AP45+AR45+AX45-2*ABS(AP47)) -> –10 | AP47: =IF(AK47,-4,-5) -> -5 | AU47: + | AV47: 0 | AW47: + | AX47: =if($BA$20, if(AV45,4, if(AU45,3 ,if(AT45,2, 0))), 0) -> 0 | AZ47: Delay (Hold Turn)
B48: Traits | K48: Fin. | L48: Agile | N48: Additional | Q48: MAP | S48: Damage | W48: Str | Y48: W.Spec | AA48: Traits | AG48: Reload | AI48: Range | AK48: Agile | AM48: Additional | AP48: MAP | AR48: Damage | AV48: Misc. | AX48: W.Spec
AZ49: Ready (Hold Action)
B51: ACTIONS, REACTIONS & ACTIVITIES
B52: Name | L52: Source / Notes | AF52: Resistance, Immunities, and Notes
B54: Description
B55: test
B58: Name | L58: Source / Notes | AF58: Name | AP58: Source / Notes
B60: Description | AF60: Description
B64: Name | L64: Source / Notes | AF64: Name | AP64: Source / Notes
B66: Description | AF66: Description
B70: Name | L70: Source / Notes | AF70: Name | AP70: Source / Notes
B72: Description | AF72: Description
B76: Name | L76: Source / Notes | AF76: Name | AP76: Source / Notes
B78: Description | AF78: Description

Sheet Abilities
A1: ABILITIES
B3: SKILLS
H4: Total | K4: Dex | M4: Prof. | N4: T | O4: E | P4: M | Q4: L | S4: Item | U4: Armor | W4: Feats | Y4: Feats listed | AM4: Item Being Used | AY4: FALSE | AZ4: Fade Calculations
C5: Acrobatics | H5: =MODIFIER(K5+M5+S5-U5+W5) -> +0 | J5: = | K5: =vlookup(K4,Data!$B$14:$C$19,2,0) -> 0 | L5: + | M5: =if(Q5,8+Level,if(P5,6+Level,if(O5,4+Level,if(N5,2+Level,IF('Character Sheet'!$BA$18,IF(Level>= 7, Level, ROUNDDOWN(Level/2,0)),0))))) -> 0 | N5: FALSE | O5: FALSE | P5: FALSE | Q5: FALSE | R5: + | S5: 0 | T5: – | U5: =ABS(if(Inventory!$Y$6>'Character Sheet'!$O$13,Inventory!$S$6,0)) -> 0 | V5: + | W5: 0
H6: Total | K6: Int | M6: Prof. | N6: T | O6: E | P6: M | Q6: L | S6: Item | W6: Feats | Y6: Feats listed | AM6: Item Being Used
C7: Arcana | H7: =MODIFIER(K7+M7+S7+W7) -> +0 | J7: = | K7: =vlookup(K6,Data!$B$14:$C$19,2,0) -> 0 | L7: + | M7: =if(Q7,8+Level,if(P7,6+Level,if(O7,4+Level,if(N7,2+Level,IF('Character Sheet'!$BA$18,IF(Level>= 7, Level, ROUNDDOWN(Level/2,0)),0))))) -> 0 | N7: FALSE | O7: FALSE | P7: FALSE | Q7: FALSE | R7: + | S7: 0 | U7: + | W7: 0 | AX7: SKILLS
H8: Total | K8: Str | M8: Prof. | N8: T | O8: E | P8: M | Q8: L | S8: Item | U8: Armor | W8: Feats | Y8: Feats listed | AM8: Item Being Used | AX8: 1st lv: [Class Bonus] + [Int Mod] for starting skills, each with a max of trained. On standard classes you gain more skill proficencies every other level 3rd lv: You can now put points into Expert ranked skills (if you are trained) 7th lv: You can now become a Master in a skill 15th lv: Legendary skill proficiencies are possible
C9: Athletics | H9: =MODIFIER(K9+M9+S9-U9+W9) -> +0 | J9: = | K9: =vlookup(K8,Data!$B$14:$C$19,2,0) -> 0 | L9: + | M9: =if(Q9,8+Level,if(P9,6+Level,if(O9,4+Level,if(N9,2+Level,IF('Character Sheet'!$BA$18,IF(Level>= 7, Level, ROUNDDOWN(Level/2,0)),0))))) -> 0 | N9: FALSE | O9: FALSE | P9: FALSE | Q9: FALSE | R9: + | S9: 0 | T9: – | U9: =ABS(if(Inventory!$Y$6>'Character Sheet'!$O$13,Inventory!$S$6,0)) -> 0 | V9: + | W9: 0
H10: Total | K10: Int | M10: Prof. | N10: T | O10: E | P10: M | Q10: L | S10: Item | W10: Feats | Y10: Feats listed | AM10: Item Being Used
C11: Crafting | H11: =MODIFIER(K11+M11+S11+W11) -> +0 | J11: = | K11: =vlookup(K10,Data!$B$14:$C$19,2,0) -> 0 | L11: + | M11: =if(Q11,8+Level,if(P11,6+Level,if(O11,4+Level,if(N11,2+Level,IF('Character Sheet'!$BA$18,IF(Level>= 7, Level, ROUNDDOWN(Level/2,0)),0))))) -> 0 | N11: FALSE | O11: FALSE | P11: FALSE | Q11: FALSE | R11: + | S11: 0 | U11: + | W11: 0
H12: Total | K12: Cha | M12: Prof. | N12: T | O12: E | P12: M | Q12: L | S12: Item | W12: Feats | Y12: Feats listed | AM12: Item Being Used
C13: Deception | H13: =MODIFIER(K13+M13+S13+W13) -> +0 | J13: = | K13: =vlookup(K12,Data!$B$14:$C$19,2,0) -> 0 | L13: + | M13: =if(Q13,8+Level,if(P13,6+Level,if(O13,4+Level,if(N13,2+Level,IF('Character Sheet'!$BA$18,IF(Level>= 7, Level, ROUNDDOWN(Level/2,0)),0))))) -> 0 | N13: FALSE | O13: FALSE | P13: FALSE | Q13: FALSE | R13: + | S13: 0 | U13: + | W13: 0
H14: Total | K14: Cha | M14: Prof. | N14: T | O14: E | P14: M | Q14: L | S14: Item | W14: Feats | Y14: Feats listed | AM14: Item Being Used
C15: Diplomacy | H15: =MODIFIER(K15+M15+S15+W15) -> +0 | J15: = | K15: =vlookup(K14,Data!$B$14:$C$19,2,0) -> 0 | L15: + | M15: =if(Q15,8+Level,if(P15,6+Level,if(O15,4+Level,if(N15,2+Level,IF('Character Sheet'!$BA$18,IF(Level>= 7, Level, ROUNDDOWN(Level/2,0)),0))))) -> 0 | N15: FALSE | O15: FALSE | P15: FALSE | Q15: FALSE | R15: + | S15: 0 | U15: + | W15: 0
H16: Total | K16: Cha | M16: Prof. | N16: T | O16: E | P16: M | Q16: L | S16: Item | W16: Feats | Y16: Feats listed | AM16: Item Being Used
C17: Intimidation | H17: =MODIFIER(K17+M17+S17+W17) -> +0 | J17: = | K17: =vlookup(K16,Data!$B$14:$C$19,2,0) -> 0 | L17: + | M17: =if(Q17,8+Level,if(P17,6+Level,if(O17,4+Level,if(N17,2+Level,IF('Character Sheet'!$BA$18,IF(Level>= 7, Level, ROUNDDOWN(Level/2,0)),0))))) -> 0 | N17: FALSE | O17: FALSE | P17: FALSE | Q17: FALSE | R17: + | S17: 0 | U17: + | W17: 0
H18: Total | K18: Int | M18: Prof. | N18: T | O18: E | P18: M | Q18: L | S18: Item | W18: Feats | Y18: Feats listed | AM18: Item Being Used
F19: Lore | H19: =MODIFIER(K19+M19+S19+W19) -> +0 | J19: = | K19: =vlookup(K18,Data!$B$14:$C$19,2,0) -> 0 | L19: + | M19: =if(Q19,8+Level,if(P19,6+Level,if(O19,4+Level,if(N19,2+Level,IF('Character Sheet'!$BA$18,IF(Level>= 7, Level, ROUNDDOWN(Level/2,0)),0))))) -> 0 | N19: FALSE | O19: FALSE | P19: FALSE | Q19: FALSE | R19: + | S19: 0 | U19: + | W19: 0
H20: Total | K20: Int | M20: Prof. | N20: T | O20: E | P20: M | Q20: L | S20: Item | W20: Feats | Y20: Feats listed | AM20: Item Being Used
F21: Lore | H21: =MODIFIER(K21+M21+S21+W21) -> +0 | J21: = | K21: =vlookup(K20,Data!$B$14:$C$19,2,0) -> 0 | L21: + | M21: =if(Q21,8+Level,if(P21,6+Level,if(O21,4+Level,if(N21,2+Level,IF('Character Sheet'!$BA$18,IF(Level>= 7, Level, ROUNDDOWN(Level/2,0)),0))))) -> 0 | N21: FALSE | O21: FALSE | P21: FALSE | Q21: FALSE | R21: + | S21: 0 | U21: + | W21: 0 | AX21: SIMPLE DC
H22: Total | K22: Int | M22: Prof. | N22: T | O22: E | P22: M | Q22: L | S22: Item | W22: Feats | Y22: Feats listed | AM22: Item Being Used
F23: Lore | H23: =MODIFIER(K23+M23+S23+W23) -> +0 | J23: = | K23: =vlookup(K22,Data!$B$14:$C$19,2,0) -> 0 | L23: + | M23: =if(Q23,8+Level,if(P23,6+Level,if(O23,4+Level,if(N23,2+Level,IF('Character Sheet'!$BA$18,IF(Level>= 7, Level, ROUNDDOWN(Level/2,0)),0))))) -> 0 | N23: FALSE | O23: FALSE | P23: FALSE | Q23: FALSE | R23: + | S23: 0 | U23: + | W23: 0
H24: Total | K24: Int | M24: Prof. | N24: T | O24: E | P24: M | Q24: L | S24: Item | W24: Feats | Y24: Feats listed | AM24: Item Being Used
F25: Lore | H25: =MODIFIER(K25+M25+S25+W25) -> +0 | J25: = | K25: =vlookup(K24,Data!$B$14:$C$19,2,0) -> 0 | L25: + | M25: =if(Q25,8+Level,if(P25,6+Level,if(O25,4+Level,if(N25,2+Level,IF('Character Sheet'!$BA$18,IF(Level>= 7, Level, ROUNDDOWN(Level/2,0)),0))))) -> 0 | N25: FALSE | O25: FALSE | P25: FALSE | Q25: FALSE | R25: + | S25: 0 | U25: + | W25: 0
H26: Total | K26: Wis | M26: Prof. | N26: T | O26: E | P26: M | Q26: L | S26: Item | W26: Feats | Y26: Feats listed | AM26: Item Being Used
C27: Medicine | H27: =MODIFIER(K27+M27+S27+W27) -> +0 | J27: = | K27: =vlookup(K26,Data!$B$14:$C$19,2,0) -> 0 | L27: + | M27: =if(Q27,8+Level,if(P27,6+Level,if(O27,4+Level,if(N27,2+Level,IF('Character Sheet'!$BA$18,IF(Level>= 7, Level, ROUNDDOWN(Level/2,0)),0))))) -> 0 | N27: FALSE | O27: FALSE | P27: FALSE | Q27: FALSE | R27: + | S27: 0 | U27: + | W27: 0
H28: Total | K28: Wis | M28: Prof. | N28: T | O28: E | P28: M | Q28: L | S28: Item | W28: Feats | Y28: Feats listed | AM28: Item Being Used
C29: Nature | H29: =MODIFIER(K29+M29+S29+W29) -> +0 | J29: = | K29: =vlookup(K28,Data!$B$14:$C$19,2,0) -> 0 | L29: + | M29: =if(Q29,8+Level,if(P29,6+Level,if(O29,4+Level,if(N29,2+Level,IF('Character Sheet'!$BA$18,IF(Level>= 7, Level, ROUNDDOWN(Level/2,0)),0))))) -> 0 | N29: FALSE | O29: FALSE | P29: FALSE | Q29: FALSE | R29: + | S29: 0 | U29: + | W29: 0
H30: Total | K30: Int | M30: Prof. | N30: T | O30: E | P30: M | Q30: L | S30: Item | W30: Feats | Y30: Feats listed | AM30: Item Being Used
C31: Occultism | H31: =MODIFIER(K31+M31+S31+W31) -> +0 | J31: = | K31: =vlookup(K30,Data!$B$14:$C$19,2,0) -> 0 | L31: + | M31: =if(Q31,8+Level,if(P31,6+Level,if(O31,4+Level,if(N31,2+Level,IF('Character Sheet'!$BA$18,IF(Level>= 7, Level, ROUNDDOWN(Level/2,0)),0))))) -> 0 | N31: FALSE | O31: FALSE | P31: FALSE | Q31: FALSE | R31: + | S31: 0 | U31: + | W31: 0
H32: Total | K32: Cha | M32: Prof. | N32: T | O32: E | P32: M | Q32: L | S32: Item | W32: Feats | Y32: Feats listed | AM32: Item Being Used
C33: Performance | H33: =MODIFIER(K33+M33+S33+W33) -> +0 | J33: = | K33: =vlookup(K32,Data!$B$14:$C$19,2,0) -> 0 | L33: + | M33: =if(Q33,8+Level,if(P33,6+Level,if(O33,4+Level,if(N33,2+Level,IF('Character Sheet'!$BA$18,IF(Level>= 7, Level, ROUNDDOWN(Level/2,0)),0))))) -> 0 | N33: FALSE | O33: FALSE | P33: FALSE | Q33: FALSE | R33: + | S33: 0 | U33: + | W33: 0 | AX33: SITUATIONAL
H34: Total | K34: Wis | M34: Prof. | N34: T | O34: E | P34: M | Q34: L | S34: Item | W34: Feats | Y34: Feats listed | AM34: Item Being Used | AX34: random effects to use as needed
C35: Religion | H35: =MODIFIER(K35+M35+S35+W35) -> +0 | J35: = | K35: =vlookup(K34,Data!$B$14:$C$19,2,0) -> 0 | L35: + | M35: =if(Q35,8+Level,if(P35,6+Level,if(O35,4+Level,if(N35,2+Level,IF('Character Sheet'!$BA$18,IF(Level>= 7, Level, ROUNDDOWN(Level/2,0)),0))))) -> 0 | N35: FALSE | O35: FALSE | P35: FALSE | Q35: FALSE | R35: + | S35: 0 | U35: + | W35: 0
H36: Total | K36: Int | M36: Prof. | N36: T | O36: E | P36: M | Q36: L | S36: Item | W36: Feats | Y36: Feats listed | AM36: Item Being Used
C37: Society | H37: =MODIFIER(K37+M37+S37+W37) -> +0 | J37: = | K37: =vlookup(K36,Data!$B$14:$C$19,2,0) -> 0 | L37: + | M37: =if(Q37,8+Level,if(P37,6+Level,if(O37,4+Level,if(N37,2+Level,IF('Character Sheet'!$BA$18,IF(Level>= 7, Level, ROUNDDOWN(Level/2,0)),0))))) -> 0 | N37: FALSE | O37: FALSE | P37: FALSE | Q37: FALSE | R37: + | S37: 0 | U37: + | W37: 0
H38: Total | K38: Dex | M38: Prof. | N38: T | O38: E | P38: M | Q38: L | S38: Item | U38: Armor | W38: Feats | Y38: Feats listed | AM38: Item Being Used
C39: Stealth | H39: =MODIFIER(K39+M39+S39-U39+W39) -> +0 | J39: = | K39: =vlookup(K38,Data!$B$14:$C$19,2,0) -> 0 | L39: + | M39: =if(Q39,8+Level,if(P39,6+Level,if(O39,4+Level,if(N39,2+Level,IF('Character Sheet'!$BA$18,IF(Level>= 7, Level, ROUNDDOWN(Level/2,0)),0))))) -> 0 | N39: FALSE | O39: FALSE | P39: FALSE | Q39: FALSE | R39: + | S39: 0 | T39: – | U39: =ABS(if(Inventory!$Y$6>'Character Sheet'!$O$13,Inventory!$S$6,0)) -> 0 | V39: + | W39: 0
H40: Total | K40: Wis | M40: Prof. | N40: T | O40: E | P40: M | Q40: L | S40: Item | W40: Feats | Y40: Feats listed | AM40: Item Being Used
C41: Survival | H41: =MODIFIER(K41+M41+S41+W41) -> +0 | J41: = | K41: =vlookup(K40,Data!$B$14:$C$19,2,0) -> 0 | L41: + | M41: =if(Q41,8+Level,if(P41,6+Level,if(O41,4+Level,if(N41,2+Level,IF('Character Sheet'!$BA$18,IF(Level>= 7, Level, ROUNDDOWN(Level/2,0)),0))))) -> 0 | N41: FALSE | O41: FALSE | P41: FALSE | Q41: FALSE | R41: + | S41: 0 | U41: + | W41: 0
H42: Total | K42: Dex | M42: Prof. | N42: T | O42: E | P42: M | Q42: L | S42: Item | U42: Armor | W42: Feats | Y42: Feats listed | AM42: Item Being Used
C43: Thievery | H43: =MODIFIER(K43+M43+S43-U43+W43) -> +0 | J43: = | K43: =vlookup(K42,Data!$B$14:$C$19,2,0) -> 0 | L43: + | M43: =if(Q43,8+Level,if(P43,6+Level,if(O43,4+Level,if(N43,2+Level,IF('Character Sheet'!$BA$18,IF(Level>= 7, Level, ROUNDDOWN(Level/2,0)),0))))) -> 0 | N43: FALSE | O43: FALSE | P43: FALSE | Q43: FALSE | R43: + | S43: 0 | T43: – | U43: =ABS(if(Inventory!$Y$6>'Character Sheet'!$O$13,Inventory!$S$6,0)) -> 0 | V43: + | W43: 0
B45: Note: Limited space; Please right click each box and make use of "Insert Note" ability for full description of ability and feat.
B47: ANCESTRY FEATS & ABILITIES | W47: CLASS FEATS & ABILITIES | AR47: SPECIAL ABILITIES
B48: Feat Name | R48: Special 1st | W48: Test | AM48: Feature 1st | AR48: Class Feature expanded
R50: Heritage 1st | AM50: Feature 1st
R52: Feat 1st | AM52: Feat 1st
R54: Feat 5th | AM54: Feat 2nd
R56: Feat 9th | AM56: Feature 3rd | AR56: Class Feature expanded
R58: Feat 13th | AM58: Feat 4th
R60: Feat 17th | AM60: Feature 5th
R62: Bonus | AM62: Feat 6th
R64: Bonus | AM64: Feature 7th
AR65: ROGUE EXTRA SKILL FEATS
B66: SKILL FEATS | AM66: Feat 8th | AR66: Rogue lv 1
R68: Background | AM68: Feature 9th | AR68: Rogue lv 3
R70: 2nd | AM70: Feat 10th | AR70: Rogue lv 5
R72: 4th | AM72: Feature 11th | AR72: Rogue lv 7
R74: 6th | AM74: Feat 12th | AR74: Rogue lv 9
R76: 8th | AM76: Feature 13th | AR76: Rogue lv 11
R78: 10th | AM78: Feat 14th | AR78: Rogue lv 13
R80: 12th | AM80: Feature 15th | AR80: Rogue lv 15
R82: 14th | AM82: Feat 16th | AR82: Rogue lv 17
R84: 16th | AM84: Feature 17th | AR84: Rogue lv 19
R86: 18th | AM86: Feat 18th
R88: 20th | AM88: Feature 19th
AR89: GENERAL VS SKILL FEATS
R90: Bonus | AM90: Feat 20th | AR90: Skill feats are obtained every even level, while general feats are obtained at 3rd lv and every 4 levels after. This means that general feats are rarer and tend towards stronger; however skill feats are a subcatagory of general feats so it is possible to take skill feats in place of general feats. Skill feats: Improve skill abilities by giving either new options, actions, or replacing parts of a skill. These tend to require proficency in the specific skill associated with it as a prerequisite. General Feats: Often more powerful feats with less prerequisites than skill feats
R92: Bonus | AM92: Bonus
R94: Bonus | AM94: Bonus
B99: GENERAL FEATS
R100: 3rd | AM100: 19th
R102: 7th | AM102: Bonus
R104: 11th | AM104: Bonus
R106: 15th | AM106: Bonus

Sheet Inventory
B2: INVENTORY
B4: ARMOR | AG4: OTHER INVENTORY | BH4: OTHER OTHER INVENTORY | CI4: Coin Bulk
B5: Item | M5: AC | P5: Dex Cap | S5: Check Pen | V5: Speed Pen | Y5: Str Req | AB5: Bulk | AE5: Invest | AG5: Weapon 1 | BA5: Qty | BC5: Bulk | BE5: Total Bulk | BH5: Adventurer's pack (max. 4 bulk, minus 2 bulk) | CF5: Total Bulk | CJ5: Standard Rules
B6: Padded armor | M6: 1 | P6: 3 | S6: 0 | V6: 0 | Y6: 10 | AB6: L | AE6: 0 | BB6: x | BC6: 1 | BD6: = | BE6: =IF(BC6="",0,IF(BA6="", CALCBULK(BC6), BA6*CALCBULK(BC6))) -> 1 | CF6: =MAX(SUM(CF8:CG38) - 2, 0) -> 0 | CJ6: 0
B7: Group | M7: Runes | P7: Armor Traits | AG7: Weapon 2 | BA7: Qty | BC7: Bulk | BE7: Total Bulk | BI7: Backpack, Bedroll, Belt pouch (2), Chalk (10), Flint/steel, Rope (50 ft), Rations (2 weeks), Soap, Torch (5), Waterskin | CB7: Qty | CD7: Bulk | CF7: Total Bulk | CJ7: Exact Wieght
B8: Light Armor | M8: 0 | BB8: x | BC8: 1 | BD8: = | BE8: =IF(BC8="",0,IF(BA8="", CALCBULK(BC8), BA8*CALCBULK(BC8))) -> 1 | CC8: x | CD8: 1 | CE8: = | CF8: =IF(CD8="",0,IF(CB8="", CALCBULK(CD8), CB8*CALCBULK(CD8))) -> 1 | CJ8: 0
AG9: Healer's/Alchemist's/Thieves' Tool | BA9: Qty | BC9: Bulk | BE9: Total Bulk | BI9: Climbing/Repair/Disguise/Snare kit | CB9: Qty | CD9: Bulk | CF9: Total Bulk | CJ9: Resulting Bulk
B10: SHIELD | BB10: x | BC10: 1 | BD10: = | BE10: =IF(BC10="",0,IF(BA10="", CALCBULK(BC10), BA10*CALCBULK(BC10))) -> 1 | CC10: x | CD10: 1 | CE10: = | CF10: =IF(CD10="",0,IF(CB10="", CALCBULK(CD10), CB10*CALCBULK(CD10))) -> 1 | CI10: =IFS(CJ8,(Sum(X16,X18,AB16,AB18)/1000),CJ6=1,ROUNDDOWN(SUM(X16,X18,AB16,AB18)/1000,0),CJ6=0, "0") -> 0
B11: Item | M11: AC | P11: Speed Pen | S11: Hardness | V11: Max HP | Y11: BT | AB11: Bulk | AE11: Invest | BA11: Qty | BC11: Bulk | BE11: Total Bulk | CB11: Qty | CD11: Bulk | CF11: Total Bulk
B12: Buckler | M12: 1 | P12: 0 | S12: 3 | V12: 6 | Y12: 3 | AB12: L | AE12: 0 | BB12: x | BC12: 0 | BD12: = | BE12: =IF(BC12="",0,IF(BA12="", CALCBULK(BC12), BA12*CALCBULK(BC12))) -> 0 | CC12: x | CD12: 0 | CE12: = | CF12: =IF(CD12="",0,IF(CB12="", CALCBULK(CD12), CB12*CALCBULK(CD12))) -> 0
BA13: Qty | BC13: Bulk | BE13: Total Bulk | CB13: Qty | CD13: Bulk | CF13: Total Bulk
B14: INVENTORY | BB14: x | BD14: = | BE14: =IF(BC14="",0,IF(BA14="", CALCBULK(BC14), BA14*CALCBULK(BC14))) -> 0 | CC14: x | CD14: 0 | CE14: = | CF14: =IF(CD14="",0,IF(CB14="", CALCBULK(CD14), CB14*CALCBULK(CD14))) -> 0
B15: Current Bulk | E15: Exact Bulk | I15: Invested | M15: Max | O15: Notes | X15: CP | AB15: GP | BA15: Qty | BC15: Bulk | BE15: Total Bulk | CB15: Qty | CD15: Bulk | CF15: Total Bulk
B16: =ROUNDDOWN(E16,0) -> 3 | E16: =SUM(CALCBULK(AB6,AB12),BE6:BE40,CF6,BE50)+Sum(AE26:AE54)+(IF(CC40,CF40))+CI10 -> 3.2 | I16: =SUM($I$26:$I$54,AE12,AE6) -> 1 | L16: / | M16: 10 | X16: 0 | AB16: 15 | BB16: x | BD16: = | BE16: =IF(BC16="",0,IF(BA16="", CALCBULK(BC16), BA16*CALCBULK(BC16))) -> 0 | CC16: x | CD16: 0 | CE16: = | CF16: =IF(CD16="",0,IF(CB16="", CALCBULK(CD16), CB16*CALCBULK(CD16))) -> 0
B17: Enc | D17: Max | F17: Base | I17: Str | K17: Bonus | M17: Item | X17: SP | AB17: PP | BA17: Qty | BC17: Bulk | BE17: Total Bulk | CB17: Qty | CD17: Bulk | CF17: Total Bulk
B18: =5+$I$18+$K$18+$M$18 -> 5 | C18: / | D18: =10+$I$18+$K$18+$M$18 -> 10 | E18: = | F18: 5 / 10 | H18: + | I18: =vlookup(I17,Data!$B$14:$C$19,2,0) -> 0 | J18: + | K18: 0 | L18: + | M18: 0 | X18: 0 | AB18: 0 | BB18: x | BD18: = | BE18: =IF(BC18="",0,IF(BA18="", CALCBULK(BC18), BA18*CALCBULK(BC18))) -> 0 | CC18: x | CD18: 0 | CE18: = | CF18: =IF(CD18="",0,IF(CB18="", CALCBULK(CD18), CB18*CALCBULK(CD18))) -> 0
BA19: Qty | BC19: Bulk | BE19: Total Bulk | CB19: Qty | CD19: Bulk | CF19: Total Bulk
B20: AMMUNITION | BB20: x | BD20: = | BE20: =IF(BC20="",0,IF(BA20="", CALCBULK(BC20), BA20*CALCBULK(BC20))) -> 0 | CC20: x | CD20: 0 | CE20: = | CF20: =IF(CD20="",0,IF(CB20="", CALCBULK(CD20), CB20*CALCBULK(CD20))) -> 0
B21: Arrows | F21: Frost Arrow | J21: Type 3 | N21: Type 4 | T21: Type 5 | Z21: Type 6 | AD21: Bulk | BA21: Qty | BC21: Bulk | BE21: Total Bulk | CB21: Qty | CD21: Bulk | CF21: Total Bulk
B22: 0 | F22: 0 | J22: 0 | N22: 0 | T22: 0 | Z22: 0 | AD22: =Sum(B22,F22,J22,N22,T22,Z22)*0.01 -> 0 | BB22: x | BD22: = | BE22: =IF(BC22="",0,IF(BA22="", CALCBULK(BC22), BA22*CALCBULK(BC22))) -> 0 | CC22: x | CD22: 0 | CE22: = | CF22: =IF(CD22="",0,IF(CB22="", CALCBULK(CD22), CB22*CALCBULK(CD22))) -> 0
BA23: Qty | BC23: Bulk | BE23: Total Bulk | CB23: Qty | CD23: Bulk | CF23: Total Bulk
B24: MAGIC ITEMS | BB24: x | BD24: = | BE24: =IF(BC24="",0,IF(BA24="", CALCBULK(BC24), BA24*CALCBULK(BC24))) -> 0 | CC24: x | CD24: 0 | CE24: = | CF24: =IF(CD24="",0,IF(CB24="", CALCBULK(CD24), CB24*CALCBULK(CD24))) -> 0
B25: Name | I25: Invest | L25: Description | AE25: Bulk | BA25: Qty | BC25: Bulk | BE25: Total Bulk | CB25: Qty | CD25: Bulk | CF25: Total Bulk
B26: Stick of Division | I26: 1 | K26: The most stick-like of sticks, has the powers of multiplication | AE26: 0 | BB26: x | BD26: = | BE26: =IF(BC26="",0,IF(BA26="", CALCBULK(BC26), BA26*CALCBULK(BC26))) -> 0 | CC26: x | CD26: 0 | CE26: = | CF26: =IF(CD26="",0,IF(CB26="", CALCBULK(CD26), CB26*CALCBULK(CD26))) -> 0
I27: 0 | AE27: Bulk | BA27: Qty | BC27: Bulk | BE27: Total Bulk | CB27: Qty | CD27: Bulk | CF27: Total Bulk
AE28: 0 | BB28: x | BD28: = | BE28: =IF(BC28="",0,IF(BA28="", CALCBULK(BC28), BA28*CALCBULK(BC28))) -> 0 | CC28: x | CD28: 0 | CE28: = | CF28: =IF(CD28="",0,IF(CB28="", CALCBULK(CD28), CB28*CALCBULK(CD28))) -> 0
I29: 0 | AE29: Bulk | BA29: Qty | BC29: Bulk | BE29: Total Bulk | CB29: Qty | CD29: Bulk | CF29: Total Bulk
BB30: x | BD30: = | BE30: =IF(BC30="",0,IF(BA30="", CALCBULK(BC30), BA30*CALCBULK(BC30))) -> 0 | CC30: x | CD30: 0 | CE30: = | CF30: =IF(CD30="",0,IF(CB30="", CALCBULK(CD30), CB30*CALCBULK(CD30))) -> 0
I31: 0 | AE31: Bulk | BA31: Qty | BC31: Bulk | BE31: Total Bulk | CB31: Qty | CD31: Bulk | CF31: Total Bulk
BB32: x | BD32: = | BE32: =IF(BC32="",0,IF(BA32="", CALCBULK(BC32), BA32*CALCBULK(BC32))) -> 0 | CC32: x | CD32: 0 | CE32: = | CF32: =IF(CD32="",0,IF(CB32="", CALCBULK(CD32), CB32*CALCBULK(CD32))) -> 0
I33: 0 | AE33: Bulk | BA33: Qty | BC33: Bulk | BE33: Total Bulk | CB33: Qty | CD33: Bulk | CF33: Total Bulk
BB34: x | BD34: = | BE34: =IF(BC34="",0,IF(BA34="", CALCBULK(BC34), BA34*CALCBULK(BC34))) -> 0 | CC34: x | CD34: 0 | CE34: = | CF34: =IF(CD34="",0,IF(CB34="", CALCBULK(CD34), CB34*CALCBULK(CD34))) -> 0
I35: 0 | AE35: Bulk | BA35: Qty | BC35: Bulk | BE35: Total Bulk | CB35: Qty | CD35: Bulk | CF35: Total Bulk
BB36: x | BD36: = | BE36: =IF(BC36="",0,IF(BA36="", CALCBULK(BC36), BA36*CALCBULK(BC36))) -> 0 | CC36: x | CD36: 0 | CE36: = | CF36: =IF(CD36="",0,IF(CB36="", CALCBULK(CD36), CB36*CALCBULK(CD36))) -> 0
I37: 0 | AE37: Bulk | BA37: Qty | BC37: Bulk | BE37: Total Bulk | CB37: Qty | CD37: Bulk | CF37: Total Bulk
BB38: x | BD38: = | BE38: =IF(BC38="",0,IF(BA38="", CALCBULK(BC38), BA38*CALCBULK(BC38))) -> 0 | CC38: x | CD38: 0 | CE38: = | CF38: =IF(CD38="",0,IF(CB38="", CALCBULK(CD38), CB38*CALCBULK(CD38))) -> 0
I39: 0 | AE39: Bulk | AG39: Bandolier (max. 8 items of light bulk) | BE39: Total Bulk | BH39: Special Container / Bag of Holding | CA39: Contribute Bulk? | CF39: Total Bulk
BE40: =SUM(BE42,BE44,BE46,BE48) -> 0 | CC40: 0 | CF40: =SUM(CF42:CF54) -> 0
I41: 0 | AE41: Bulk | BA41: Qty | BC41: Bulk | BE41: Total Bulk | CB41: Qty | CD41: Bulk | CF41: Total Bulk
BA42: 0 | BB42: x | BC42: L | BD42: = | BE42: =IF(BC42="",0,IF(BA42="", CALCBULK(BC42), BA42*CALCBULK(BC42))) -> 0 | CC42: x | CD42: 0 | CE42: = | CF42: =IF(CD42="",0,IF(CB42="", CALCBULK(CD42), CB42*CALCBULK(CD42))) -> 0
I43: 0 | AE43: Bulk | BA43: Qty | BC43: Bulk | BE43: Total Bulk | CB43: Qty | CD43: Bulk | CF43: Total Bulk
BA44: 0 | BB44: x | BC44: L | BD44: = | BE44: =IF(BC44="",0,IF(BA44="", CALCBULK(BC44), BA44*CALCBULK(BC44))) -> 0 | CC44: x | CD44: 0 | CE44: = | CF44: =IF(CD44="",0,IF(CB44="", CALCBULK(CD44), CB44*CALCBULK(CD44))) -> 0
I45: 0 | AE45: Bulk | BA45: Qty | BC45: Bulk | BE45: Total Bulk | CB45: Qty | CD45: Bulk | CF45: Total Bulk
BA46: 0 | BB46: x | BC46: L | BD46: = | BE46: =IF(BC46="",0,IF(BA46="", CALCBULK(BC46), BA46*CALCBULK(BC46))) -> 0 | CC46: x | CD46: 0 | CE46: = | CF46: =IF(CD46="",0,IF(CB46="", CALCBULK(CD46), CB46*CALCBULK(CD46))) -> 0
I47: 0 | AE47: Bulk | BA47: Qty | BC47: Bulk | BE47: Total Bulk | CB47: Qty | CD47: Bulk | CF47: Total Bulk
BA48: 0 | BB48: x | BC48: L | BD48: = | BE48: =IF(BC48="",0,IF(BA48="", CALCBULK(BC48), BA48*CALCBULK(BC48))) -> 0 | CC48: x | CD48: 0 | CE48: = | CF48: =IF(CD48="",0,IF(CB48="", CALCBULK(CD48), CB48*CALCBULK(CD48))) -> 0
I49: 0 | AE49: Bulk | AG49: Belt Pouch (max. 4 items of light bulk) | BE49: Total Bulk | CB49: Qty | CD49: Bulk | CF49: Total Bulk
BE50: =SUM(BE52,BE54) -> 0 | CC50: x | CD50: 0 | CE50: = | CF50: =IF(CD50="",0,IF(CB50="", CALCBULK(CD50), CB50*CALCBULK(CD50))) -> 0
I51: 0 | AE51: Bulk | BA51: Qty | BC51: Bulk | BE51: Total Bulk | CB51: Qty | CD51: Bulk | CF51: Total Bulk
BA52: 0 | BB52: x | BC52: L | BD52: = | BE52: =IF(BC52="",0,IF(BA52="", CALCBULK(BC52), BA52*CALCBULK(BC52))) -> 0 | CC52: x | CD52: 0 | CE52: = | CF52: =IF(CD52="",0,IF(CB52="", CALCBULK(CD52), CB52*CALCBULK(CD52))) -> 0
I53: 0 | AE53: Bulk | BA53: Qty | BC53: Bulk | BE53: Total Bulk | CB53: Qty | CD53: Bulk | CF53: Total Bulk
BA54: 0 | BB54: x | BC54: L | BD54: = | BE54: =IF(BC54="",0,IF(BA54="", CALCBULK(BC54), BA54*CALCBULK(BC54))) -> 0 | CC54: x | CD54: 0 | CE54: = | CF54: =IF(CD54="",0,IF(CB54="", CALCBULK(CD54), CB54*CALCBULK(CD54))) -> 0

Sheet Spells
B2: CASTER LEVEL | Caster Level | V2: CANTRIPS | Cantrip
B3: Level | F3: Caster Type: | S3: Cantrip | V3: Lv | X3: Lv+ | Z3: Actions | AC3: Name | AO3: Range | AR3: Target/Area | AY3: Save/Attack | BF3: Lv | BH3: Lv+ | BJ3: Actions | BM3: Name | BY3: Range | CB3: Target/Area | CI3: Save/Attack | CP3: Spell book and all known spells?
B4: =Level -> 1 | F4: Druid | S4: =Roundup(Level/2,0) -> 1 | V4: =IF(AC4="","",$S$4) -> 1 | X4: =IF(AC4="","",VLOOKUP(AC4,'Spell Database'!$A$2:$W$980,5,FALSE)) -> Y | Z4: =IF(AC4="","",VLOOKUP(AC4,'Spell Database'!$A$2:$W$980,6,FALSE)) | AC4: Acid Splash | AO4: =IF(AC4="","",VLOOKUP(AC4,'Spell Database'!$A$2:$W$980,8,FALSE)) -> 30ft | AR4: =IF(AC4="","",VLOOKUP(AC4,'Spell Database'!$A$2:$W$980,9,FALSE)) -> 1 creature | AY4: =IF(AC4="","",VLOOKUP(AC4,'Spell Database'!$A$2:$W$980,10,FALSE)) -> Attack | BF4: =IF(BM4="","",$S$4) | BH4: =IF(BM4="","",VLOOKUP(BM4,'Spell Database'!$A$2:$W$980,5,FALSE)) | BJ4: =IF(BM4="","",VLOOKUP(BM4,'Spell Database'!$A$2:$W$980,6,FALSE)) | BY4: =IF(BM4="","",VLOOKUP(BM4,'Spell Database'!$A$2:$W$980,8,FALSE)) | CB4: =IF(BM4="","",VLOOKUP(BM4,'Spell Database'!$A$2:$W$980,9,FALSE)) | CI4: =IF(BM4="","",VLOOKUP(BM4,'Spell Database'!$A$2:$W$980,10,FALSE))
V5: Type | X5: Rarity | Z5: Component | AC5: =IF(AC4="","",VLOOKUP(AC4,'Spell Database'!$A$2:$V$980, (IFs(V4=1,"13", V4=2,"14", V4=3,"15", V4=4,"16", V4=5,"17", V4=6,"18", V4=7,"19", V4=8,"20", V4=9,"21", V4=10,"22")),FALSE)) -> On hit deal 1d6 acid damage, plus 1 splash. On Crit target gains 1 persistent acid damage. | BF5: Type | BH5: Rarity | BJ5: Component | BM5: =IF(BM4="","",VLOOKUP(BM4,'Spell Database'!$A$2:$V$980, (IFs(BF4=1,"13", BF4=2,"14", BF4=3,"15", BF4=4,"16", BF4=5,"17", BF4=6,"18", BF4=7,"19", BF4=8,"20", BF4=9,"21", BF4=10,"22")),FALSE))
B6: Level | F6: Max | H6: Used | V6: =IF(AC4="","",VLOOKUP(AC4,'Spell Database'!$A$2:$W$980,12,FALSE)) -> C | X6: =IF(AC4="","",VLOOKUP(AC4,'Spell Database'!$A$2:$W$980,3,FALSE)) -> C | Z6: =IF(AC4="","",VLOOKUP(AC4,'Spell Database'!$A$2:$W$980,7,FALSE)) -> S,V | BF6: =IF(BM4="","",VLOOKUP(BM4,'Spell Database'!$A$2:$W$980,12,FALSE)) | BH6: =IF(BM4="","",VLOOKUP(BM4,'Spell Database'!$A$2:$W$980,3,FALSE)) | BJ6: =IF(BM4="","",VLOOKUP(BM4,'Spell Database'!$A$2:$W$980,7,FALSE))
K7: Types of Casters | V7: Duration | Z7: School | BF7: Duration | BJ7: School
B8: Cantrip | F8: =IF(F4="",0, SWITCH(F4,"Magus",VLOOKUP(Level,Data!E27:P46,2), "Summoner",VLOOKUP(Level,Data!E27:P46,2), "Sorcerer",VLOOKUP(Level,Data!E50:P69,2), "Psychic",VLOOKUP(Level,Data!E73:DR92,2), "Basic Spellcaster",VLOOKUP(Level,Data!R27:AC46,2),"Expert Spellcaster",VLOOKUP(Level,Data!R50:AC69,2), "Master Spellcaster",VLOOKUP(Level,Data!R73:AC92,2),VLOOKUP(Level,Data!E4:P23,2))) -> 5 | H8: X | K8: Spontanious: Flexible Spell slots | V8: =IF(AC4="","",VLOOKUP(AC4,'Spell Database'!$A$2:$W$980,11,FALSE)) -> Instant | Z8: =IF(AC4="","",VLOOKUP(AC4,'Spell Database'!$A$2:$W$980,4,FALSE)) -> Evo | BF8: =IF(BM4="","",VLOOKUP(BM4,'Spell Database'!$A$2:$W$980,11,FALSE)) | BJ8: =IF(BM4="","",VLOOKUP(BM4,'Spell Database'!$A$2:$W$980,4,FALSE))
K9: Bards, Oracle, Sorcerers | V9: Lv | X9: Lv+ | Z9: Actions | AC9: Name | AO9: Range | AR9: Target/Area | AY9: Save/Attack | BF9: Lv | BH9: Lv+ | BJ9: Actions | BM9: Name | BY9: Range | CB9: Target/Area | CI9: Save/Attack
B10: Focus | F10: 0 | H10: 0 | K10: Every spell you learn becomes an option to cast, but can only be changed out when you level up. Any spell can be cast by expending the spellslot, no preperation required. Cant overcast easily. | V10: =IF(AC10="","",$S$4) -> 1 | X10: =IF(AC10="","",VLOOKUP(AC10,'Spell Database'!$A$2:$W$980,5,FALSE)) -> Y | Z10: =IF(AC10="","",VLOOKUP(AC10,'Spell Database'!$A$2:$W$980,6,FALSE)) | AC10: Detect Magic | AO10: =IF(AC10="","",VLOOKUP(AC10,'Spell Database'!$A$2:$W$980,8,FALSE)) -> 30ft | AR10: =IF(AC10="","",VLOOKUP(AC10,'Spell Database'!$A$2:$W$980,9,FALSE)) -> N/A | AY10: =IF(AC10="","",VLOOKUP(AC10,'Spell Database'!$A$2:$W$980,10,FALSE)) -> N/A | BF10: =IF(BM10="","",$S$4) | BH10: =IF(BM10="","",VLOOKUP(BM10,'Spell Database'!$A$2:$W$980,5,FALSE)) | BJ10: =IF(BM10="","",VLOOKUP(BM10,'Spell Database'!$A$2:$W$980,6,FALSE)) | BY10: =IF(BM10="","",VLOOKUP(BM10,'Spell Database'!$A$2:$W$980,8,FALSE)) | CB10: =IF(BM10="","",VLOOKUP(BM10,'Spell Database'!$A$2:$W$980,9,FALSE)) | CI10: =IF(BM10="","",VLOOKUP(BM10,'Spell Database'!$A$2:$W$980,10,FALSE))
V11: Type | X11: Rarity | Z11: Component | AC11: =IF(AC10="","",VLOOKUP(AC10,'Spell Database'!$A$2:$V$980, (IFs(V10=1,"13", V10=2,"14", V10=3,"15", V10=4,"16", V10=5,"17", V10=6,"18", V10=7,"19", V10=8,"20", V10=9,"21", V10=10,"22")),FALSE)) -> Send out a pulse that registers the presence of magic, registering nothing beyond "presense of magic item." Freely magic items you already know about. Deceptive Illusion magic is detected only if it is a lower level than Detect Magic Spell (Invisibility spells register normally) | BF11: Type | BH11: Rarity | BJ11: Component | BM11: =IF(BM10="","",VLOOKUP(BM10,'Spell Database'!$A$2:$V$980, (IFs(BF10=1,"13", BF10=2,"14", BF10=3,"15", BF10=4,"16", BF10=5,"17", BF10=6,"18", BF10=7,"19", BF10=8,"20", BF10=9,"21", BF10=10,"22")),FALSE))
B12: 1st Lv | F12: =IF(F4="",0, SWITCH(F4,"Magus",VLOOKUP(Level,Data!E27:P46,3), "Summoner",VLOOKUP(Level,Data!E27:P46,3), "Sorcerer",VLOOKUP(Level,Data!E50:P69,3), "Psychic",VLOOKUP(Level,Data!E73:DR92,3), "Basic Spellcaster",VLOOKUP(Level,Data!R27:AC46,3),"Expert Spellcaster",VLOOKUP(Level,Data!R50:AC69,3), "Master Spellcaster",VLOOKUP(Level,Data!R73:AC92,3),VLOOKUP(Level,Data!E4:P23,3))) -> 2 | H12: =Sum(AK40,AK46,AK52,BX40,BX46,BX52) -> 0 | V12: =IF(AC10="","",VLOOKUP(AC10,'Spell Database'!$A$2:$W$980,12,FALSE)) -> C | X12: =IF(AC10="","",VLOOKUP(AC10,'Spell Database'!$A$2:$W$980,3,FALSE)) -> C | Z12: =IF(AC10="","",VLOOKUP(AC10,'Spell Database'!$A$2:$W$980,7,FALSE)) -> S,V | BF12: =IF(BM10="","",VLOOKUP(BM10,'Spell Database'!$A$2:$W$980,12,FALSE)) | BH12: =IF(BM10="","",VLOOKUP(BM10,'Spell Database'!$A$2:$W$980,3,FALSE)) | BJ12: =IF(BM10="","",VLOOKUP(BM10,'Spell Database'!$A$2:$W$980,7,FALSE))
V13: Duration | Z13: School | BF13: Duration | BJ13: School
B14: 2nd Lv | F14: =IF(F4="",0, SWITCH(F4,"Magus",VLOOKUP(Level,Data!E27:P46,4), "Summoner",VLOOKUP(Level,Data!E27:P46,4), "Sorcerer",VLOOKUP(Level,Data!E50:P69,4), "Psychic",VLOOKUP(Level,Data!E73:DR92,4), "Basic Spellcaster",VLOOKUP(Level,Data!R27:AC46,4),"Expert Spellcaster",VLOOKUP(Level,Data!R50:AC69,4), "Master Spellcaster",VLOOKUP(Level,Data!R73:AC92,4),VLOOKUP(Level,Data!E4:P23,4))) -> 0 | H14: =SUM(AK60,AK66,AK72,BX60,BX66,BX72) -> 0 | V14: =IF(AC10="","",VLOOKUP(AC10,'Spell Database'!$A$2:$W$980,11,FALSE)) -> Instant | Z14: =IF(AC10="","",VLOOKUP(AC10,'Spell Database'!$A$2:$W$980,4,FALSE)) -> Div | BF14: =IF(BM10="","",VLOOKUP(BM10,'Spell Database'!$A$2:$W$980,11,FALSE)) | BJ14: =IF(BM10="","",VLOOKUP(BM10,'Spell Database'!$A$2:$W$980,4,FALSE))
V15: Lv | X15: Lv+ | Z15: Actions | AC15: Name | AO15: Range | AR15: Target/Area | AY15: Save/Attack | BF15: Lv | BH15: Lv+ | BJ15: Actions | BM15: Name | BY15: Range | CB15: Target/Area | CI15: Save/Attack
B16: 3rd Lv | F16: =IF(F4="",0, SWITCH(F4,"Magus",VLOOKUP(Level,Data!E27:P46,5), "Summoner",VLOOKUP(Level,Data!E27:P46,5), "Sorcerer",VLOOKUP(Level,Data!E50:P69,5), "Psychic",VLOOKUP(Level,Data!E73:DR92,5), "Basic Spellcaster",VLOOKUP(Level,Data!R27:AC46,5),"Expert Spellcaster",VLOOKUP(Level,Data!R50:AC69,5), "Master Spellcaster",VLOOKUP(Level,Data!R73:AC92,5),VLOOKUP(Level,Data!E4:P23,5))) -> 0 | H16: =SUM(AK80,AK86,BX80,BX86) -> 0 | K16: Prepared: Flexible Spell knowledge | V16: =IF(AC16="","",$S$4) | X16: =IF(AC16="","",VLOOKUP(AC16,'Spell Database'!$A$2:$W$980,5,FALSE)) | Z16: =IF(AC16="","",VLOOKUP(AC16,'Spell Database'!$A$2:$W$980,6,FALSE)) | AO16: =IF(AC16="","",VLOOKUP(AC16,'Spell Database'!$A$2:$W$980,8,FALSE)) | AR16: =IF(AC16="","",VLOOKUP(AC16,'Spell Database'!$A$2:$W$980,9,FALSE)) | AY16: =IF(AC16="","",VLOOKUP(AC16,'Spell Database'!$A$2:$W$980,10,FALSE)) | BF16: =IF(BM16="","",$S$4) | BH16: =IF(BM16="","",VLOOKUP(BM16,'Spell Database'!$A$2:$W$980,5,FALSE)) | BJ16: =IF(BM16="","",VLOOKUP(BM16,'Spell Database'!$A$2:$W$980,6,FALSE)) | BY16: =IF(BM16="","",VLOOKUP(BM16,'Spell Database'!$A$2:$W$980,8,FALSE)) | CB16: =IF(BM16="","",VLOOKUP(BM16,'Spell Database'!$A$2:$W$980,9,FALSE)) | CI16: =IF(BM16="","",VLOOKUP(BM16,'Spell Database'!$A$2:$W$980,10,FALSE))
K17: Cleric, druid, wizard | V17: Type | X17: Rarity | Z17: Component | AC17: =IF(AC16="","",VLOOKUP(AC16,'Spell Database'!$A$2:$V$980, (IFs(V16=1,"13", V16=2,"14", V16=3,"15", V16=4,"16", V16=5,"17", V16=6,"18", V16=7,"19", V16=8,"20", V16=9,"21", V16=10,"22")),FALSE)) | BF17: Type | BH17: Rarity | BJ17: Component | BM17: =IF(BM16="","",VLOOKUP(BM16,'Spell Database'!$A$2:$V$980, (IFs(BF16=1,"13", BF16=2,"14", BF16=3,"15", BF16=4,"16", BF16=5,"17", BF16=6,"18", BF16=7,"19", BF16=8,"20", BF16=9,"21", BF16=10,"22")),FALSE))
B18: 4th Lv | F18: =IF(F4="",0, SWITCH(F4,"Magus",VLOOKUP(Level,Data!E27:P46,6), "Summoner",VLOOKUP(Level,Data!E27:P46,6), "Sorcerer",VLOOKUP(Level,Data!E50:P69,6), "Psychic",VLOOKUP(Level,Data!E73:DR92,6), "Basic Spellcaster",VLOOKUP(Level,Data!R27:AC46,6),"Expert Spellcaster",VLOOKUP(Level,Data!R50:AC69,6), "Master Spellcaster",VLOOKUP(Level,Data!R73:AC92,6),VLOOKUP(Level,Data!E4:P23,6))) -> 0 | H18: =SUM(AK94,AK100,BX94,BX100) -> 0 | K18: Every morning you prepare the spells you wish to cast that day, and the level you want to cast them at. You can only cast a spell as many times as you prepare it. | V18: =IF(AC16="","",VLOOKUP(AC16,'Spell Database'!$A$2:$W$980,12,FALSE)) | X18: =IF(AC16="","",VLOOKUP(AC16,'Spell Database'!$A$2:$W$980,3,FALSE)) | Z18: =IF(AC16="","",VLOOKUP(AC16,'Spell Database'!$A$2:$W$980,7,FALSE)) | BF18: =IF(BM16="","",VLOOKUP(BM16,'Spell Database'!$A$2:$W$980,12,FALSE)) | BH18: =IF(BM16="","",VLOOKUP(BM16,'Spell Database'!$A$2:$W$980,3,FALSE)) | BJ18: =IF(BM16="","",VLOOKUP(BM16,'Spell Database'!$A$2:$W$980,7,FALSE))
V19: Duration | Z19: School | BF19: Duration | BJ19: School
B20: 5th Lv | F20: =IF(F4="",0, SWITCH(F4,"Magus",VLOOKUP(Level,Data!E27:P46,7), "Summoner",VLOOKUP(Level,Data!E27:P46,7), "Sorcerer",VLOOKUP(Level,Data!E50:P69,7), "Psychic",VLOOKUP(Level,Data!E73:DR92,7), "Basic Spellcaster",VLOOKUP(Level,Data!R27:AC46,7),"Expert Spellcaster",VLOOKUP(Level,Data!R50:AC69,7), "Master Spellcaster",VLOOKUP(Level,Data!R73:AC92,7),VLOOKUP(Level,Data!E4:P23,7))) -> 0 | H20: =SUM(AK108,AK114,BX108,BX114,) -> 0 | V20: =IF(AC16="","",VLOOKUP(AC16,'Spell Database'!$A$2:$W$980,11,FALSE)) | Z20: =IF(AC16="","",VLOOKUP(AC16,'Spell Database'!$A$2:$W$980,4,FALSE)) | BF20: =IF(BM16="","",VLOOKUP(BM16,'Spell Database'!$A$2:$W$980,11,FALSE)) | BJ20: =IF(BM16="","",VLOOKUP(BM16,'Spell Database'!$A$2:$W$980,4,FALSE))
B22: 6th Lv | F22: =IF(F4="",0, SWITCH(F4,"Magus",VLOOKUP(Level,Data!E27:P46,8), "Summoner",VLOOKUP(Level,Data!E27:P46,8), "Sorcerer",VLOOKUP(Level,Data!E50:P69,8), "Psychic",VLOOKUP(Level,Data!E73:DR92,8), "Basic Spellcaster",VLOOKUP(Level,Data!R27:AC46,8),"Expert Spellcaster",VLOOKUP(Level,Data!R50:AC69,8), "Master Spellcaster",VLOOKUP(Level,Data!R73:AC92,8),VLOOKUP(Level,Data!E4:P23,8))) -> 0 | H22: =SUM(AK122,AK128,BX122,BX128) -> 0 | V22: FOCUS SPELLS AND EXTRA CANTRIPS | Cantrip
V23: Lv | X23: Lv+ | Z23: Actions | AC23: Name | AO23: Range | AR23: Target/Area | AY23: Save/Attack | BF23: Lv | BH23: Lv+ | BJ23: Actions | BM23: Name | BY23: Range | CB23: Target/Area | CI23: Save/Attack
B24: 7th Lv | F24: =IF(F4="",0, SWITCH(F4,"Magus",VLOOKUP(Level,Data!E27:P46,9), "Summoner",VLOOKUP(Level,Data!E27:P46,9), "Sorcerer",VLOOKUP(Level,Data!E50:P69,9), "Psychic",VLOOKUP(Level,Data!E73:DR92,9), "Basic Spellcaster",VLOOKUP(Level,Data!R27:AC46,9),"Expert Spellcaster",VLOOKUP(Level,Data!R50:AC69,9), "Master Spellcaster",VLOOKUP(Level,Data!R73:AC92,9),VLOOKUP(Level,Data!E4:P23,9))) -> 0 | H24: =SUM(AK136,AK142,BX136,BX142) -> 0 | V24: =IF(AC24="","",$S$4) | X24: =IF(AC24="","",VLOOKUP(AC24,'Spell Database'!$A$2:$W$980,5,FALSE)) | Z24: =IF(AC24="","",VLOOKUP(AC24,'Spell Database'!$A$2:$W$980,6,FALSE)) | AO24: =IF(AC24="","",VLOOKUP(AC24,'Spell Database'!$A$2:$W$980,8,FALSE)) | AR24: =IF(AC24="","",VLOOKUP(AC24,'Spell Database'!$A$2:$W$980,9,FALSE)) | AY24: =IF(AC24="","",VLOOKUP(AC24,'Spell Database'!$A$2:$W$980,10,FALSE)) | BF24: =IF(BM24="","",$S$4) | BH24: =IF(BM24="","",VLOOKUP(BM24,'Spell Database'!$A$2:$W$980,5,FALSE)) | BJ24: =IF(BM24="","",VLOOKUP(BM24,'Spell Database'!$A$2:$W$980,6,FALSE)) | BY24: =IF(BM24="","",VLOOKUP(BM24,'Spell Database'!$A$2:$W$980,8,FALSE)) | CB24: =IF(BM24="","",VLOOKUP(BM24,'Spell Database'!$A$2:$W$980,9,FALSE)) | CI24: =IF(BM24="","",VLOOKUP(BM24,'Spell Database'!$A$2:$W$980,10,FALSE))
V25: Type | X25: Rarity | Z25: Component | AC25: =IF(AC24="","",VLOOKUP(AC24,'Spell Database'!$A$2:$V$980, (IFs(V24=1,"13", V24=2,"14", V24=3,"15", V24=4,"16", V24=5,"17", V24=6,"18", V24=7,"19", V24=8,"20", V24=9,"21", V24=10,"22")),FALSE)) | BF25: Type | BH25: Rarity | BJ25: Component | BM25: =IF(BM24="","",VLOOKUP(BM24,'Spell Database'!$A$2:$V$980, (IFs(BF24=1,"13", BF24=2,"14", BF24=3,"15", BF24=4,"16", BF24=5,"17", BF24=6,"18", BF24=7,"19", BF24=8,"20", BF24=9,"21", BF24=10,"22")),FALSE))
B26: 8th Lv | F26: =IF(F4="",0, SWITCH(F4,"Magus",VLOOKUP(Level,Data!E27:P46,10), "Summoner",VLOOKUP(Level,Data!E27:P46,10), "Sorcerer",VLOOKUP(Level,Data!E50:P69,10), "Psychic",VLOOKUP(Level,Data!E73:DR92,10), "Basic Spellcaster",VLOOKUP(Level,Data!R27:AC46,10),"Expert Spellcaster",VLOOKUP(Level,Data!R50:AC69,10), "Master Spellcaster",VLOOKUP(Level,Data!R73:AC92,10),VLOOKUP(Level,Data!E4:P23,10))) -> 0 | H26: =SUM(AK150,AK156,BX150,BX156) -> 0 | V26: =IF(AC24="","",VLOOKUP(AC24,'Spell Database'!$A$2:$W$980,12,FALSE)) | X26: =IF(AC24="","",VLOOKUP(AC24,'Spell Database'!$A$2:$W$980,3,FALSE)) | Z26: =IF(AC24="","",VLOOKUP(AC24,'Spell Database'!$A$2:$W$980,7,FALSE)) | BF26: =IF(BM24="","",VLOOKUP(BM24,'Spell Database'!$A$2:$W$980,12,FALSE)) | BH26: =IF(BM24="","",VLOOKUP(BM24,'Spell Database'!$A$2:$W$980,3,FALSE)) | BJ26: =IF(BM24="","",VLOOKUP(BM24,'Spell Database'!$A$2:$W$980,7,FALSE))
V27: Duration | Z27: School | BF27: Duration | BJ27: School
B28: 9th Lv | F28: =IF(F4="",0, SWITCH(F4,"Magus",VLOOKUP(Level,Data!E27:P46,11), "Summoner",VLOOKUP(Level,Data!E27:P46,11), "Sorcerer",VLOOKUP(Level,Data!E50:P69,11), "Psychic",VLOOKUP(Level,Data!E73:DR92,11), "Basic Spellcaster",VLOOKUP(Level,Data!R27:AC46,11),"Expert Spellcaster",VLOOKUP(Level,Data!R50:AC69,11), "Master Spellcaster",VLOOKUP(Level,Data!R73:AC92,11),VLOOKUP(Level,Data!E4:P23,11))) -> 0 | H28: =SUM(AK164,AK170,BX164,BX170) -> 0 | V28: =IF(AC24="","",VLOOKUP(AC24,'Spell Database'!$A$2:$W$980,11,FALSE)) | Z28: =IF(AC24="","",VLOOKUP(AC24,'Spell Database'!$A$2:$W$980,4,FALSE)) | BF28: =IF(BM24="","",VLOOKUP(BM24,'Spell Database'!$A$2:$W$980,11,FALSE)) | BJ28: =IF(BM24="","",VLOOKUP(BM24,'Spell Database'!$A$2:$W$980,4,FALSE))
V29: Lv | X29: Lv+ | Z29: Actions | AC29: Name | AO29: Range | AR29: Target/Area | AY29: Save/Attack | BF29: Lv | BH29: Lv+ | BJ29: Actions | BM29: Name | BY29: Range | CB29: Target/Area | CI29: Save/Attack
B30: 10th Lv | F30: =IF(F4="",0, SWITCH(F4,"Magus",VLOOKUP(Level,Data!E27:P46,12), "Summoner",VLOOKUP(Level,Data!E27:P46,12), "Sorcerer",VLOOKUP(Level,Data!E50:P69,12), "Psychic",VLOOKUP(Level,Data!E73:DR92,12), "Basic Spellcaster",VLOOKUP(Level,Data!R27:AC46,12),"Expert Spellcaster",VLOOKUP(Level,Data!R50:AC69,12), "Master Spellcaster",VLOOKUP(Level,Data!R73:AC92,12),VLOOKUP(Level,Data!E4:P23,12))) -> 0 | H30: =SUM(AK178,BX178) -> 0 | V30: =IF(AC30="","",$S$4) | X30: =IF(AC30="","",VLOOKUP(AC30,'Spell Database'!$A$2:$W$980,5,FALSE)) | Z30: =IF(AC30="","",VLOOKUP(AC30,'Spell Database'!$A$2:$W$980,6,FALSE)) | AO30: =IF(AC30="","",VLOOKUP(AC30,'Spell Database'!$A$2:$W$980,8,FALSE)) | AR30: =IF(AC30="","",VLOOKUP(AC30,'Spell Database'!$A$2:$W$980,9,FALSE)) | AY30: =IF(AC30="","",VLOOKUP(AC30,'Spell Database'!$A$2:$W$980,10,FALSE)) | BF30: =IF(BM30="","",$S$4) | BH30: =IF(BM30="","",VLOOKUP(BM30,'Spell Database'!$A$2:$W$980,5,FALSE)) | BJ30: =IF(BM30="","",VLOOKUP(BM30,'Spell Database'!$A$2:$W$980,6,FALSE)) | BY30: =IF(BM30="","",VLOOKUP(BM30,'Spell Database'!$A$2:$W$980,8,FALSE)) | CB30: =IF(BM30="","",VLOOKUP(BM30,'Spell Database'!$A$2:$W$980,9,FALSE)) | CI30: =IF(BM30="","",VLOOKUP(BM30,'Spell Database'!$A$2:$W$980,10,FALSE))
V31: Type | X31: Rarity | Z31: Component | AC31: =IF(AC30="","",VLOOKUP(AC30,'Spell Database'!$A$2:$V$980, (IFs(V30=1,"13", V30=2,"14", V30=3,"15", V30=4,"16", V30=5,"17", V30=6,"18", V30=7,"19", V30=8,"20", V30=9,"21", V30=10,"22")),FALSE)) | BF31: Type | BH31: Rarity | BJ31: Component | BM31: =IF(BM30="","",VLOOKUP(BM30,'Spell Database'!$A$2:$V$980, (IFs(BF30=1,"13", BF30=2,"14", BF30=3,"15", BF30=4,"16", BF30=5,"17", BF30=6,"18", BF30=7,"19", BF30=8,"20", BF30=9,"21", BF30=10,"22")),FALSE))
V32: =IF(AC30="","",VLOOKUP(AC30,'Spell Database'!$A$2:$W$980,12,FALSE)) | X32: =IF(AC30="","",VLOOKUP(AC30,'Spell Database'!$A$2:$W$980,3,FALSE)) | Z32: =IF(AC30="","",VLOOKUP(AC30,'Spell Database'!$A$2:$W$980,7,FALSE)) | BF32: =IF(BM30="","",VLOOKUP(BM30,'Spell Database'!$A$2:$W$980,12,FALSE)) | BH32: =IF(BM30="","",VLOOKUP(BM30,'Spell Database'!$A$2:$W$980,3,FALSE)) | BJ32: =IF(BM30="","",VLOOKUP(BM30,'Spell Database'!$A$2:$W$980,7,FALSE))
D33: Long Rest | H33: FALSE | V33: Duration | Z33: School | BF33: Duration | BJ33: School
V34: =IF(AC30="","",VLOOKUP(AC30,'Spell Database'!$A$2:$W$980,11,FALSE)) | Z34: =IF(AC30="","",VLOOKUP(AC30,'Spell Database'!$A$2:$W$980,4,FALSE)) | BF34: =IF(BM30="","",VLOOKUP(BM30,'Spell Database'!$A$2:$W$980,11,FALSE)) | BJ34: =IF(BM30="","",VLOOKUP(BM30,'Spell Database'!$A$2:$W$980,4,FALSE))
H35: =IF(H33,true,"")
B36: 1st LEVEL SPELLS | CB36: MAGIC ITEM SPELLS
B37: Lv | D37: Lv+ | F37: Actions | I37: Name | U37: Range | X37: Target/Area | AE37: Save/Attack | AK37: Prepared | AO37: Lv | AQ37: Lv+ | AS37: Actions | AV37: Name | BH37: Range | BK37: Target/Area | BR37: Save/Attack | BX37: Prepared | CB37: Lv | CD37: Lv+ | CF37: Actions | CI37: Name | CS37: Range | CV37: Target/Area | DC37: Save/Attack | DH37: Item DC | DK37: Uses | DN37: Used
B38: =IF(I38="","",VLOOKUP(I38,'Spell Database'!$A$2:$W$980,2,FALSE)) -> 1 | D38: =IF(I38="","",VLOOKUP(I38,'Spell Database'!$A$2:$W$980,5,FALSE)) -> Y | F38: =IF(I38="","",VLOOKUP(I38,'Spell Database'!$A$2:$W$980,6,FALSE)) | I38: Animate Dead | U38: =IF(I38="","",VLOOKUP(I38,'Spell Database'!$A$2:$W$980,8,FALSE)) -> 30ft | X38: =IF(I38="","",VLOOKUP(I38,'Spell Database'!$A$2:$W$980,9,FALSE)) -> N/A | AE38: =IF(I38="","",VLOOKUP(I38,'Spell Database'!$A$2:$W$980,10,FALSE)) -> N/A | AO38: =IF(AV38="","",VLOOKUP(AV38,'Spell Database'!$A$2:$W$980,2,FALSE)) | AQ38: =IF(AV38="","",VLOOKUP(AV38,'Spell Database'!$A$2:$W$980,5,FALSE)) | AS38: =IF(AV38="","",VLOOKUP(AV38,'Spell Database'!$A$2:$W$980,6,FALSE)) | BH38: =IF(AV38="","",VLOOKUP(AV38,'Spell Database'!$A$2:$W$980,8,FALSE)) | BK38: =IF(AV38="","",VLOOKUP(AV38,'Spell Database'!$A$2:$W$980,9,FALSE)) | BR38: =IF(AV38="","",VLOOKUP(AV38,'Spell Database'!$A$2:$W$980,10,FALSE)) | CB38: =IF(CI38="","",VLOOKUP(CI38,'Spell Database'!$A$2:$W$980,2,FALSE)) | CD38: =IF(CI38="","",VLOOKUP(CI38,'Spell Database'!$A$2:$W$980,5,FALSE)) | CF38: =IF(CI38="","",VLOOKUP(CI38,'Spell Database'!$A$2:$W$980,6,FALSE)) | CS38: =IF(CI38="","",VLOOKUP(CI38,'Spell Database'!$A$2:$W$980,8,FALSE)) | CV38: =IF(CI38="","",VLOOKUP(CI38,'Spell Database'!$A$2:$W$980,9,FALSE)) | DC38: =IF(CI38="","",VLOOKUP(CI38,'Spell Database'!$A$2:$W$980,10,FALSE))
B39: Type | D39: Rarity | F39: Component | I39: =IF(I38="","",VLOOKUP(I38,'Spell Database'!$A$2:$V$980, (IFs(B38=1,"13", B38=2,"14", B38=3,"15", B38=4,"16", B38=5,"17", B38=6,"18", B38=7,"19", B38=8,"20", B38=9,"21", B38=10,"22")),FALSE)) -> You magically summon a corpse or skeleton filled with necromatic life. You summon an creature whose level is -1 with the undead trait. This creature gains the summoned trait. | AK39: Used | AO39: Type | AQ39: Rarity | AS39: Component | AV39: =IF(AV38="","",VLOOKUP(AV38,'Spell Database'!$A$2:$V$980, (IFs(AO38=1,"13", AO38=2,"14", AO38=3,"15", AO38=4,"16", AO38=5,"17", AO38=6,"18", AO38=7,"19", AO38=8,"20", AO38=9,"21", AO38=10,"22")),FALSE)) | BX39: Used | CB39: Type | CD39: Rarity | CF39: Component | CI39: =IF(CI38="","",VLOOKUP(CI38,'Spell Database'!$A$2:$V$980, (IFs(CB38=1,"13", CB38=2,"14", CB38=3,"15", CB38=4,"16", CB38=5,"17", CB38=6,"18", CB38=7,"19", CB38=8,"20", CB38=9,"21", CB38=10,"22")),FALSE)) | DK39: Source
B40: =IF(I38="","",VLOOKUP(I38,'Spell Database'!$A$2:$W$980,12,FALSE)) -> S | D40: =IF(I38="","",VLOOKUP(I38,'Spell Database'!$A$2:$W$980,3,FALSE)) -> C | F40: =IF(I38="","",VLOOKUP(I38,'Spell Database'!$A$2:$W$980,7,FALSE)) -> M,S,V | AK40: 0 | AO40: =IF(AV38="","",VLOOKUP(AV38,'Spell Database'!$A$2:$W$980,12,FALSE)) | AQ40: =IF(AV38="","",VLOOKUP(AV38,'Spell Database'!$A$2:$W$980,3,FALSE)) | AS40: =IF(AV38="","",VLOOKUP(AV38,'Spell Database'!$A$2:$W$980,7,FALSE)) | BX40: 0 | CB40: =IF(CI38="","",VLOOKUP(CI38,'Spell Database'!$A$2:$W$980,12,FALSE)) | CD40: =IF(CI38="","",VLOOKUP(CI38,'Spell Database'!$A$2:$W$980,3,FALSE)) | CF40: =IF(CI38="","",VLOOKUP(CI38,'Spell Database'!$A$2:$W$980,7,FALSE))
B41: Duration | F41: School | AO41: Duration | AS41: School | CB41: Duration | CF41: School
B42: =IF(I38="","",VLOOKUP(I38,'Spell Database'!$A$2:$W$980,11,FALSE)) -> [S] 1min | F42: =IF(I38="","",VLOOKUP(I38,'Spell Database'!$A$2:$W$980,4,FALSE)) -> Nec | AO42: =IF(AV38="","",VLOOKUP(AV38,'Spell Database'!$A$2:$W$980,11,FALSE)) | AS42: =IF(AV38="","",VLOOKUP(AV38,'Spell Database'!$A$2:$W$980,4,FALSE)) | CB42: =IF(CI38="","",VLOOKUP(CI38,'Spell Database'!$A$2:$W$980,11,FALSE)) | CF42: =IF(CI38="","",VLOOKUP(CI38,'Spell Database'!$A$2:$W$980,4,FALSE))
B43: Lv | D43: Lv+ | F43: Actions | I43: Name | U43: Range | X43: Target/Area | AE43: Save/Attack | AK43: Prepared | AO43: Lv | AQ43: Lv+ | AS43: Actions | AV43: Name | BH43: Range | BK43: Target/Area | BR43: Save/Attack | BX43: Prepared | CB43: Lv | CD43: Lv+ | CF43: Actions | CI43: Name | CS43: Range | CV43: Target/Area | DC43: Save/Attack | DH43: Item DC | DK43: Uses | DN43: Used
B44: =IF(I44="","",VLOOKUP(I44,'Spell Database'!$A$2:$W$980,2,FALSE)) | D44: =IF(I44="","",VLOOKUP(I44,'Spell Database'!$A$2:$W$980,5,FALSE)) | F44: =IF(I44="","",VLOOKUP(I44,'Spell Database'!$A$2:$W$980,6,FALSE)) | U44: =IF(I44="","",VLOOKUP(I44,'Spell Database'!$A$2:$W$980,8,FALSE)) | X44: =IF(I44="","",VLOOKUP(I44,'Spell Database'!$A$2:$W$980,9,FALSE)) | AE44: =IF(I44="","",VLOOKUP(I44,'Spell Database'!$A$2:$W$980,10,FALSE)) | AO44: =IF(AV44="","",VLOOKUP(AV44,'Spell Database'!$A$2:$W$980,2,FALSE)) | AQ44: =IF(AV44="","",VLOOKUP(AV44,'Spell Database'!$A$2:$W$980,5,FALSE)) | AS44: =IF(AV44="","",VLOOKUP(AV44,'Spell Database'!$A$2:$W$980,6,FALSE)) | BH44: =IF(AV44="","",VLOOKUP(AV44,'Spell Database'!$A$2:$W$980,8,FALSE)) | BK44: =IF(AV44="","",VLOOKUP(AV44,'Spell Database'!$A$2:$W$980,9,FALSE)) | BR44: =IF(AV44="","",VLOOKUP(AV44,'Spell Database'!$A$2:$W$980,10,FALSE)) | CB44: =IF(CI44="","",VLOOKUP(CI44,'Spell Database'!$A$2:$W$980,2,FALSE)) | CD44: =IF(CI44="","",VLOOKUP(CI44,'Spell Database'!$A$2:$W$980,5,FALSE)) | CF44: =IF(CI44="","",VLOOKUP(CI44,'Spell Database'!$A$2:$W$980,6,FALSE)) | CS44: =IF(CI44="","",VLOOKUP(CI44,'Spell Database'!$A$2:$W$980,8,FALSE)) | CV44: =IF(CI44="","",VLOOKUP(CI44,'Spell Database'!$A$2:$W$980,9,FALSE)) | DC44: =IF(CI44="","",VLOOKUP(CI44,'Spell Database'!$A$2:$W$980,10,FALSE))
B45: Type | D45: Rarity | F45: Component | I45: =IF(I44="","",VLOOKUP(I44,'Spell Database'!$A$2:$V$980, (IFs(B44=1,"13", B44=2,"14", B44=3,"15", B44=4,"16", B44=5,"17", B44=6,"18", B44=7,"19", B44=8,"20", B44=9,"21", B44=10,"22")),FALSE)) | AK45: Used | AO45: Type | AQ45: Rarity | AS45: Component | AV45: =IF(AV44="","",VLOOKUP(AV44,'Spell Database'!$A$2:$V$980, (IFs(AO44=1,"13", AO44=2,"14", AO44=3,"15", AO44=4,"16", AO44=5,"17", AO44=6,"18", AO44=7,"19", AO44=8,"20", AO44=9,"21", AO44=10,"22")),FALSE)) | BX45: Used | CB45: Type | CD45: Rarity | CF45: Component | CI45: =IF(CI44="","",VLOOKUP(CI44,'Spell Database'!$A$2:$V$980, (IFs(CB44=1,"13", CB44=2,"14", CB44=3,"15", CB44=4,"16", CB44=5,"17", CB44=6,"18", CB44=7,"19", CB44=8,"20", CB44=9,"21", CB44=10,"22")),FALSE)) | DK45: Source
B46: =IF(I44="","",VLOOKUP(I44,'Spell Database'!$A$2:$W$980,12,FALSE)) | D46: =IF(I44="","",VLOOKUP(I44,'Spell Database'!$A$2:$W$980,3,FALSE)) | F46: =IF(I44="","",VLOOKUP(I44,'Spell Database'!$A$2:$W$980,7,FALSE)) | AK46: 0 | AO46: =IF(AV44="","",VLOOKUP(AV44,'Spell Database'!$A$2:$W$980,12,FALSE)) | AQ46: =IF(AV44="","",VLOOKUP(AV44,'Spell Database'!$A$2:$W$980,3,FALSE)) | AS46: =IF(AV44="","",VLOOKUP(AV44,'Spell Database'!$A$2:$W$980,7,FALSE)) | BX46: 0 | CB46: =IF(CI44="","",VLOOKUP(CI44,'Spell Database'!$A$2:$W$980,12,FALSE)) | CD46: =IF(CI44="","",VLOOKUP(CI44,'Spell Database'!$A$2:$W$980,3,FALSE)) | CF46: =IF(CI44="","",VLOOKUP(CI44,'Spell Database'!$A$2:$W$980,7,FALSE))
B47: Duration | F47: School | AO47: Duration | AS47: School | CB47: Duration | CF47: School
B48: =IF(I44="","",VLOOKUP(I44,'Spell Database'!$A$2:$W$980,11,FALSE)) | F48: =IF(I44="","",VLOOKUP(I44,'Spell Database'!$A$2:$W$980,4,FALSE)) | AO48: =IF(AV44="","",VLOOKUP(AV44,'Spell Database'!$A$2:$W$980,11,FALSE)) | AS48: =IF(AV44="","",VLOOKUP(AV44,'Spell Database'!$A$2:$W$980,4,FALSE)) | CB48: =IF(CI44="","",VLOOKUP(CI44,'Spell Database'!$A$2:$W$980,11,FALSE)) | CF48: =IF(CI44="","",VLOOKUP(CI44,'Spell Database'!$A$2:$W$980,4,FALSE))
B49: Lv | D49: Lv+ | F49: Actions | I49: Name | U49: Range | X49: Target/Area | AE49: Save/Attack | AK49: Prepared | AO49: Lv | AQ49: Lv+ | AS49: Actions | AV49: Name | BH49: Range | BK49: Target/Area | BR49: Save/Attack | BX49: Prepared | CB49: Lv | CD49: Lv+ | CF49: Actions | CI49: Name | CS49: Range | CV49: Target/Area | DC49: Save/Attack | DH49: Item DC | DK49: Uses | DN49: Used
B50: =IF(I50="","",VLOOKUP(I50,'Spell Database'!$A$2:$W$980,2,FALSE)) | D50: =IF(I50="","",VLOOKUP(I50,'Spell Database'!$A$2:$W$980,5,FALSE)) | F50: =IF(I50="","",VLOOKUP(I50,'Spell Database'!$A$2:$W$980,6,FALSE)) | U50: =IF(I50="","",VLOOKUP(I50,'Spell Database'!$A$2:$W$980,8,FALSE)) | X50: =IF(I50="","",VLOOKUP(I50,'Spell Database'!$A$2:$W$980,9,FALSE)) | AE50: =IF(I50="","",VLOOKUP(I50,'Spell Database'!$A$2:$W$980,10,FALSE)) | AO50: =IF(AV50="","",VLOOKUP(AV50,'Spell Database'!$A$2:$W$980,2,FALSE)) | AQ50: =IF(AV50="","",VLOOKUP(AV50,'Spell Database'!$A$2:$W$980,5,FALSE)) | AS50: =IF(AV50="","",VLOOKUP(AV50,'Spell Database'!$A$2:$W$980,6,FALSE)) | BH50: =IF(AV50="","",VLOOKUP(AV50,'Spell Database'!$A$2:$W$980,8,FALSE)) | BK50: =IF(AV50="","",VLOOKUP(AV50,'Spell Database'!$A$2:$W$980,9,FALSE)) | BR50: =IF(AV50="","",VLOOKUP(AV50,'Spell Database'!$A$2:$W$980,10,FALSE)) | CB50: =IF(CI50="","",VLOOKUP(CI50,'Spell Database'!$A$2:$W$980,2,FALSE)) | CD50: =IF(CI50="","",VLOOKUP(CI50,'Spell Database'!$A$2:$W$980,5,FALSE)) | CF50: =IF(CI50="","",VLOOKUP(CI50,'Spell Database'!$A$2:$W$980,6,FALSE)) | CS50: =IF(CI50="","",VLOOKUP(CI50,'Spell Database'!$A$2:$W$980,8,FALSE)) | CV50: =IF(CI50="","",VLOOKUP(CI50,'Spell Database'!$A$2:$W$980,9,FALSE)) | DC50: =IF(CI50="","",VLOOKUP(CI50,'Spell Database'!$A$2:$W$980,10,FALSE))
B51: Type | D51: Rarity | F51: Component | I51: =IF(I50="","",VLOOKUP(I50,'Spell Database'!$A$2:$V$980, (IFs(B50=1,"13", B50=2,"14", B50=3,"15", B50=4,"16", B50=5,"17", B50=6,"18", B50=7,"19", B50=8,"20", B50=9,"21", B50=10,"22")),FALSE)) | AK51: Used | AO51: Type | AQ51: Rarity | AS51: Component | AV51: =IF(AV50="","",VLOOKUP(AV50,'Spell Database'!$A$2:$V$980, (IFs(AO50=1,"13", AO50=2,"14", AO50=3,"15", AO50=4,"16", AO50=5,"17", AO50=6,"18", AO50=7,"19", AO50=8,"20", AO50=9,"21", AO50=10,"22")),FALSE)) | BX51: Used | CB51: Type | CD51: Rarity | CF51: Component | CI51: =IF(CI50="","",VLOOKUP(CI50,'Spell Database'!$A$2:$V$980, (IFs(CB50=1,"13", CB50=2,"14", CB50=3,"15", CB50=4,"16", CB50=5,"17", CB50=6,"18", CB50=7,"19", CB50=8,"20", CB50=9,"21", CB50=10,"22")),FALSE)) | DK51: Source
B52: =IF(I50="","",VLOOKUP(I50,'Spell Database'!$A$2:$W$980,12,FALSE)) | D52: =IF(I50="","",VLOOKUP(I50,'Spell Database'!$A$2:$W$980,3,FALSE)) | F52: =IF(I50="","",VLOOKUP(I50,'Spell Database'!$A$2:$W$980,7,FALSE)) | AK52: 0 | AO52: =IF(AV50="","",VLOOKUP(AV50,'Spell Database'!$A$2:$W$980,12,FALSE)) | AQ52: =IF(AV50="","",VLOOKUP(AV50,'Spell Database'!$A$2:$W$980,3,FALSE)) | AS52: =IF(AV50="","",VLOOKUP(AV50,'Spell Database'!$A$2:$W$980,7,FALSE)) | BX52: 0 | CB52: =IF(CI50="","",VLOOKUP(CI50,'Spell Database'!$A$2:$W$980,12,FALSE)) | CD52: =IF(CI50="","",VLOOKUP(CI50,'Spell Database'!$A$2:$W$980,3,FALSE)) | CF52: =IF(CI50="","",VLOOKUP(CI50,'Spell Database'!$A$2:$W$980,7,FALSE))
B53: Duration | F53: School | AO53: Duration | AS53: School | CB53: Duration | CF53: School
B54: =IF(I50="","",VLOOKUP(I50,'Spell Database'!$A$2:$W$980,11,FALSE)) | F54: =IF(I50="","",VLOOKUP(I50,'Spell Database'!$A$2:$W$980,4,FALSE)) | AO54: =IF(AV50="","",VLOOKUP(AV50,'Spell Database'!$A$2:$W$980,11,FALSE)) | AS54: =IF(AV50="","",VLOOKUP(AV50,'Spell Database'!$A$2:$W$980,4,FALSE)) | CB54: =IF(CI50="","",VLOOKUP(CI50,'Spell Database'!$A$2:$W$980,11,FALSE)) | CF54: =IF(CI50="","",VLOOKUP(CI50,'Spell Database'!$A$2:$W$980,4,FALSE))
CB55: Lv | CD55: Lv+ | CF55: Actions | CI55: Name | CS55: Range | CV55: Target/Area | DC55: Save/Attack | DH55: Item DC | DK55: Uses | DN55: Used
B56: 2ND LEVEL SPELLS | CB56: =IF(CI56="","",VLOOKUP(CI56,'Spell Database'!$A$2:$W$980,2,FALSE)) | CD56: =IF(CI56="","",VLOOKUP(CI56,'Spell Database'!$A$2:$W$980,5,FALSE)) | CF56: =IF(CI56="","",VLOOKUP(CI56,'Spell Database'!$A$2:$W$980,6,FALSE)) | CS56: =IF(CI56="","",VLOOKUP(CI56,'Spell Database'!$A$2:$W$980,8,FALSE)) | CV56: =IF(CI56="","",VLOOKUP(CI56,'Spell Database'!$A$2:$W$980,9,FALSE)) | DC56: =IF(CI56="","",VLOOKUP(CI56,'Spell Database'!$A$2:$W$980,10,FALSE))
B57: Lv | D57: Lv+ | F57: Actions | I57: Name | U57: Range | X57: Target/Area | AE57: Save/Attack | AK57: Prepared | AO57: Lv | AQ57: Lv+ | AS57: Actions | AV57: Name | BH57: Range | BK57: Target/Area | BR57: Save/Attack | BX57: Prepared | CB57: Type | CD57: Rarity | CF57: Component | CI57: =IF(CI56="","",VLOOKUP(CI56,'Spell Database'!$A$2:$V$980, (IFs(CB56=1,"13", CB56=2,"14", CB56=3,"15", CB56=4,"16", CB56=5,"17", CB56=6,"18", CB56=7,"19", CB56=8,"20", CB56=9,"21", CB56=10,"22")),FALSE)) | DK57: Source
B58: =IF(I58="","",VLOOKUP(I58,'Spell Database'!$A$2:$W$980,2,FALSE)) | D58: =IF(I58="","",VLOOKUP(I58,'Spell Database'!$A$2:$W$980,5,FALSE)) | F58: =IF(I58="","",VLOOKUP(I58,'Spell Database'!$A$2:$W$980,6,FALSE)) | U58: =IF(I58="","",VLOOKUP(I58,'Spell Database'!$A$2:$W$980,8,FALSE)) | X58: =IF(I58="","",VLOOKUP(I58,'Spell Database'!$A$2:$W$980,9,FALSE)) | AE58: =IF(I58="","",VLOOKUP(I58,'Spell Database'!$A$2:$W$980,10,FALSE)) | AO58: =IF(AV58="","",VLOOKUP(AV58,'Spell Database'!$A$2:$W$980,2,FALSE)) | AQ58: =IF(AV58="","",VLOOKUP(AV58,'Spell Database'!$A$2:$W$980,5,FALSE)) | AS58: =IF(AV58="","",VLOOKUP(AV58,'Spell Database'!$A$2:$W$980,6,FALSE)) | BH58: =IF(AV58="","",VLOOKUP(AV58,'Spell Database'!$A$2:$W$980,8,FALSE)) | BK58: =IF(AV58="","",VLOOKUP(AV58,'Spell Database'!$A$2:$W$980,9,FALSE)) | BR58: =IF(AV58="","",VLOOKUP(AV58,'Spell Database'!$A$2:$W$980,10,FALSE)) | CB58: =IF(CI56="","",VLOOKUP(CI56,'Spell Database'!$A$2:$W$980,12,FALSE)) | CD58: =IF(CI56="","",VLOOKUP(CI56,'Spell Database'!$A$2:$W$980,3,FALSE)) | CF58: =IF(CI56="","",VLOOKUP(CI56,'Spell Database'!$A$2:$W$980,7,FALSE))
B59: Type | D59: Rarity | F59: Component | I59: =IF(I58="","",VLOOKUP(I58,'Spell Database'!$A$2:$V$980, (IFs(B58=1,"13", B58=2,"14", B58=3,"15", B58=4,"16", B58=5,"17", B58=6,"18", B58=7,"19", B58=8,"20", B58=9,"21", B58=10,"22")),FALSE)) | AK59: Used | AO59: Type | AQ59: Rarity | AS59: Component | AV59: =IF(AV58="","",VLOOKUP(AV58,'Spell Database'!$A$2:$V$980, (IFs(AO58=1,"13", AO58=2,"14", AO58=3,"15", AO58=4,"16", AO58=5,"17", AO58=6,"18", AO58=7,"19", AO58=8,"20", AO58=9,"21", AO58=10,"22")),FALSE)) | BX59: Used | CB59: Duration | CF59: School
B60: =IF(I58="","",VLOOKUP(I58,'Spell Database'!$A$2:$W$980,12,FALSE)) | D60: =IF(I58="","",VLOOKUP(I58,'Spell Database'!$A$2:$W$980,3,FALSE)) | F60: =IF(I58="","",VLOOKUP(I58,'Spell Database'!$A$2:$W$980,7,FALSE)) | AO60: =IF(AV58="","",VLOOKUP(AV58,'Spell Database'!$A$2:$W$980,12,FALSE)) | AQ60: =IF(AV58="","",VLOOKUP(AV58,'Spell Database'!$A$2:$W$980,3,FALSE)) | AS60: =IF(AV58="","",VLOOKUP(AV58,'Spell Database'!$A$2:$W$980,7,FALSE)) | CB60: =IF(CI56="","",VLOOKUP(CI56,'Spell Database'!$A$2:$W$980,11,FALSE)) | CF60: =IF(CI56="","",VLOOKUP(CI56,'Spell Database'!$A$2:$W$980,4,FALSE))
B61: Duration | F61: School | AO61: Duration | AS61: School | CB61: Lv | CD61: Lv+ | CF61: Actions | CI61: Name | CS61: Range | CV61: Target/Area | DC61: Save/Attack | DH61: Item DC | DK61: Uses | DN61: Used
B62: =IF(I58="","",VLOOKUP(I58,'Spell Database'!$A$2:$W$980,11,FALSE)) | F62: =IF(I58="","",VLOOKUP(I58,'Spell Database'!$A$2:$W$980,4,FALSE)) | AO62: =IF(AV58="","",VLOOKUP(AV58,'Spell Database'!$A$2:$W$980,11,FALSE)) | AS62: =IF(AV58="","",VLOOKUP(AV58,'Spell Database'!$A$2:$W$980,4,FALSE)) | CB62: =IF(CI62="","",VLOOKUP(CI62,'Spell Database'!$A$2:$W$980,2,FALSE)) | CD62: =IF(CI62="","",VLOOKUP(CI62,'Spell Database'!$A$2:$W$980,5,FALSE)) | CF62: =IF(CI62="","",VLOOKUP(CI62,'Spell Database'!$A$2:$W$980,6,FALSE)) | CS62: =IF(CI62="","",VLOOKUP(CI62,'Spell Database'!$A$2:$W$980,8,FALSE)) | CV62: =IF(CI62="","",VLOOKUP(CI62,'Spell Database'!$A$2:$W$980,9,FALSE)) | DC62: =IF(CI62="","",VLOOKUP(CI62,'Spell Database'!$A$2:$W$980,10,FALSE))
B63: Lv | D63: Lv+ | F63: Actions | I63: Name | U63: Range | X63: Target/Area | AE63: Save/Attack | AK63: Prepared | AO63: Lv | AQ63: Lv+ | AS63: Actions | AV63: Name | BH63: Range | BK63: Target/Area | BR63: Save/Attack | BX63: Prepared | CB63: Type | CD63: Rarity | CF63: Component | CI63: =IF(CI62="","",VLOOKUP(CI62,'Spell Database'!$A$2:$V$980, (IFs(CB62=1,"13", CB62=2,"14", CB62=3,"15", CB62=4,"16", CB62=5,"17", CB62=6,"18", CB62=7,"19", CB62=8,"20", CB62=9,"21", CB62=10,"22")),FALSE)) | DK63: Source
B64: =IF(I64="","",VLOOKUP(I64,'Spell Database'!$A$2:$W$980,2,FALSE)) | D64: =IF(I64="","",VLOOKUP(I64,'Spell Database'!$A$2:$W$980,5,FALSE)) | F64: =IF(I64="","",VLOOKUP(I64,'Spell Database'!$A$2:$W$980,6,FALSE)) | U64: =IF(I64="","",VLOOKUP(I64,'Spell Database'!$A$2:$W$980,8,FALSE)) | X64: =IF(I64="","",VLOOKUP(I64,'Spell Database'!$A$2:$W$980,9,FALSE)) | AE64: =IF(I64="","",VLOOKUP(I64,'Spell Database'!$A$2:$W$980,10,FALSE)) | AO64: =IF(AV64="","",VLOOKUP(AV64,'Spell Database'!$A$2:$W$980,2,FALSE)) | AQ64: =IF(AV64="","",VLOOKUP(AV64,'Spell Database'!$A$2:$W$980,5,FALSE)) | AS64: =IF(AV64="","",VLOOKUP(AV64,'Spell Database'!$A$2:$W$980,6,FALSE)) | BH64: =IF(AV64="","",VLOOKUP(AV64,'Spell Database'!$A$2:$W$980,8,FALSE)) | BK64: =IF(AV64="","",VLOOKUP(AV64,'Spell Database'!$A$2:$W$980,9,FALSE)) | BR64: =IF(AV64="","",VLOOKUP(AV64,'Spell Database'!$A$2:$W$980,10,FALSE)) | CB64: =IF(CI62="","",VLOOKUP(CI62,'Spell Database'!$A$2:$W$980,12,FALSE)) | CD64: =IF(CI62="","",VLOOKUP(CI62,'Spell Database'!$A$2:$W$980,3,FALSE)) | CF64: =IF(CI62="","",VLOOKUP(CI62,'Spell Database'!$A$2:$W$980,7,FALSE))
B65: Type | D65: Rarity | F65: Component | I65: =IF(I64="","",VLOOKUP(I64,'Spell Database'!$A$2:$V$980, (IFs(B64=1,"13", B64=2,"14", B64=3,"15", B64=4,"16", B64=5,"17", B64=6,"18", B64=7,"19", B64=8,"20", B64=9,"21", B64=10,"22")),FALSE)) | AK65: Used | AO65: Type | AQ65: Rarity | AS65: Component | AV65: =IF(AV64="","",VLOOKUP(AV64,'Spell Database'!$A$2:$V$980, (IFs(AO64=1,"13", AO64=2,"14", AO64=3,"15", AO64=4,"16", AO64=5,"17", AO64=6,"18", AO64=7,"19", AO64=8,"20", AO64=9,"21", AO64=10,"22")),FALSE)) | BX65: Used | CB65: Duration | CF65: School
B66: =IF(I64="","",VLOOKUP(I64,'Spell Database'!$A$2:$W$980,12,FALSE)) | D66: =IF(I64="","",VLOOKUP(I64,'Spell Database'!$A$2:$W$980,3,FALSE)) | F66: =IF(I64="","",VLOOKUP(I64,'Spell Database'!$A$2:$W$980,7,FALSE)) | AO66: =IF(AV64="","",VLOOKUP(AV64,'Spell Database'!$A$2:$W$980,12,FALSE)) | AQ66: =IF(AV64="","",VLOOKUP(AV64,'Spell Database'!$A$2:$W$980,3,FALSE)) | AS66: =IF(AV64="","",VLOOKUP(AV64,'Spell Database'!$A$2:$W$980,7,FALSE)) | CB66: =IF(CI62="","",VLOOKUP(CI62,'Spell Database'!$A$2:$W$980,11,FALSE)) | CF66: =IF(CI62="","",VLOOKUP(CI62,'Spell Database'!$A$2:$W$980,4,FALSE))
B67: Duration | F67: School | AO67: Duration | AS67: School | CB67: Lv | CD67: Lv+ | CF67: Actions | CI67: Name | CS67: Range | CV67: Target/Area | DC67: Save/Attack | DH67: Item DC | DK67: Uses | DN67: Used
B68: =IF(I64="","",VLOOKUP(I64,'Spell Database'!$A$2:$W$980,11,FALSE)) | F68: =IF(I64="","",VLOOKUP(I64,'Spell Database'!$A$2:$W$980,4,FALSE)) | AO68: =IF(AV64="","",VLOOKUP(AV64,'Spell Database'!$A$2:$W$980,11,FALSE)) | AS68: =IF(AV64="","",VLOOKUP(AV64,'Spell Database'!$A$2:$W$980,4,FALSE)) | CB68: =IF(CI68="","",VLOOKUP(CI68,'Spell Database'!$A$2:$W$980,2,FALSE)) | CD68: =IF(CI68="","",VLOOKUP(CI68,'Spell Database'!$A$2:$W$980,5,FALSE)) | CF68: =IF(CI68="","",VLOOKUP(CI68,'Spell Database'!$A$2:$W$980,6,FALSE)) | CS68: =IF(CI68="","",VLOOKUP(CI68,'Spell Database'!$A$2:$W$980,8,FALSE)) | CV68: =IF(CI68="","",VLOOKUP(CI68,'Spell Database'!$A$2:$W$980,9,FALSE)) | DC68: =IF(CI68="","",VLOOKUP(CI68,'Spell Database'!$A$2:$W$980,10,FALSE))
B69: Lv | D69: Lv+ | F69: Actions | I69: Name | U69: Range | X69: Target/Area | AE69: Save/Attack | AK69: Prepared | AO69: Lv | AQ69: Lv+ | AS69: Actions | AV69: Name | BH69: Range | BK69: Target/Area | BR69: Save/Attack | BX69: Prepared | CB69: Type | CD69: Rarity | CF69: Component | CI69: =IF(CI68="","",VLOOKUP(CI68,'Spell Database'!$A$2:$V$980, (IFs(CB68=1,"13", CB68=2,"14", CB68=3,"15", CB68=4,"16", CB68=5,"17", CB68=6,"18", CB68=7,"19", CB68=8,"20", CB68=9,"21", CB68=10,"22")),FALSE)) | DK69: Source
B70: =IF(I70="","",VLOOKUP(I70,'Spell Database'!$A$2:$W$980,2,FALSE)) | D70: =IF(I70="","",VLOOKUP(I70,'Spell Database'!$A$2:$W$980,5,FALSE)) | F70: =IF(I70="","",VLOOKUP(I70,'Spell Database'!$A$2:$W$980,6,FALSE)) | U70: =IF(I70="","",VLOOKUP(I70,'Spell Database'!$A$2:$W$980,8,FALSE)) | X70: =IF(I70="","",VLOOKUP(I70,'Spell Database'!$A$2:$W$980,9,FALSE)) | AE70: =IF(I70="","",VLOOKUP(I70,'Spell Database'!$A$2:$W$980,10,FALSE)) | AO70: =IF(AV70="","",VLOOKUP(AV70,'Spell Database'!$A$2:$W$980,2,FALSE)) | AQ70: =IF(AV70="","",VLOOKUP(AV70,'Spell Database'!$A$2:$W$980,5,FALSE)) | AS70: =IF(AV70="","",VLOOKUP(AV70,'Spell Database'!$A$2:$W$980,6,FALSE)) | BH70: =IF(AV70="","",VLOOKUP(AV70,'Spell Database'!$A$2:$W$980,8,FALSE)) | BK70: =IF(AV70="","",VLOOKUP(AV70,'Spell Database'!$A$2:$W$980,9,FALSE)) | BR70: =IF(AV70="","",VLOOKUP(AV70,'Spell Database'!$A$2:$W$980,10,FALSE)) | CB70: =IF(CI68="","",VLOOKUP(CI68,'Spell Database'!$A$2:$W$980,12,FALSE)) | CD70: =IF(CI68="","",VLOOKUP(CI68,'Spell Database'!$A$2:$W$980,3,FALSE)) | CF70: =IF(CI68="","",VLOOKUP(CI68,'Spell Database'!$A$2:$W$980,7,FALSE))
B71: Type | D71: Rarity | F71: Component | I71: =IF(I70="","",VLOOKUP(I70,'Spell Database'!$A$2:$V$980, (IFs(B70=1,"13", B70=2,"14", B70=3,"15", B70=4,"16", B70=5,"17", B70=6,"18", B70=7,"19", B70=8,"20", B70=9,"21", B70=10,"22")),FALSE)) | AK71: Used | AO71: Type | AQ71: Rarity | AS71: Component | AV71: =IF(AV70="","",VLOOKUP(AV70,'Spell Database'!$A$2:$V$980, (IFs(AO70=1,"13", AO70=2,"14", AO70=3,"15", AO70=4,"16", AO70=5,"17", AO70=6,"18", AO70=7,"19", AO70=8,"20", AO70=9,"21", AO70=10,"22")),FALSE)) | BX71: Used | CB71: Duration | CF71: School
B72: =IF(I70="","",VLOOKUP(I70,'Spell Database'!$A$2:$W$980,12,FALSE)) | D72: =IF(I70="","",VLOOKUP(I70,'Spell Database'!$A$2:$W$980,3,FALSE)) | F72: =IF(I70="","",VLOOKUP(I70,'Spell Database'!$A$2:$W$980,7,FALSE)) | AO72: =IF(AV70="","",VLOOKUP(AV70,'Spell Database'!$A$2:$W$980,12,FALSE)) | AQ72: =IF(AV70="","",VLOOKUP(AV70,'Spell Database'!$A$2:$W$980,3,FALSE)) | AS72: =IF(AV70="","",VLOOKUP(AV70,'Spell Database'!$A$2:$W$980,7,FALSE)) | CB72: =IF(CI68="","",VLOOKUP(CI68,'Spell Database'!$A$2:$W$980,11,FALSE)) | CF72: =IF(CI68="","",VLOOKUP(CI68,'Spell Database'!$A$2:$W$980,4,FALSE))
B73: Duration | F73: School | AO73: Duration | AS73: School | CB73: Lv | CD73: Lv+ | CF73: Actions | CI73: Name | CS73: Range | CV73: Target/Area | DC73: Save/Attack | DH73: Item DC | DK73: Uses | DN73: Used
B74: =IF(I70="","",VLOOKUP(I70,'Spell Database'!$A$2:$W$980,11,FALSE)) | F74: =IF(I70="","",VLOOKUP(I70,'Spell Database'!$A$2:$W$980,4,FALSE)) | AO74: =IF(AV70="","",VLOOKUP(AV70,'Spell Database'!$A$2:$W$980,11,FALSE)) | AS74: =IF(AV70="","",VLOOKUP(AV70,'Spell Database'!$A$2:$W$980,4,FALSE)) | CB74: =IF(CI74="","",VLOOKUP(CI74,'Spell Database'!$A$2:$W$980,2,FALSE)) | CD74: =IF(CI74="","",VLOOKUP(CI74,'Spell Database'!$A$2:$W$980,5,FALSE)) | CF74: =IF(CI74="","",VLOOKUP(CI74,'Spell Database'!$A$2:$W$980,6,FALSE)) | CS74: =IF(CI74="","",VLOOKUP(CI74,'Spell Database'!$A$2:$W$980,8,FALSE)) | CV74: =IF(CI74="","",VLOOKUP(CI74,'Spell Database'!$A$2:$W$980,9,FALSE)) | DC74: =IF(CI74="","",VLOOKUP(CI74,'Spell Database'!$A$2:$W$980,10,FALSE))
CB75: Type | CD75: Rarity | CF75: Component | CI75: =IF(CI74="","",VLOOKUP(CI74,'Spell Database'!$A$2:$V$980, (IFs(CB74=1,"13", CB74=2,"14", CB74=3,"15", CB74=4,"16", CB74=5,"17", CB74=6,"18", CB74=7,"19", CB74=8,"20", CB74=9,"21", CB74=10,"22")),FALSE)) | DK75: Source
B76: 3RD LEVEL SPELLS | CB76: =IF(CI74="","",VLOOKUP(CI74,'Spell Database'!$A$2:$W$980,12,FALSE)) | CD76: =IF(CI74="","",VLOOKUP(CI74,'Spell Database'!$A$2:$W$980,3,FALSE)) | CF76: =IF(CI74="","",VLOOKUP(CI74,'Spell Database'!$A$2:$W$980,7,FALSE))
B77: Lv | D77: Lv+ | F77: Actions | I77: Name | U77: Range | X77: Target/Area | AE77: Save/Attack | AK77: Prepared | AO77: Lv | AQ77: Lv+ | AS77: Actions | AV77: Name | BH77: Range | BK77: Target/Area | BR77: Save/Attack | BX77: Prepared | CB77: Duration | CF77: School
B78: =IF(I78="","",VLOOKUP(I78,'Spell Database'!$A$2:$W$980,2,FALSE)) | D78: =IF(I78="","",VLOOKUP(I78,'Spell Database'!$A$2:$W$980,5,FALSE)) | F78: =IF(I78="","",VLOOKUP(I78,'Spell Database'!$A$2:$W$980,6,FALSE)) | U78: =IF(I78="","",VLOOKUP(I78,'Spell Database'!$A$2:$W$980,8,FALSE)) | X78: =IF(I78="","",VLOOKUP(I78,'Spell Database'!$A$2:$W$980,9,FALSE)) | AE78: =IF(I78="","",VLOOKUP(I78,'Spell Database'!$A$2:$W$980,10,FALSE)) | AO78: =IF(AV78="","",VLOOKUP(AV78,'Spell Database'!$A$2:$W$980,2,FALSE)) | AQ78: =IF(AV78="","",VLOOKUP(AV78,'Spell Database'!$A$2:$W$980,5,FALSE)) | AS78: =IF(AV78="","",VLOOKUP(AV78,'Spell Database'!$A$2:$W$980,6,FALSE)) | BH78: =IF(AV78="","",VLOOKUP(AV78,'Spell Database'!$A$2:$W$980,8,FALSE)) | BK78: =IF(AV78="","",VLOOKUP(AV78,'Spell Database'!$A$2:$W$980,9,FALSE)) | BR78: =IF(AV78="","",VLOOKUP(AV78,'Spell Database'!$A$2:$W$980,10,FALSE)) | CB78: =IF(CI74="","",VLOOKUP(CI74,'Spell Database'!$A$2:$W$980,11,FALSE)) | CF78: =IF(CI74="","",VLOOKUP(CI74,'Spell Database'!$A$2:$W$980,4,FALSE))
B79: Type | D79: Rarity | F79: Component | I79: =IF(I78="","",VLOOKUP(I78,'Spell Database'!$A$2:$V$980, (IFs(B78=1,"13", B78=2,"14", B78=3,"15", B78=4,"16", B78=5,"17", B78=6,"18", B78=7,"19", B78=8,"20", B78=9,"21", B78=10,"22")),FALSE)) | AK79: Used | AO79: Type | AQ79: Rarity | AS79: Component | AV79: =IF(AV78="","",VLOOKUP(AV78,'Spell Database'!$A$2:$V$980, (IFs(AO78=1,"13", AO78=2,"14", AO78=3,"15", AO78=4,"16", AO78=5,"17", AO78=6,"18", AO78=7,"19", AO78=8,"20", AO78=9,"21", AO78=10,"22")),FALSE)) | BX79: Used | CB79: Lv | CD79: Lv+ | CF79: Actions | CI79: Name | CS79: Range | CV79: Target/Area | DC79: Save/Attack | DH79: Item DC | DK79: Uses | DN79: Used
B80: =IF(I78="","",VLOOKUP(I78,'Spell Database'!$A$2:$W$980,12,FALSE)) | D80: =IF(I78="","",VLOOKUP(I78,'Spell Database'!$A$2:$W$980,3,FALSE)) | F80: =IF(I78="","",VLOOKUP(I78,'Spell Database'!$A$2:$W$980,7,FALSE)) | AO80: =IF(AV78="","",VLOOKUP(AV78,'Spell Database'!$A$2:$W$980,12,FALSE)) | AQ80: =IF(AV78="","",VLOOKUP(AV78,'Spell Database'!$A$2:$W$980,3,FALSE)) | AS80: =IF(AV78="","",VLOOKUP(AV78,'Spell Database'!$A$2:$W$980,7,FALSE)) | CB80: =IF(CI80="","",VLOOKUP(CI80,'Spell Database'!$A$2:$W$980,2,FALSE)) | CD80: =IF(CI80="","",VLOOKUP(CI80,'Spell Database'!$A$2:$W$980,5,FALSE)) | CF80: =IF(CI80="","",VLOOKUP(CI80,'Spell Database'!$A$2:$W$980,6,FALSE)) | CS80: =IF(CI80="","",VLOOKUP(CI80,'Spell Database'!$A$2:$W$980,8,FALSE)) | CV80: =IF(CI80="","",VLOOKUP(CI80,'Spell Database'!$A$2:$W$980,9,FALSE)) | DC80: =IF(CI80="","",VLOOKUP(CI80,'Spell Database'!$A$2:$W$980,10,FALSE))
B81: Duration | F81: School | AO81: Duration | AS81: School | CB81: Type | CD81: Rarity | CF81: Component | CI81: =IF(CI80="","",VLOOKUP(CI80,'Spell Database'!$A$2:$V$980, (IFs(CB80=1,"13", CB80=2,"14", CB80=3,"15", CB80=4,"16", CB80=5,"17", CB80=6,"18", CB80=7,"19", CB80=8,"20", CB80=9,"21", CB80=10,"22")),FALSE)) | DK81: Source
B82: =IF(I78="","",VLOOKUP(I78,'Spell Database'!$A$2:$W$980,11,FALSE)) | F82: =IF(I78="","",VLOOKUP(I78,'Spell Database'!$A$2:$W$980,4,FALSE)) | AO82: =IF(AV78="","",VLOOKUP(AV78,'Spell Database'!$A$2:$W$980,11,FALSE)) | AS82: =IF(AV78="","",VLOOKUP(AV78,'Spell Database'!$A$2:$W$980,4,FALSE)) | CB82: =IF(CI80="","",VLOOKUP(CI80,'Spell Database'!$A$2:$W$980,12,FALSE)) | CD82: =IF(CI80="","",VLOOKUP(CI80,'Spell Database'!$A$2:$W$980,3,FALSE)) | CF82: =IF(CI80="","",VLOOKUP(CI80,'Spell Database'!$A$2:$W$980,7,FALSE))
B83: Lv | D83: Lv+ | F83: Actions | I83: Name | U83: Range | X83: Target/Area | AE83: Save/Attack | AK83: Prepared | AO83: Lv | AQ83: Lv+ | AS83: Actions | AV83: Name | BH83: Range | BK83: Target/Area | BR83: Save/Attack | BX83: Prepared | CB83: Duration | CF83: School
B84: =IF(I84="","",VLOOKUP(I84,'Spell Database'!$A$2:$W$980,2,FALSE)) | D84: =IF(I84="","",VLOOKUP(I84,'Spell Database'!$A$2:$W$980,5,FALSE)) | F84: =IF(I84="","",VLOOKUP(I84,'Spell Database'!$A$2:$W$980,6,FALSE)) | U84: =IF(I84="","",VLOOKUP(I84,'Spell Database'!$A$2:$W$980,8,FALSE)) | X84: =IF(I84="","",VLOOKUP(I84,'Spell Database'!$A$2:$W$980,9,FALSE)) | AE84: =IF(I84="","",VLOOKUP(I84,'Spell Database'!$A$2:$W$980,10,FALSE)) | AO84: =IF(AV84="","",VLOOKUP(AV84,'Spell Database'!$A$2:$W$980,2,FALSE)) | AQ84: =IF(AV84="","",VLOOKUP(AV84,'Spell Database'!$A$2:$W$980,5,FALSE)) | AS84: =IF(AV84="","",VLOOKUP(AV84,'Spell Database'!$A$2:$W$980,6,FALSE)) | BH84: =IF(AV84="","",VLOOKUP(AV84,'Spell Database'!$A$2:$W$980,8,FALSE)) | BK84: =IF(AV84="","",VLOOKUP(AV84,'Spell Database'!$A$2:$W$980,9,FALSE)) | BR84: =IF(AV84="","",VLOOKUP(AV84,'Spell Database'!$A$2:$W$980,10,FALSE)) | CB84: =IF(CI80="","",VLOOKUP(CI80,'Spell Database'!$A$2:$W$980,11,FALSE)) | CF84: =IF(CI80="","",VLOOKUP(CI80,'Spell Database'!$A$2:$W$980,4,FALSE))
B85: Type | D85: Rarity | F85: Component | I85: =IF(I84="","",VLOOKUP(I84,'Spell Database'!$A$2:$V$980, (IFs(B84=1,"13", B84=2,"14", B84=3,"15", B84=4,"16", B84=5,"17", B84=6,"18", B84=7,"19", B84=8,"20", B84=9,"21", B84=10,"22")),FALSE)) | AK85: Used | AO85: Type | AQ85: Rarity | AS85: Component | AV85: =IF(AV84="","",VLOOKUP(AV84,'Spell Database'!$A$2:$V$980, (IFs(AO84=1,"13", AO84=2,"14", AO84=3,"15", AO84=4,"16", AO84=5,"17", AO84=6,"18", AO84=7,"19", AO84=8,"20", AO84=9,"21", AO84=10,"22")),FALSE)) | BX85: Used | CB85: Lv | CD85: Lv+ | CF85: Actions | CI85: Name | CS85: Range | CV85: Target/Area | DC85: Save/Attack | DH85: Item DC | DK85: Uses | DN85: Used
B86: =IF(I84="","",VLOOKUP(I84,'Spell Database'!$A$2:$W$980,12,FALSE)) | D86: =IF(I84="","",VLOOKUP(I84,'Spell Database'!$A$2:$W$980,3,FALSE)) | F86: =IF(I84="","",VLOOKUP(I84,'Spell Database'!$A$2:$W$980,7,FALSE)) | AO86: =IF(AV84="","",VLOOKUP(AV84,'Spell Database'!$A$2:$W$980,12,FALSE)) | AQ86: =IF(AV84="","",VLOOKUP(AV84,'Spell Database'!$A$2:$W$980,3,FALSE)) | AS86: =IF(AV84="","",VLOOKUP(AV84,'Spell Database'!$A$2:$W$980,7,FALSE)) | CB86: =IF(CI86="","",VLOOKUP(CI86,'Spell Database'!$A$2:$W$980,2,FALSE)) | CD86: =IF(CI86="","",VLOOKUP(CI86,'Spell Database'!$A$2:$W$980,5,FALSE)) | CF86: =IF(CI86="","",VLOOKUP(CI86,'Spell Database'!$A$2:$W$980,6,FALSE)) | CS86: =IF(CI86="","",VLOOKUP(CI86,'Spell Database'!$A$2:$W$980,8,FALSE)) | CV86: =IF(CI86="","",VLOOKUP(CI86,'Spell Database'!$A$2:$W$980,9,FALSE)) | DC86: =IF(CI86="","",VLOOKUP(CI86,'Spell Database'!$A$2:$W$980,10,FALSE))
B87: Duration | F87: School | AO87: Duration | AS87: School | CB87: Type | CD87: Rarity | CF87: Component | CI87: =IF(CI86="","",VLOOKUP(CI86,'Spell Database'!$A$2:$V$980, (IFs(CB86=1,"13", CB86=2,"14", CB86=3,"15", CB86=4,"16", CB86=5,"17", CB86=6,"18", CB86=7,"19", CB86=8,"20", CB86=9,"21", CB86=10,"22")),FALSE)) | DK87: Source
B88: =IF(I84="","",VLOOKUP(I84,'Spell Database'!$A$2:$W$980,11,FALSE)) | F88: =IF(I84="","",VLOOKUP(I84,'Spell Database'!$A$2:$W$980,4,FALSE)) | AO88: =IF(AV84="","",VLOOKUP(AV84,'Spell Database'!$A$2:$W$980,11,FALSE)) | AS88: =IF(AV84="","",VLOOKUP(AV84,'Spell Database'!$A$2:$W$980,4,FALSE)) | CB88: =IF(CI86="","",VLOOKUP(CI86,'Spell Database'!$A$2:$W$980,12,FALSE)) | CD88: =IF(CI86="","",VLOOKUP(CI86,'Spell Database'!$A$2:$W$980,3,FALSE)) | CF88: =IF(CI86="","",VLOOKUP(CI86,'Spell Database'!$A$2:$W$980,7,FALSE))
CB89: Duration | CF89: School
B90: 4TH LEVEL SPELLS | CB90: =IF(CI86="","",VLOOKUP(CI86,'Spell Database'!$A$2:$W$980,11,FALSE)) | CF90: =IF(CI86="","",VLOOKUP(CI86,'Spell Database'!$A$2:$W$980,4,FALSE))
B91: Lv | D91: Lv+ | F91: Actions | I91: Name | U91: Range | X91: Target/Area | AE91: Save/Attack | AK91: Prepared | AO91: Lv | AQ91: Lv+ | AS91: Actions | AV91: Name | BH91: Range | BK91: Target/Area | BR91: Save/Attack | BX91: Prepared | CB91: Lv | CD91: Lv+ | CF91: Actions | CI91: Name | CS91: Range | CV91: Target/Area | DC91: Save/Attack | DH91: Item DC | DK91: Uses | DN91: Used
B92: =IF(I92="","",VLOOKUP(I92,'Spell Database'!$A$2:$W$980,2,FALSE)) | D92: =IF(I92="","",VLOOKUP(I92,'Spell Database'!$A$2:$W$980,5,FALSE)) | F92: =IF(I92="","",VLOOKUP(I92,'Spell Database'!$A$2:$W$980,6,FALSE)) | U92: =IF(I92="","",VLOOKUP(I92,'Spell Database'!$A$2:$W$980,8,FALSE)) | X92: =IF(I92="","",VLOOKUP(I92,'Spell Database'!$A$2:$W$980,9,FALSE)) | AE92: =IF(I92="","",VLOOKUP(I92,'Spell Database'!$A$2:$W$980,10,FALSE)) | AO92: =IF(AV92="","",VLOOKUP(AV92,'Spell Database'!$A$2:$W$980,2,FALSE)) | AQ92: =IF(AV92="","",VLOOKUP(AV92,'Spell Database'!$A$2:$W$980,5,FALSE)) | AS92: =IF(AV92="","",VLOOKUP(AV92,'Spell Database'!$A$2:$W$980,6,FALSE)) | BH92: =IF(AV92="","",VLOOKUP(AV92,'Spell Database'!$A$2:$W$980,8,FALSE)) | BK92: =IF(AV92="","",VLOOKUP(AV92,'Spell Database'!$A$2:$W$980,9,FALSE)) | BR92: =IF(AV92="","",VLOOKUP(AV92,'Spell Database'!$A$2:$W$980,10,FALSE)) | CB92: =IF(CI92="","",VLOOKUP(CI92,'Spell Database'!$A$2:$W$980,2,FALSE)) | CD92: =IF(CI92="","",VLOOKUP(CI92,'Spell Database'!$A$2:$W$980,5,FALSE)) | CF92: =IF(CI92="","",VLOOKUP(CI92,'Spell Database'!$A$2:$W$980,6,FALSE)) | CS92: =IF(CI92="","",VLOOKUP(CI92,'Spell Database'!$A$2:$W$980,8,FALSE)) | CV92: =IF(CI92="","",VLOOKUP(CI92,'Spell Database'!$A$2:$W$980,9,FALSE)) | DC92: =IF(CI92="","",VLOOKUP(CI92,'Spell Database'!$A$2:$W$980,10,FALSE))
B93: Type | D93: Rarity | F93: Component | I93: =IF(I92="","",VLOOKUP(I92,'Spell Database'!$A$2:$V$980, (IFs(B92=1,"13", B92=2,"14", B92=3,"15", B92=4,"16", B92=5,"17", B92=6,"18", B92=7,"19", B92=8,"20", B92=9,"21", B92=10,"22")),FALSE)) | AK93: Used | AO93: Type | AQ93: Rarity | AS93: Component | AV93: =IF(AV92="","",VLOOKUP(AV92,'Spell Database'!$A$2:$V$980, (IFs(AO92=1,"13", AO92=2,"14", AO92=3,"15", AO92=4,"16", AO92=5,"17", AO92=6,"18", AO92=7,"19", AO92=8,"20", AO92=9,"21", AO92=10,"22")),FALSE)) | BX93: Used | CB93: Type | CD93: Rarity | CF93: Component | CI93: =IF(CI92="","",VLOOKUP(CI92,'Spell Database'!$A$2:$V$980, (IFs(CB92=1,"13", CB92=2,"14", CB92=3,"15", CB92=4,"16", CB92=5,"17", CB92=6,"18", CB92=7,"19", CB92=8,"20", CB92=9,"21", CB92=10,"22")),FALSE)) | DK93: Source
B94: =IF(I92="","",VLOOKUP(I92,'Spell Database'!$A$2:$W$980,12,FALSE)) | D94: =IF(I92="","",VLOOKUP(I92,'Spell Database'!$A$2:$W$980,3,FALSE)) | F94: =IF(I92="","",VLOOKUP(I92,'Spell Database'!$A$2:$W$980,7,FALSE)) | AO94: =IF(AV92="","",VLOOKUP(AV92,'Spell Database'!$A$2:$W$980,12,FALSE)) | AQ94: =IF(AV92="","",VLOOKUP(AV92,'Spell Database'!$A$2:$W$980,3,FALSE)) | AS94: =IF(AV92="","",VLOOKUP(AV92,'Spell Database'!$A$2:$W$980,7,FALSE)) | CB94: =IF(CI92="","",VLOOKUP(CI92,'Spell Database'!$A$2:$W$980,12,FALSE)) | CD94: =IF(CI92="","",VLOOKUP(CI92,'Spell Database'!$A$2:$W$980,3,FALSE)) | CF94: =IF(CI92="","",VLOOKUP(CI92,'Spell Database'!$A$2:$W$980,7,FALSE))
B95: Duration | F95: School | AO95: Duration | AS95: School | CB95: Duration | CF95: School
B96: =IF(I92="","",VLOOKUP(I92,'Spell Database'!$A$2:$W$980,11,FALSE)) | F96: =IF(I92="","",VLOOKUP(I92,'Spell Database'!$A$2:$W$980,4,FALSE)) | AO96: =IF(AV92="","",VLOOKUP(AV92,'Spell Database'!$A$2:$W$980,11,FALSE)) | AS96: =IF(AV92="","",VLOOKUP(AV92,'Spell Database'!$A$2:$W$980,4,FALSE)) | CB96: =IF(CI92="","",VLOOKUP(CI92,'Spell Database'!$A$2:$W$980,11,FALSE)) | CF96: =IF(CI92="","",VLOOKUP(CI92,'Spell Database'!$A$2:$W$980,4,FALSE))
B97: Lv | D97: Lv+ | F97: Actions | I97: Name | U97: Range | X97: Target/Area | AE97: Save/Attack | AK97: Prepared | AO97: Lv | AQ97: Lv+ | AS97: Actions | AV97: Name | BH97: Range | BK97: Target/Area | BR97: Save/Attack | BX97: Prepared | CB97: Lv | CD97: Lv+ | CF97: Actions | CI97: Name | CS97: Range | CV97: Target/Area | DC97: Save/Attack | DH97: Item DC | DK97: Uses | DN97: Used
B98: =IF(I98="","",VLOOKUP(I98,'Spell Database'!$A$2:$W$980,2,FALSE)) | D98: =IF(I98="","",VLOOKUP(I98,'Spell Database'!$A$2:$W$980,5,FALSE)) | F98: =IF(I98="","",VLOOKUP(I98,'Spell Database'!$A$2:$W$980,6,FALSE)) | U98: =IF(I98="","",VLOOKUP(I98,'Spell Database'!$A$2:$W$980,8,FALSE)) | X98: =IF(I98="","",VLOOKUP(I98,'Spell Database'!$A$2:$W$980,9,FALSE)) | AE98: =IF(I98="","",VLOOKUP(I98,'Spell Database'!$A$2:$W$980,10,FALSE)) | AO98: =IF(AV98="","",VLOOKUP(AV98,'Spell Database'!$A$2:$W$980,2,FALSE)) | AQ98: =IF(AV98="","",VLOOKUP(AV98,'Spell Database'!$A$2:$W$980,5,FALSE)) | AS98: =IF(AV98="","",VLOOKUP(AV98,'Spell Database'!$A$2:$W$980,6,FALSE)) | BH98: =IF(AV98="","",VLOOKUP(AV98,'Spell Database'!$A$2:$W$980,8,FALSE)) | BK98: =IF(AV98="","",VLOOKUP(AV98,'Spell Database'!$A$2:$W$980,9,FALSE)) | BR98: =IF(AV98="","",VLOOKUP(AV98,'Spell Database'!$A$2:$W$980,10,FALSE)) | CB98: =IF(CI98="","",VLOOKUP(CI98,'Spell Database'!$A$2:$W$980,2,FALSE)) | CD98: =IF(CI98="","",VLOOKUP(CI98,'Spell Database'!$A$2:$W$980,5,FALSE)) | CF98: =IF(CI98="","",VLOOKUP(CI98,'Spell Database'!$A$2:$W$980,6,FALSE)) | CS98: =IF(CI98="","",VLOOKUP(CI98,'Spell Database'!$A$2:$W$980,8,FALSE)) | CV98: =IF(CI98="","",VLOOKUP(CI98,'Spell Database'!$A$2:$W$980,9,FALSE)) | DC98: =IF(CI98="","",VLOOKUP(CI98,'Spell Database'!$A$2:$W$980,10,FALSE))
B99: Type | D99: Rarity | F99: Component | I99: =IF(I98="","",VLOOKUP(I98,'Spell Database'!$A$2:$V$980, (IFs(B98=1,"13", B98=2,"14", B98=3,"15", B98=4,"16", B98=5,"17", B98=6,"18", B98=7,"19", B98=8,"20", B98=9,"21", B98=10,"22")),FALSE)) | AK99: Used | AO99: Type | AQ99: Rarity | AS99: Component | AV99: =IF(AV98="","",VLOOKUP(AV98,'Spell Database'!$A$2:$V$980, (IFs(AO98=1,"13", AO98=2,"14", AO98=3,"15", AO98=4,"16", AO98=5,"17", AO98=6,"18", AO98=7,"19", AO98=8,"20", AO98=9,"21", AO98=10,"22")),FALSE)) | BX99: Used | CB99: Type | CD99: Rarity | CF99: Component | CI99: =IF(CI98="","",VLOOKUP(CI98,'Spell Database'!$A$2:$V$980, (IFs(CB98=1,"13", CB98=2,"14", CB98=3,"15", CB98=4,"16", CB98=5,"17", CB98=6,"18", CB98=7,"19", CB98=8,"20", CB98=9,"21", CB98=10,"22")),FALSE)) | DK99: Source
B100: =IF(I98="","",VLOOKUP(I98,'Spell Database'!$A$2:$W$980,12,FALSE)) | D100: =IF(I98="","",VLOOKUP(I98,'Spell Database'!$A$2:$W$980,3,FALSE)) | F100: =IF(I98="","",VLOOKUP(I98,'Spell Database'!$A$2:$W$980,7,FALSE)) | AO100: =IF(AV98="","",VLOOKUP(AV98,'Spell Database'!$A$2:$W$980,12,FALSE)) | AQ100: =IF(AV98="","",VLOOKUP(AV98,'Spell Database'!$A$2:$W$980,3,FALSE)) | AS100: =IF(AV98="","",VLOOKUP(AV98,'Spell Database'!$A$2:$W$980,7,FALSE)) | CB100: =IF(CI98="","",VLOOKUP(CI98,'Spell Database'!$A$2:$W$980,12,FALSE)) | CD100: =IF(CI98="","",VLOOKUP(CI98,'Spell Database'!$A$2:$W$980,3,FALSE)) | CF100: =IF(CI98="","",VLOOKUP(CI98,'Spell Database'!$A$2:$W$980,7,FALSE))
B101: Duration | F101: School | AO101: Duration | AS101: School | CB101: Duration | CF101: School
B102: =IF(I98="","",VLOOKUP(I98,'Spell Database'!$A$2:$W$980,11,FALSE)) | F102: =IF(I98="","",VLOOKUP(I98,'Spell Database'!$A$2:$W$980,4,FALSE)) | AO102: =IF(AV98="","",VLOOKUP(AV98,'Spell Database'!$A$2:$W$980,11,FALSE)) | AS102: =IF(AV98="","",VLOOKUP(AV98,'Spell Database'!$A$2:$W$980,4,FALSE)) | CB102: =IF(CI98="","",VLOOKUP(CI98,'Spell Database'!$A$2:$W$980,11,FALSE)) | CF102: =IF(CI98="","",VLOOKUP(CI98,'Spell Database'!$A$2:$W$980,4,FALSE))
...

Sheet Spell Database
A1: name | B1: level | C1: rarity | D1: school | E1: heightenable | F1: actions | G1: components | H1: Range | I1: Target | J1: Saving Throw | K1: Duration | L1: category | M1: Level 1 | N1: Level 2 | O1: Level 3 | P1: Level 4 | Q1: Level 5 | R1: Level 6 | S1: Level 7 | T1: Level 8 | U1: Level 9 | V1: Level 10 | W1: traditions | X1: Source
A2: Acid Splash | B2: =Spells!$S$4 -> 1 | C2: C | D2: Evo | E2: Y | F2: ='Character Sheet'!$C$9 | G2: S,V | H2: 30ft | I2: 1 creature | J2: Attack | K2: Instant | L2: C | M2: On hit deal 1d6 acid damage, plus 1 splash. On Crit target gains 1 persistent acid damage. | N2: On hit deal 1d6 acid damage, plus 1 splash. On Crit target gains 1 persistent acid damage. | O2: On hit deal 1d6+[Spellcasting Mod] acid damage, plus 1 splash. On Crit target gains 2 persistent acid damage. | P2: On hit deal 1d6+[Spellcasting Mod] acid damage, plus 1 splash. On Crit target gains 2 persistent acid damage. | Q2: On hit deal 2d6+[Spellcasting Mod] acid damage, plus 2 splash damage. On Crit target gains 3 persistent acid damage. | R2: On hit deal 2d6+[Spellcasting Mod] acid damage, plus 2 splash damage. On Crit target gains 3 persistent acid damage. | S2: On hit deal 3d6+[Spellcasting Mod] acid damage, plus 3 splash damage. On Crit target gains 4 persistent acid damage. | T2: On hit deal 3d6+[Spellcasting Mod] acid damage, plus 3 splash damage. On Crit target gains 4 persistent acid damage. | U2: On hit deal 4d6+[Spellcasting Mod] acid damage, plus 4 splash damage. On Crit target gains 5 persistent acid damage. | V2: On hit deal 4d6+[Spellcasting Mod] acid damage, plus 4 splash damage. On Crit target gains 5 persistent acid damage. | W2: arcane, primal | X2: Core
A3: Approximate | B3: =Spells!$S$4 -> 1 | C3: C | D3: Div | E3: N | F3: ='Character Sheet'!$C$9 | G3: S,V | H3: 10ft | I3: 1ft cube | J3: N/A | K3: Instant | L3: C | M3: Name object to count; instantly gain rounded number of objects you can see. Rounds to the largest number (180 copper becomes 200). Note: "Dented copper coins" is different than "copper coins" and gold plated coins will show up as "gold coins" | N3: Name object to count; instantly gain rounded number of objects you can see. Rounds to the largest number (180 copper becomes 200). Note: "Dented copper coins" is different than "copper coins" and gold plated coins will show up as "gold coins" | O3: Name object to count; instantly gain rounded number of objects you can see. Rounds to the largest number (180 copper becomes 200). Note: "Dented copper coins" is different than "copper coins" and gold plated coins will show up as "gold coins" | P3: Name object to count; instantly gain rounded number of objects you can see. Rounds to the largest number (180 copper becomes 200). Note: "Dented copper coins" is different than "copper coins" and gold plated coins will show up as "gold coins" | Q3: Name object to count; instantly gain rounded number of objects you can see. Rounds to the largest number (180 copper becomes 200). Note: "Dented copper coins" is different than "copper coins" and gold plated coins will show up as "gold coins" | R3: Name object to count; instantly gain rounded number of objects you can see. Rounds to the largest number (180 copper becomes 200). Note: "Dented copper coins" is different than "copper coins" and gold plated coins will show up as "gold coins" | S3: Name object to count; instantly gain rounded number of objects you can see. Rounds to the largest number (180 copper becomes 200). Note: "Dented copper coins" is different than "copper coins" and gold plated coins will show up as "gold coins" | T3: Name object to count; instantly gain rounded number of objects you can see. Rounds to the largest number (180 copper becomes 200). Note: "Dented copper coins" is different than "copper coins" and gold plated coins will show up as "gold coins" | U3: Name object to count; instantly gain rounded number of objects you can see. Rounds to the largest number (180 copper becomes 200). Note: "Dented copper coins" is different than "copper coins" and gold plated coins will show up as "gold coins" | V3: Name object to count; instantly gain rounded number of objects you can see. Rounds to the largest number (180 copper becomes 200). Note: "Dented copper coins" is different than "copper coins" and gold plated coins will show up as "gold coins" | W3: arcane, divine, occult, primal | X3: Secrets of Magic
A4: Bullhorn | B4: =Spells!$S$4 -> 1 | C4: C | D4: Ill | E4: Y | F4: ='Character Sheet'!$C$9 | G4: S,V | H4: Self | I4: Self | J4: N/A | K4: 10 min | L4: C | M4: For the duration your voice can be heard clearly by anyone within 500ft, even if ambiant noise would block sound. Walls still block sound. Gain a +1 to attempts to Perform or Coerce. You can freely dismiss the spell. | N4: For the duration your voice can be heard clearly by anyone within 500ft, even if ambiant noise would block sound. Walls still block sound. Gain a +1 to attempts to Perform or Coerce. You can freely dismiss the spell. | O4: For the duration your voice can be heard clearly by anyone within 500ft, even if ambiant noise would block sound. Walls still block sound. Gain a +1 to attempts to Perform or Coerce. You can freely dismiss the spell. | P4: For the duration your voice can be heard clearly by anyone within 500ft, even if ambiant noise would block sound. Walls still block sound. Gain a +1 to attempts to Perform or Coerce. You can freely dismiss the spell. | Q4: For the duration your voice can be heard clearly by anyone within 1200ft, even if ambiant noise would block sound. Walls still block sound. Gain a +1 to attempts to Perform or Coerce. You can freely dismiss the spell. | R4: For the duration your voice can be heard clearly by anyone within 1200ft, even if ambiant noise would block sound. Walls still block sound. Gain a +1 to attempts to Perform or Coerce. You can freely dismiss the spell. | S4: For the duration your voice can be heard clearly by anyone within 1 mile (5200ft), even if ambiant noise would block sound. Walls still block sound. Gain a +1 to attempts to Perform or Coerce. You can freely dismiss the spell. | T4: For the duration your voice can be heard clearly by anyone within 1 mile (5200ft), even if ambiant noise would block sound. Walls still block sound. Gain a +1 to attempts to Perform or Coerce. You can freely dismiss the spell. | U4: For the duration your voice can be heard clearly by anyone within 1 mile (5200ft), even if ambiant noise would block sound. Walls still block sound. Gain a +1 to attempts to Perform or Coerce. You can freely dismiss the spell. | V4: For the duration your voice can be heard clearly by anyone within 1 mile (5200ft), even if ambiant noise would block sound. Walls still block sound. Gain a +1 to attempts to Perform or Coerce. You can freely dismiss the spell. | W4: arcane, divine, occult | X4: Secrets of Magic
A5: Chill Touch | B5: =Spells!$S$4 -> 1 | C5: C | D5: Nec | E5: Y | F5: ='Character Sheet'!$C$9 | G5: S,V | H5: Touch | I5: 1 creature | J5: Basic Fortitude | K5: Instant | L5: C | M5: Against Living: Deal 1d4+[Mod] Negative damage on failed save. Become enfeebled 1 for 1 round on crit fail. Against Undead: Target becomes flat-footed for 1 round. On Crit fail target makes Will save or flees for 1 round. | N5: Against Living: Deal 2d4+[Mod] Negative damage on failed save. Become enfeebled 1 for 1 round on crit fail. Against Undead: Target becomes flat-footed for 1 round. On Crit fail target makes Will save or flees for 1 round. | O5: Against Living: Deal 3d4+[Mod] Negative damage on failed save. Become enfeebled 1 for 1 round on crit fail. Against Undead: Target becomes flat-footed for 1 round. On Crit fail target makes Will save or flees for 1 round. | P5: Against Living: Deal 4d4+[Mod] Negative damage on failed save. Become enfeebled 1 for 1 round on crit fail. Against Undead: Target becomes flat-footed for 1 round. On Crit fail target makes Will save or flees for 1 round. | Q5: Against Living: Deal 5d4+[Mod] Negative damage on failed save. Become enfeebled 1 for 1 round on crit fail. Against Undead: Target becomes flat-footed for 1 round. On Crit fail target makes Will save or flees for 1 round." | R5: Against Living: Deal 6d4+[Mod] Negative damage on failed save. Become enfeebled 1 for 1 round on crit fail. Against Undead: Target becomes flat-footed for 1 round. On Crit fail target makes Will save or flees for 1 round. | S5: Against Living: Deal 7d4+[Mod] Negative damage on failed save. Become enfeebled 1 for 1 round on crit fail. Against Undead: Target becomes flat-footed for 1 round. On Crit fail target makes Will save or flees for 1 round." | T5: Against Living: Deal 8d4+[Mod] Negative damage on failed save. Become enfeebled 1 for 1 round on crit fail. Against Undead: Target becomes flat-footed for 1 round. On Crit fail target makes Will save or flees for 1 round. | U5: Against Living: Deal 9d4+[Mod] Negative damage on failed save. Become enfeebled 1 for 1 round on crit fail. Against Undead: Target becomes flat-footed for 1 round. On Crit fail target makes Will save or flees for 1 round." | V5: Against Living: Deal 10d4+[Mod] Negative damage on failed save. Become enfeebled 1 for 1 round on crit fail. Against Undead: Target becomes flat-footed for 1 round. On Crit fail target makes Will save or flees for 1 round." | W5: arcane, divine, occult | X5: Core
A6: Dancing Lights | B6: =Spells!$S$4 -> 1 | C6: C | D6: Evo | E6: N | F6: ='Character Sheet'!$C$9 | G6: S,V | H6: 120ft | I6: N/A | J6: N/A | K6: [S] | L6: C | M6: Create 4 floating lights, no two of which can be more than 10ft apart. Sheds light upto 20ft of bright light and 20 more ft dim. When sustaining can move any number of lights upto 60ft. | N6: Create 4 floating lights, no two of which can be more than 10ft apart. Sheds light upto 20ft of bright light and 20 more ft dim. When sustaining can move any number of lights upto 60ft. | O6: Create 4 floating lights, no two of which can be more than 10ft apart. Sheds light upto 20ft of bright light and 20 more ft dim. When sustaining can move any number of lights upto 60ft. | P6: Create 4 floating lights, no two of which can be more than 10ft apart. Sheds light upto 20ft of bright light and 20 more ft dim. When sustaining can move any number of lights upto 60ft. | Q6: Create 4 floating lights, no two of which can be more than 10ft apart. Sheds light upto 20ft of bright light and 20 more ft dim. When sustaining can move any number of lights upto 60ft. | R6: Create 4 floating lights, no two of which can be more than 10ft apart. Sheds light upto 20ft of bright light and 20 more ft dim. When sustaining can move any number of lights upto 60ft. | S6: Create 4 floating lights, no two of which can be more than 10ft apart. Sheds light upto 20ft of bright light and 20 more ft dim. When sustaining can move any number of lights upto 60ft. | T6: Create 4 floating lights, no two of which can be more than 10ft apart. Sheds light upto 20ft of bright light and 20 more ft dim. When sustaining can move any number of lights upto 60ft. | U6: Create 4 floating lights, no two of which can be more than 10ft apart. Sheds light upto 20ft of bright light and 20 more ft dim. When sustaining can move any number of lights upto 60ft. | V6: Create 4 floating lights, no two of which can be more than 10ft apart. Sheds light upto 20ft of bright light and 20 more ft dim. When sustaining can move any number of lights upto 60ft. | W6: arcane, occult, primal | X6: Core
A7: Daze | B7: =Spells!$S$4 -> 1 | C7: C | D7: Ench | E7: Y | F7: ='Character Sheet'!$C$9 | G7: S,V | H7: 60ft | I7: 1 creature | J7: Will | K7: Instant | L7: C | M7: Cloud the target's mind with a mental jolt. Deals mental damage equal to [Spellcasting Mod]. On a crit fail target also becomes stunned 1 for 1 round. | N7: Cloud the target's mind with a mental jolt. Deals mental damage equal to [Spellcasting Mod]. On a crit fail target also becomes stunned 1 for 1 round. | O7: Cloud the target's mind with a mental jolt. Deals mental damage equal to 1d6+[Spellcasting Mod]. On a crit fail target also becomes stunned 1 for 1 round. | P7: Cloud the target's mind with a mental jolt. Deals mental damage equal to 1d6+[Spellcasting Mod]. On a crit fail target also becomes stunned 1 for 1 round. | Q7: Cloud the target's mind with a mental jolt. Deals mental damage equal to 2d6+[Spellcasting Mod]. On a crit fail target also becomes stunned 1 for 1 round. | R7: Cloud the target's mind with a mental jolt. Deals mental damage equal to 2d6+[Spellcasting Mod]. On a crit fail target also becomes stunned 1 for 1 round. | S7: Cloud the target's mind with a mental jolt. Deals mental damage equal to 3d6+[Spellcasting Mod]. On a crit fail target also becomes stunned 1 for 1 round. | T7: Cloud the target's mind with a mental jolt. Deals mental damage equal to 3d6+[Spellcasting Mod]. On a crit fail target also becomes stunned 1 for 1 round. | U7: Cloud the target's mind with a mental jolt. Deals mental damage equal to 4d6+[Spellcasting Mod]. On a crit fail target also becomes stunned 1 for 1 round. | V7: Cloud the target's mind with a mental jolt. Deals mental damage equal to 4d6+[Spellcasting Mod]. On a crit fail target also becomes stunned 1 for 1 round. | W7: arcane, divine, occult | X7: Core
A8: Detect Magic | B8: =Spells!$S$4 -> 1 | C8: C | D8: Div | E8: Y | F8: ='Character Sheet'!$C$9 | G8: S,V | H8: 30ft | I8: N/A | J8: N/A | K8: Instant | L8: C | M8: Send out a pulse that registers the presence of magic, registering nothing beyond "presense of magic item." Freely magic items you already know about. Deceptive Illusion magic is detected only if it is a lower level than Detect Magic Spell (Invisibility spells register normally) | N8: Send out a pulse that registers the presence of magic, registering nothing beyond "presense of magic item." Freely magic items you already know about. Deceptive Illusion magic is detected only if it is a lower level than Detect Magic Spell (Invisibility spells register normally) | O8: Send out a pulse that registers the presence of magic, registering "presense of magic item" and the school of magic of the strongest item detected. Freely magic items you already know about. Deceptive Illusion magic is detected only if it is a lower level than Detect Magic Spell (Invisibility spells register normally) | P8: Send out a pulse that registers the presence of magic, registering "presense of magic item" and both the rough location and school of magic of the strongest item detected. Freely magic items you already know about. Deceptive Illusion magic is detected only if it is a lower level than Detect Magic Spell (Invisibility spells register normally) | Q8: Send out a pulse that registers the presence of magic, registering "presense of magic item" and both the rough location and school of magic of the strongest item detected. Freely magic items you already know about. Deceptive Illusion magic is detected only if it is a lower level than Detect Magic Spell (Invisibility spells register normally) | R8: Send out a pulse that registers the presence of magic, registering "presense of magic item" and both the rough location and school of magic of the strongest item detected. Freely magic items you already know about. Deceptive Illusion magic is detected only if it is a lower level than Detect Magic Spell (Invisibility spells register normally) | S8: Send out a pulse that registers the presence of magic, registering "presense of magic item" and both the rough location and school of magic of the strongest item detected. Freely magic items you already know about. Deceptive Illusion magic is detected only if it is a lower level than Detect Magic Spell (Invisibility spells register normally) | T8: Send out a pulse that registers the presence of magic, registering "presense of magic item" and both the rough location and school of magic of the strongest item detected. Freely magic items you already know about. Deceptive Illusion magic is detected only if it is a lower level than Detect Magic Spell (Invisibility spells register normally) | U8: Send out a pulse that registers the presence of magic, registering "presense of magic item" and both the rough location and school of magic of the strongest item detected. Freely magic items you already know about. Deceptive Illusion magic is detected only if it is a lower level than Detect Magic Spell (Invisibility spells register normally) | V8: Send out a pulse that registers the presence of magic, registering "presense of magic item" and both the rough location and school of magic of the strongest item detected. Freely magic items you already know about. Deceptive Illusion magic is detected only if it is a lower level than Detect Magic Spell (Invisibility spells register normally) | W8: arcane, divine, occult, primal | X8: Core
A9: Disrupt Undead | B9: =Spells!$S$4 -> 1 | C9: C | D9: Nec | E9: Y | F9: ='Character Sheet'!$C$9 | G9: S,V | H9: 30ft | I9: 1 Undead | J9: Basic Fortitude | K9: Instant | L9: C | M9: Lancing an undead to deal 1d6+[Mod] positive damage. On Crit fail target becomes enfeebled 1 for 1 round. | N9: Lancing an undead to deal 2d6+[Mod] positive damage. On Crit fail target becomes enfeebled 1 for 1 round. | O9: Lancing an undead to deal 3d6+[Mod] positive damage. On Crit fail target becomes enfeebled 1 for 1 round. | P9: Lancing an undead to deal 4d6+[Mod] positive damage. On Crit fail target becomes enfeebled 1 for 1 round. | Q9: Lancing an undead to deal 5d6+[Mod] positive damage. On Crit fail target becomes enfeebled 1 for 1 round. | R9: Lancing an undead to deal 6d6+[Mod] positive damage. On Crit fail target becomes enfeebled 1 for 1 round. | S9: Lancing an undead to deal 7d6+[Mod] positive damage. On Crit fail target becomes enfeebled 1 for 1 round. | T9: Lancing an undead to deal 8d6+[Mod] positive damage. On Crit fail target becomes enfeebled 1 for 1 round. | U9: Lancing an undead to deal 9d6+[Mod] positive damage. On Crit fail target becomes enfeebled 1 for 1 round. | V9: Lancing an undead to deal 10d6+[Mod] positive damage. On Crit fail target becomes enfeebled 1 for 1 round. | W9: divine, primal | X9: Core
A10: Divine Lance | B10: =Spells!$S$4 -> 1 | C10: C | D10: Evo | E10: Y | F10: ='Character Sheet'!$C$9 | G10: S,V | H10: 30ft | I10: 1 creature | J10: Attack | K10: Instant | L10: C | M10: Unleash a lance of divine enegery. On hit deal 1d4+[Mod] damage determined by the alignment of your diety (chaotic, evil, good, or lawful). | N10: Unleash a lance of divine enegery. On hit deal 2d4+[Mod] damage determined by the alignment of your diety (chaotic, evil, good, or lawful). | O10: Unleash a lance of divine enegery. On hit deal 3d4+[Mod] damage determined by the alignment of your diety (chaotic, evil, good, or lawful). | P10: Unleash a lance of divine enegery. On hit deal 4d4+[Mod] damage determined by the alignment of your diety (chaotic, evil, good, or lawful). | Q10: Unleash a lance of divine enegery. On hit deal 5d4+[Mod] damage determined by the alignment of your diety (chaotic, evil, good, or lawful). | R10: Unleash a lance of divine enegery. On hit deal 6d4+[Mod] damage determined by the alignment of your diety (chaotic, evil, good, or lawful). | S10: Unleash a lance of divine enegery. On hit deal 7d4+[Mod] damage determined by the alignment of your diety (chaotic, evil, good, or lawful). | T10: Unleash a lance of divine enegery. On hit deal 8d4+[Mod] damage determined by the alignment of your diety (chaotic, evil, good, or lawful). | U10: Unleash a lance of divine enegery. On hit deal 9d4+[Mod] damage determined by the alignment of your diety (chaotic, evil, good, or lawful). | V10: Unleash a lance of divine enegery. On hit deal 10d4+[Mod] damage determined by the alignment of your diety (chaotic, evil, good, or lawful). | W10: divine | X10: Core
A11: Electric Arc | B11: =Spells!$S$4 -> 1 | C11: C | D11: Evo | E11: Y | F11: ='Character Sheet'!$C$9 | G11: S,V | H11: 30ft | I11: Upto 2 | J11: Basic Reflex | K11: Instant | L11: C | M11: An arc of lightniung that leaps from one target to another. Deal 1d4+[Mod] electrical damage to upto two creastures. | N11: An arc of lightniung that leaps from one target to another. Deal 2d4+[Mod] electrical damage to upto two creastures. | O11: An arc of lightniung that leaps from one target to another. Deal 3d4+[Mod] electrical damage to upto two creastures. | P11: An arc of lightniung that leaps from one target to another. Deal 4d4+[Mod] electrical damage to upto two creastures. | Q11: An arc of lightniung that leaps from one target to another. Deal 5d4+[Mod] electrical damage to upto two creastures. | R11: An arc of lightniung that leaps from one target to another. Deal 6d4+[Mod] electrical damage to upto two creastures. | S11: An arc of lightniung that leaps from one target to another. Deal 7d4+[Mod] electrical damage to upto two creastures. | T11: An arc of lightniung that leaps from one target to another. Deal 8d4+[Mod] electrical damage to upto two creastures. | U11: An arc of lightniung that leaps from one target to another. Deal 9d4+[Mod] electrical damage to upto two creastures. | V11: An arc of lightniung that leaps from one target to another. Deal 10d4+[Mod] electrical damage to upto two creastures. | W11: arcane, primal | X11: Core
A12: Forbidding Ward | B12: =Spells!$S$4 -> 1 | C12: C | D12: Abj | E12: Y | F12: ='Character Sheet'!$C$9 | G12: S,V | H12: 30ft | I12: 1 ally, 1 enemy | J12: N/A | K12: [S] 1min | L12: C | M12: Protect an ally against a single enemy, granting a +1 bonus to AC and saving throws against the target enemy. | N12: Protect an ally against a single enemy, granting a +1 bonus to AC and saving throws against the target enemy. | O12: Protect an ally against a single enemy, granting a +1 bonus to AC and saving throws against the target enemy. | P12: Protect an ally against a single enemy, granting a +1 bonus to AC and saving throws against the target enemy. | Q12: Protect an ally against a single enemy, granting a +1 bonus to AC and saving throws against the target enemy. | R12: Protect an ally against a single enemy, granting a +2 bonus to AC and saving throws against the target enemy. | S12: Protect an ally against a single enemy, granting a +2 bonus to AC and saving throws against the target enemy. | T12: Protect an ally against a single enemy, granting a +2 bonus to AC and saving throws against the target enemy. | U12: Protect an ally against a single enemy, granting a +2 bonus to AC and saving throws against the target enemy. | V12: Protect an ally against a single enemy, granting a +2 bonus to AC and saving throws against the target enemy. | W12: divine, occult | X12: Core
A13: Gale Blast | B13: =Spells!$S$4 -> 1 | C13: C | D13: Evo | E13: Y | F13: ='Character Sheet'!$C$9 | G13: S,V | H13: Self | I13: 5ft radius | J13: Basic Fortitude | K13: Instant | L13: C | M13: Protect yourself with the wind. Each adjacent creature takes [Mod] bludgeoning damage and pushed back 5ft on a failed Fort save. Double damage and pushed back 10ft on a critical failure. | N13: Protect yourself with the wind. Each adjacent creature takes [Mod] bludgeoning damage and pushed back 5ft on a failed Fort save. Double damage and pushed back 10ft on a critical failure. | O13: Protect yourself with the wind. Each adjacent creature takes 1d6+[Mod] bludgeoning damage and pushed back 5ft on a failed Fort save. Double damage and pushed back 10ft on a critical failure. | P13: Protect yourself with the wind. Each adjacent creature takes 1d6+[Mod] bludgeoning damage and pushed back 5ft on a failed Fort save. Double damage and pushed back 10ft on a critical failure. | Q13: Protect yourself with the wind. Each adjacent creature takes 2d6+[Mod] bludgeoning damage and pushed back 5ft on a failed Fort save. Double damage and pushed back 10ft on a critical failure. | R13: Protect yourself with the wind. Each adjacent creature takes 2d6+[Mod] bludgeoning damage and pushed back 5ft on a failed Fort save. Double damage and pushed back 10ft on a critical failure. | S13: Protect yourself with the wind. Each adjacent creature takes 3d6+[Mod] bludgeoning damage and pushed back 5ft on a failed Fort save. Double damage and pushed back 10ft on a critical failure. | T13: Protect yourself with the wind. Each adjacent creature takes 3d6+[Mod] bludgeoning damage and pushed back 5ft on a failed Fort save. Double damage and pushed back 10ft on a critical failure. | U13: Protect yourself with the wind. Each adjacent creature takes 4d6+[Mod] bludgeoning damage and pushed back 5ft on a failed Fort save. Double damage and pushed back 10ft on a critical failure. | V13: Protect yourself with the wind. Each adjacent creature takes 4d6+[Mod] bludgeoning damage and pushed back 5ft on a failed Fort save. Double damage and pushed back 10ft on a critical failure. | W13: arcane, primal | X13: Secrets of Magic
... A15: Gouging Claw | B15: =Spells!$S$4 -> 1 | C15: C | D15: Tran | E15: Y | F15: ='Character Sheet'!$C$9 | G15: S,V | H15: Touch | I15: 1 creature | J15: Attack | K15: Instant | L15: C | M15: Turning a limb into a claw to make an attack. On hit deal 1d6+[Mod] slashing or piercing damage. On crit deal 1d4 persistent bleed damage. | N15: Turning a limb into a claw to make an attack. On hit deal 2d6+[Mod] slashing or piercing damage. On crit deal 2d4 persistent bleed damage. | O15: Turning a limb into a claw to make an attack. On hit deal 3d6+[Mod] slashing or piercing damage. On crit deal 3d4 persistent bleed damage. | P15: Turning a limb into a claw to make an attack. On hit deal 4d6+[Mod] slashing or piercing damage. On crit deal 4d4 persistent bleed damage. | Q15: Turning a limb into a claw to make an attack. On hit deal 5d6+[Mod] slashing or piercing damage. On crit deal 5d4 persistent bleed damage. | R15: Turning a limb into a claw to make an attack. On hit deal 6d6+[Mod] slashing or piercing damage. On crit deal 6d4 persistent bleed damage. | S15: Turning a limb into a claw to make an attack. On hit deal 7d6+[Mod] slashing or piercing damage. On crit deal 7d4 persistent bleed damage. | T15: Turning a limb into a claw to make an attack. On hit deal 8d6+[Mod] slashing or piercing damage. On crit deal 8d4 persistent bleed damage. | U15: Turning a limb into a claw to make an attack. On hit deal 9d6+[Mod] slashing or piercing damage. On crit deal 9d4 persistent bleed damage. | V15: Turning a limb into a claw to make an attack. On hit deal 10d6+[Mod] slashing or piercing damage. On crit deal 10d4 persistent bleed damage. | W15: arcane, primal | X15: Secrets of Magic
A16: Guidance | B16: =Spells!$S$4 -> 1 | C16: C | D16: Div | E16: N | F16: ='Character Sheet'!$B$9 | G16: V | H16: 30ft | I16: 1 creature | J16: N/A | K16: 1 round | L16: C | M16: Grant target a +1 status bonus to one attack, perception check, or skill check. After casting target becomes immune to the spell for the next hour. | N16: Grant target a +1 status bonus to one attack, perception check, or skill check. After casting target becomes immune to the spell for the next hour. | O16: Grant target a +1 status bonus to one attack, perception check, or skill check. After casting target becomes immune to the spell for the next hour. | P16: Grant target a +1 status bonus to one attack, perception check, or skill check. After casting target becomes immune to the spell for the next hour. | Q16: Grant target a +1 status bonus to one attack, perception check, or skill check. After casting target becomes immune to the spell for the next hour. | R16: Grant target a +1 status bonus to one attack, perception check, or skill check. After casting target becomes immune to the spell for the next hour. | S16: Grant target a +1 status bonus to one attack, perception check, or skill check. After casting target becomes immune to the spell for the next hour. | T16: Grant target a +1 status bonus to one attack, perception check, or skill check. After casting target becomes immune to the spell for the next hour. | U16: Grant target a +1 status bonus to one attack, perception check, or skill check. After casting target becomes immune to the spell for the next hour. | V16: Grant target a +1 status bonus to one attack, perception check, or skill check. After casting target becomes immune to the spell for the next hour. | W16: divine, occult, primal | X16: Core
A17: Haunting Hyme | B17: =Spells!$S$4 -> 1 | C17: C | D17: Evo | E17: Y | F17: ='Character Sheet'!$C$9 | G17: S,V | H17: Self | I17: 15ft Cone | J17: Basic Fortitude | K17: Instant | L17: C | M17: Echo a jarring hymn that only creatures in range can hear, dealing [Mod] sonic damage. On crit fail target becomes deafened for 1 minute. | N17: Echo a jarring hymn that only creatures in range can hear, dealing [Mod] sonic damage. On crit fail target becomes deafened for 1 minute. | O17: Echo a jarring hymn that only creatures in range can hear, dealing 1d6+[Mod] sonic damage. On crit fail target becomes deafened for 1 minute. | P17: Echo a jarring hymn that only creatures in range can hear, dealing 1d6+[Mod] sonic damage. On crit fail target becomes deafened for 1 minute. | Q17: Echo a jarring hymn that only creatures in range can hear, dealing 2d6+[Mod] sonic damage. On crit fail target becomes deafened for 1 minute. | R17: Echo a jarring hymn that only creatures in range can hear, dealing 2d6+[Mod] sonic damage. On crit fail target becomes deafened for 1 minute. | S17: Echo a jarring hymn that only creatures in range can hear, dealing 3d6+[Mod] sonic damage. On crit fail target becomes deafened for 1 minute. | T17: Echo a jarring hymn that only creatures in range can hear, dealing 3d6+[Mod] sonic damage. On crit fail target becomes deafened for 1 minute. | U17: Echo a jarring hymn that only creatures in range can hear, dealing 4d6+[Mod] sonic damage. On crit fail target becomes deafened for 1 minute. | V17: Echo a jarring hymn that only creatures in range can hear, dealing 4d6+[Mod] sonic damage. On crit fail target becomes deafened for 1 minute. | W17: divine, occult | X17: Secrets of Magic
A18: Healing Plaster | B18: =Spells!$S$4 -> 1 | C18: C | D18: Tran | E18: Y | F18: ='Character Sheet'!$B$9 | G18: S | H18: 5ft | I18: N/A | J18: N/A | K18: 10 min | L18: C | M18: Purify dirt and mud to aid in healing. Can be used instead of healer's tools for medicine checks. | N18: Purify dirt and mud to aid in healing. Can be used instead of healer's tools for medicine checks. | O18: Purify dirt and mud to aid in healing. Can be used instead of healer's tools for medicine checks with a +1 item bonus. | P18: Purify dirt and mud to aid in healing. Can be used instead of healer's tools for medicine checks with a +1 item bonus. | Q18: Purify dirt and mud to aid in healing. Can be used instead of healer's tools for medicine checks with a +1 item bonus. | R18: Purify dirt and mud to aid in healing. Can be used instead of healer's tools for medicine checks with a +1 item bonus. | S18: Purify dirt and mud to aid in healing. Can be used instead of healer's tools for medicine checks with a +1 item bonus. | T18: Purify dirt and mud to aid in healing. Can be used instead of healer's tools for medicine checks with a +1 item bonus. | U18: Purify dirt and mud to aid in healing. Can be used instead of healer's tools for medicine checks with a +1 item bonus. | V18: Purify dirt and mud to aid in healing. Can be used instead of healer's tools for medicine checks with a +1 item bonus. | W18: primal | X18: Secrets of Magic
A19: Infectious Enthusiasm | B19: =Spells!$S$4 -> 1 | C19: C | D19: Ench | E19: N | F19: ='Character Sheet'!$C$9 | G19: S,V | H19: 30ft | I19: N/A | J19: N/A | K19: 1 round | L19: C | M19: Encuraging yourself for a +1 to an attack, will save, or charisma based skill check. A single ally that sees you cast this spell can spend an action to gain the same bonus. Using this spell in front of someone you plan on using against will make them warry and the bonus can not be used. | N19: Encuraging yourself for a +1 to an attack, will save, or charisma based skill check. A single ally that sees you cast this spell can spend an action to gain the same bonus. Using this spell in front of someone you plan on using against will make them warry and the bonus can not be used. | O19: Encuraging yourself for a +1 to an attack, will save, or charisma based skill check. A single ally that sees you cast this spell can spend an action to gain the same bonus. Using this spell in front of someone you plan on using against will make them warry and the bonus can not be used. | P19: Encuraging yourself for a +1 to an attack, will save, or charisma based skill check. A single ally that sees you cast this spell can spend an action to gain the same bonus. Using this spell in front of someone you plan on using against will make them warry and the bonus can not be used. | Q19: Encuraging yourself for a +1 to an attack, will save, or charisma based skill check. A single ally that sees you cast this spell can spend an action to gain the same bonus. Using this spell in front of someone you plan on using against will make them warry and the bonus can not be used. | R19: Encuraging yourself for a +1 to an attack, will save, or charisma based skill check. A single ally that sees you cast this spell can spend an action to gain the same bonus. Using this spell in front of someone you plan on using against will make them warry and the bonus can not be used. | S19: Encuraging yourself for a +1 to an attack, will save, or charisma based skill check. A single ally that sees you cast this spell can spend an action to gain the same bonus. Using this spell in front of someone you plan on using against will make them warry and the bonus can not be used. | T19: Encuraging yourself for a +1 to an attack, will save, or charisma based skill check. A single ally that sees you cast this spell can spend an action to gain the same bonus. Using this spell in front of someone you plan on using against will make them warry and the bonus can not be used. | U19: Encuraging yourself for a +1 to an attack, will save, or charisma based skill check. A single ally that sees you cast this spell can spend an action to gain the same bonus. Using this spell in front of someone you plan on using against will make them warry and the bonus can not be used. | V19: Encuraging yourself for a +1 to an attack, will save, or charisma based skill check. A single ally that sees you cast this spell can spend an action to gain the same bonus. Using this spell in front of someone you plan on using against will make them warry and the bonus can not be used. | W19: arcane, occult | X19: Secrets of Magic
A20: Invoke True Name | B20: =Spells!$S$4 -> 1 | C20: R | D20: Ench | E20: Y | F20: ='Character Sheet'!$B$9 | G20: V | H20: 30ft | I20: 1 creature | J20: N/A | K20: End of turn | L20: C | M20: Enpower your magic against the target that you know the true name of. Target becomes flat-footed against you, and as a -2 circumstance penalty to saving throws against your spells. While under this spell, target has weakness 2 to your next spell. | N20: Enpower your magic against the target that you know the true name of. Target becomes flat-footed against you, and as a -2 circumstance penalty to saving throws against your spells. While under this spell, target has weakness 4 to your next spell. | O20: Enpower your magic against the target that you know the true name of. Target becomes flat-footed against you, and as a -2 circumstance penalty to saving throws against your spells. While under this spell, target has weakness 6 to your next spell. | P20: Enpower your magic against the target that you know the true name of. Target becomes flat-footed against you, and as a -2 circumstance penalty to saving throws against your spells. While under this spell, target has weakness 8 to your next spell. | Q20: Enpower your magic against the target that you know the true name of. Target becomes flat-footed against you, and as a -2 circumstance penalty to saving throws against your spells. While under this spell, target has weakness 10 to your next spell. | R20: Enpower your magic against the target that you know the true name of. Target becomes flat-footed against you, and as a -2 circumstance penalty to saving throws against your spells. While under this spell, target has weakness 12 to your next spell. | S20: Enpower your magic against the target that you know the true name of. Target becomes flat-footed against you, and as a -2 circumstance penalty to saving throws against your spells. While under this spell, target has weakness 14 to your next spell. | T20: Enpower your magic against the target that you know the true name of. Target becomes flat-footed against you, and as a -2 circumstance penalty to saving throws against your spells. While under this spell, target has weakness 16 to your next spell. | U20: Enpower your magic against the target that you know the true name of. Target becomes flat-footed against you, and as a -2 circumstance penalty to saving throws against your spells. While under this spell, target has weakness 18 to your next spell. | V20: Enpower your magic against the target that you know the true name of. Target becomes flat-footed against you, and as a -2 circumstance penalty to saving throws against your spells. While under this spell, target has weakness 20 to your next spell. | W20: arcane, divine, occult, primal | X20: Secrets of Magic
A21: Join Pasts | B21: =Spells!$S$4 -> 1 | C21: U | D21: Div | E21: Y | F21: ='Character Sheet'!$B$9 | G21: S | H21: Touch | I21: 2 creatures | J21: N/A | K21: 1 round | L21: C | M21: Touching the forhead of 2 individuals you create a mental link. Targets can share thoughts and experience, but not words. If one makes a Recall Knowledge check, all others connected can use any Lore Skill to aid without preperations. | N21: Touching the forhead of 3 individuals you create a mental link. Targets can share thoughts and experience, but not words. If one makes a Recall Knowledge check, all others connected can use any Lore Skill to aid without preperations. | O21: Touching the forhead of 4 individuals you create a mental link. Targets can share thoughts and experience, but not words. If one makes a Recall Knowledge check, all others connected can use any Lore Skill to aid without preperations. | P21: Touching the forhead of 5 individuals you create a mental link. Targets can share thoughts and experience, but not words. If one makes a Recall Knowledge check, all others connected can use any Lore Skill to aid without preperations. | Q21: Touching the forhead of 6 individuals you create a mental link. Targets can share thoughts and experience, but not words. If one makes a Recall Knowledge check, all others connected can use any Lore Skill to aid without preperations. | R21: Touching the forhead of 7 individuals you create a mental link. Targets can share thoughts and experience, but not words. If one makes a Recall Knowledge check, all others connected can use any Lore Skill to aid without preperations. | S21: Touching the forhead of 8 individuals you create a mental link. Targets can share thoughts and experience, but not words. If one makes a Recall Knowledge check, all others connected can use any Lore Skill to aid without preperations. | T21: Touching the forhead of 9 individuals you create a mental link. Targets can share thoughts and experience, but not words. If one makes a Recall Knowledge check, all others connected can use any Lore Skill to aid without preperations. | U21: Touching the forhead of 10 individuals you create a mental link. Targets can share thoughts and experience, but not words. If one makes a Recall Knowledge check, all others connected can use any Lore Skill to aid without preperations. | V21: Touching the forhead of 11 individuals you create a mental link. Targets can share thoughts and experience, but not words. If one makes a Recall Knowledge check, all others connected can use any Lore Skill to aid without preperations. | W21: occult | X21: Core
A22: Know Direction | B22: =Spells!$S$4 -> 1 | C22: C | D22: Div | E22: Y | F22: ='Character Sheet'!$C$9 | G22: S,V | H22: Self | I22: N/A | J22: N/A | K22: Instant | L22: C | M22: You immeadately know which direction North is (if it exists in your current location). | N22: You immeadately know which direction North is (if it exists in your current location). | O22: You immeadately know which direction North is (if it exists in your current location). | P22: You immeadately know which direction North is (if it exists in your current location). | Q22: You immeadately know which direction North is (if it exists in your current location). | R22: You immeadately know which direction North is (if it exists in your current location). | S22: You immeadately know which direction North is (if it exists in your current location) or the direction to a location you are familiar with. | T22: You immeadately know which direction North is (if it exists in your current location) or the direction to a location you are familiar with. | U22: You immeadately know which direction North is (if it exists in your current location) or the direction to a location you are familiar with. | V22: You immeadately know which direction North is (if it exists in your current location) or the direction to a location you are familiar with. | W22: divine, occult, primal | X22: Core
A23: Light | B23: =Spells!$S$4 -> 1 | C23: C | D23: Evo | E23: Y | F23: ='Character Sheet'!$C$9 | G23: S,V | H23: Touch | I23: 1 object | J23: N/A | K23: 1 day | L23: C | M23: Imburing an object of 1 bulk or less with light, it produces bright light within a 20ft radius and dim light for another 20ft. Second castings within the duration cancel the first spell. | N23: Imburing an object of 1 bulk or less with light, it produces bright light within a 20ft radius and dim light for another 20ft. Second castings within the duration cancel the first spell. | O23: Imburing an object of 1 bulk or less with light, it produces bright light within a 20ft radius and dim light for another 20ft. Second castings within the duration cancel the first spell. | P23: Imburing an object of 1 bulk or less with light, it produces bright light within a 60ft radius and dim light for another 60ft. Second castings within the duration cancel the first spell. | Q23: Imburing an object of 1 bulk or less with light, it produces bright light within a 60ft radius and dim light for another 60ft. Second castings within the duration cancel the first spell. | R23: Imburing an object of 1 bulk or less with light, it produces bright light within a 60ft radius and dim light for another 60ft. Second castings within the duration cancel the first spell. | S23: Imburing an object of 1 bulk or less with light, it produces bright light within a 60ft radius and dim light for another 60ft. Second castings within the duration cancel the first spell. | T23: Imburing an object of 1 bulk or less with light, it produces bright light within a 60ft radius and dim light for another 60ft. Second castings within the duration cancel the first spell. | U23: Imburing an object of 1 bulk or less with light, it produces bright light within a 60ft radius and dim light for another 60ft. Second castings within the duration cancel the first spell. | V23: Imburing an object of 1 bulk or less with light, it produces bright light within a 60ft radius and dim light for another 60ft. Second castings within the duration cancel the first spell. | W23: arcane, divine, occult, primal | X23: Core
A24: Mage Hand | B24: =Spells!$S$4 -> 1 | C24: C | D24: Evo | E24: Y | F24: ='Character Sheet'!$C$9 | G24: S,V | H24: 30ft | I24: 1 object | J24: N/A | K24: [S] | L24: C | M24: Create a magical floating hand to grasp and object and move it upto 20ft. While sustaining it can move another 20ft. The object must be unattended, upto 1 light bulk, and stay within 30ft of the caster. | N24: Create a magical floating hand to grasp and object and move it upto 20ft. While sustaining it can move another 20ft. The object must be unattended, upto 1 light bulk, and stay within 30ft of the caster. | O24: Create a magical floating hand to grasp and object and move it upto 20ft. While sustaining it can move another 20ft. The object must be unattended, upto 1 bulk, and stay within 30ft of the caster. | P24: Create a magical floating hand to grasp and object and move it upto 20ft. While sustaining it can move another 20ft. The object must be unattended, upto 1 bulk, and stay within 30ft of the caster. | Q24: Create a magical floating hand to grasp and object and move it upto 20ft. While sustaining it can move another 20ft. The object must be unattended, upto 1 bulk, and stay within 60ft of the caster. | R24: Create a magical floating hand to grasp and object and move it upto 20ft. While sustaining it can move another 20ft. The object must be unattended, upto 1 bulk, and stay within 60ft of the caster. | S24: Create a magical floating hand to grasp and object and move it upto 20ft. While sustaining it can move another 20ft. The object must be unattended, upto 2 bulk, and stay within 60ft of the caster. | T24: Create a magical floating hand to grasp and object and move it upto 20ft. While sustaining it can move another 20ft. The object must be unattended, upto 2 bulk, and stay within 60ft of the caster. | U24: Create a magical floating hand to grasp and object and move it upto 20ft. While sustaining it can move another 20ft. The object must be unattended, upto 2 bulk, and stay within 60ft of the caster. | V24: Create a magical floating hand to grasp and object and move it upto 20ft. While sustaining it can move another 20ft. The object must be unattended, upto 2 bulk, and stay within 60ft of the caster. | W24: arcane, occult | X24: Core
A25: Message | B25: =Spells!$S$4 -> 1 | C25: C | D25: Ill | E25: Y | F25: ='Character Sheet'!$B$9 | G25: V | H25: 120ft | I25: 1 creature | J25: N/A | K25: Instant | L25: C | M25: Mouthing words the target hears you perfectly. They can reply as either a reaction or free action on their next turn sending the words directly into your ear. | N25: Mouthing words the target hears you perfectly. They can reply as either a reaction or free action on their next turn sending the words directly into your ear. | O25: Mouthing words the target hears you perfectly as long as they are within 500ft. They can reply as either a reaction or free action on their next turn sending the words directly into your ear. | P25: Mouthing words the target hears you perfectly as long as they are within 500ft. They can reply as either a reaction or free action on their next turn sending the words directly into your ear. | Q25: Mouthing words the target hears you perfectly as long as they are within 500ft. They can reply as either a reaction or free action on their next turn sending the words directly into your ear. | R25: Mouthing words the target hears you perfectly as long as they are within 500ft. They can reply as either a reaction or free action on their next turn sending the words directly into your ear. | S25: Mouthing words the target hears you perfectly as long as they are within 500ft. They can reply as either a reaction or free action on their next turn sending the words directly into your ear. | T25: Mouthing words the target hears you perfectly as long as they are within 500ft. They can reply as either a reaction or free action on their next turn sending the words directly into your ear. | U25: Mouthing words the target hears you perfectly as long as they are within 500ft. They can reply as either a reaction or free action on their next turn sending the words directly into your ear. | V25: Mouthing words the target hears you perfectly as long as they are within 500ft. They can reply as either a reaction or free action on their next turn sending the words directly into your ear. | W25: arcane, divine, occult | X25: Core
A26: Phase Bolt | B26: =Spells!$S$4 -> 1 | C26: C | D26: Evo | E26: Y | F26: ='Character Sheet'!$C$9 | G26: S,V | H26: 30ft | I26: 1 creature | J26: Attack | K26: Instant | L26: C | M26: You fire a bolt of energy that phases in and out of existance until it hits the target, dealing 1d4. If the target is has any circumstance bonus to their AC (such as from a shield or cover), reduce that bonus by 2. | N26: You fire a bolt of energy that phases in and out of existance until it hits the target, dealing 2d4. If the target is has any circumstance bonus to their AC (such as from a shield or cover), reduce that bonus by 2. | O26: You fire a bolt of energy that phases in and out of existance until it hits the target, dealing 3d4. If the target is has any circumstance bonus to their AC (such as from a shield or cover), reduce that bonus by 2. | P26: You fire a bolt of energy that phases in and out of existance until it hits the target, dealing 4d4. If the target is has any circumstance bonus to their AC (such as from a shield or cover), reduce that bonus by 2. | Q26: You fire a bolt of energy that phases in and out of existance until it hits the target, dealing 5d4. If the target is has any circumstance bonus to their AC (such as from a shield or cover), reduce that bonus by 2. | R26: You fire a bolt of energy that phases in and out of existance until it hits the target, dealing 6d4. If the target is has any circumstance bonus to their AC (such as from a shield or cover), reduce that bonus by 2. | S26: You fire a bolt of energy that phases in and out of existance until it hits the target, dealing 7d4. If the target is has any circumstance bonus to their AC (such as from a shield or cover), reduce that bonus by 2. | T26: You fire a bolt of energy that phases in and out of existance until it hits the target, dealing 8d4. If the target is has any circumstance bonus to their AC (such as from a shield or cover), reduce that bonus by 2. | U26: You fire a bolt of energy that phases in and out of existance until it hits the target, dealing 9d4. If the target is has any circumstance bonus to their AC (such as from a shield or cover), reduce that bonus by 2. | V26: You fire a bolt of energy that phases in and out of existance until it hits the target, dealing 10d4. If the target is has any circumstance bonus to their AC (such as from a shield or cover), reduce that bonus by 2. | W26: arcane, occult | X26: Dark Archive
A27: Prestidigitation | B27: =Spells!$S$4 -> 1 | C27: C | D27: Evo | E27: N | F27: ='Character Sheet'!$C$9 | G27: S,V | H27: 10ft | I27: 1 object | J27: N/A | K27: [S] | L27: C | M27: Using magic you are able to do any of the following: Cook: Cool, warm, or flavor 1 pound of nonliving material. Lift: Lift unattended object of light bulk upto 1 foot off the ground. Make: Create a a fragile and crude item of negligible bulk, can not be used as a tool, weapon, or spell component. Lasts until sustained ends. Tidy: Color, clean, or soil an object of light bulk instantly. Takes 1 minute of sustaining to clean 1 bulk. | N27: Using magic you are able to do any of the following: Cook: Cool, warm, or flavor 1 pound of nonliving material. Lift: Lift unattended object of light bulk upto 1 foot off the ground. Make: Create a a fragile and crude item of negligible bulk, can not be used as a tool, weapon, or spell component. Lasts until sustained ends. Tidy: Color, clean, or soil an object of light bulk instantly. Takes 1 minute of sustaining to clean 1 bulk. | O27: Using magic you are able to do any of the following: Cook: Cool, warm, or flavor 1 pound of nonliving material. Lift: Lift unattended object of light bulk upto 1 foot off the ground. Make: Create a a fragile and crude item of negligible bulk, can not be used as a tool, weapon, or spell component. Lasts until sustained ends. Tidy: Color, clean, or soil an object of light bulk instantly. Takes 1 minute of sustaining to clean 1 bulk. | P27: Using magic you are able to do any of the following: Cook: Cool, warm, or flavor 1 pound of nonliving material. Lift: Lift unattended object of light bulk upto 1 foot off the ground. Make: Create a a fragile and crude item of negligible bulk, can not be used as a tool, weapon, or spell component. Lasts until sustained ends. Tidy: Color, clean, or soil an object of light bulk instantly. Takes 1 minute of sustaining to clean 1 bulk. | Q27: Using magic you are able to do any of the following: Cook: Cool, warm, or flavor 1 pound of nonliving material. Lift: Lift unattended object of light bulk upto 1 foot off the ground. Make: Create a a fragile and crude item of negligible bulk, can not be used as a tool, weapon, or spell component. Lasts until sustained ends. Tidy: Color, clean, or soil an object of light bulk instantly. Takes 1 minute of sustaining to clean 1 bulk. | R27: Using magic you are able to do any of the following: Cook: Cool, warm, or flavor 1 pound of nonliving material. Lift: Lift unattended object of light bulk upto 1 foot off the ground. Make: Create a a fragile and crude item of negligible bulk, can not be used as a tool, weapon, or spell component. Lasts until sustained ends. Tidy: Color, clean, or soil an object of light bulk instantly. Takes 1 minute of sustaining to clean 1 bulk. | S27: Using magic you are able to do any of the following: Cook: Cool, warm, or flavor 1 pound of nonliving material. Lift: Lift unattended object of light bulk upto 1 foot off the ground. Make: Create a a fragile and crude item of negligible bulk, can not be used as a tool, weapon, or spell component. Lasts until sustained ends. Tidy: Color, clean, or soil an object of light bulk instantly. Takes 1 minute of sustaining to clean 1 bulk. | T27: Using magic you are able to do any of the following: Cook: Cool, warm, or flavor 1 pound of nonliving material. Lift: Lift unattended object of light bulk upto 1 foot off the ground. Make: Create a a fragile and crude item of negligible bulk, can not be used as a tool, weapon, or spell component. Lasts until sustained ends. Tidy: Color, clean, or soil an object of light bulk instantly. Takes 1 minute of sustaining to clean 1 bulk. | U27: Using magic you are able to do any of the following: Cook: Cool, warm, or flavor 1 pound of nonliving material. Lift: Lift unattended object of light bulk upto 1 foot off the ground. Make: Create a a fragile and crude item of negligible bulk, can not be used as a tool, weapon, or spell component. Lasts until sustained ends. Tidy: Color, clean, or soil an object of light bulk instantly. Takes 1 minute of sustaining to clean 1 bulk. | V27: Using magic you are able to do any of the following: Cook: Cool, warm, or flavor 1 pound of nonliving material. Lift: Lift unattended object of light bulk upto 1 foot off the ground. Make: Create a a fragile and crude item of negligible bulk, can not be used as a tool, weapon, or spell component. Lasts until sustained ends. Tidy: Color, clean, or soil an object of light bulk instantly. Takes 1 minute of sustaining to clean 1 bulk. | W27: arcane, divine, occult, primal | X27: Core
A28: Produce Flame | B28: =Spells!$S$4 -> 1 | C28: C | D28: Evo | E28: Y | F28: ='Character Sheet'!$C$9 | G28: S,V | H28: 30ft | I28: 1 creature | J28: Attack | K28: Instant | L28: C | M28: Fill your palm with fire to make a ranged or melee attack dealing 1d4+[Mod] fire damage on hit. Critical hits deal 1d4 persistant fire damage. | N28: Fill your palm with fire to make a ranged or melee attack dealing 2d4+[Mod] fire damage on hit. Critical hits deal 2d4 persistant fire damage. | O28: Fill your palm with fire to make a ranged or melee attack dealing 3d4+[Mod] fire damage on hit. Critical hits deal 3d4 persistant fire damage. | P28: Fill your palm with fire to make a ranged or melee attack dealing 4d4+[Mod] fire damage on hit. Critical hits deal 4d4 persistant fire damage. | Q28: Fill your palm with fire to make a ranged or melee attack dealing 5d4+[Mod] fire damage on hit. Critical hits deal 5d4 persistant fire damage. | R28: Fill your palm with fire to make a ranged or melee attack dealing 6d4+[Mod] fire damage on hit. Critical hits deal 6d4 persistant fire damage. | S28: Fill your palm with fire to make a ranged or melee attack dealing 7d4+[Mod] fire damage on hit. Critical hits deal 7d4 persistant fire damage. | T28: Fill your palm with fire to make a ranged or melee attack dealing 8d4+[Mod] fire damage on hit. Critical hits deal 8d4 persistant fire damage. | U28: Fill your palm with fire to make a ranged or melee attack dealing 9d4+[Mod] fire damage on hit. Critical hits deal 9d4 persistant fire damage. | V28: Fill your palm with fire to make a ranged or melee attack dealing 10d4+[Mod] fire damage on hit. Critical hits deal 10d4 persistant fire damage. | W28: arcane, primal | X28: Core
A29: Protect Companion | B29: =Spells!$S$4 -> 1 | C29: C | D29: Abj | E29: Y | F29: ='Character Sheet'!$B$9 | G29: V | H29: 30ft | I29: 1 companion | J29: N/A | K29: 1 round | L29: C | M29: Target eidolon or minion gains a +1 circumstance bonus to AC as a magical shield protects them. After casting you gain the reaction "Life Block" to reduce any damage the target would take by 10, and you lose 5 hp. Target still takes any additional affects such as poison. After using this reaction you cant cast this spell for 10 minutes. | N29: Target eidolon or minion gains a +1 circumstance bonus to AC as a magical shield protects them. After casting you gain the reaction "Life Block" to reduce any damage the target would take by 10, and you lose 5 hp. Target still takes any additional affects such as poison. After using this reaction you cant cast this spell for 10 minutes. | O29: Target eidolon or minion gains a +1 circumstance bonus to AC as a magical shield protects them. After casting you gain the reaction "Life Block" to reduce any damage the target would take by upto 20, and you lose hp equal to half the damage blocked. Target still takes any additional affects such as poison. After using this reaction you cant cast this spell for 10 minutes. | P29: Target eidolon or minion gains a +1 circumstance bonus to AC as a magical shield protects them. After casting you gain the reaction "Life Block" to reduce any damage the target would take by upto 20, and you lose hp equal to half the damage blocked. Target still takes any additional affects such as poison. After using this reaction you cant cast this spell for 10 minutes. | Q29: Target eidolon or minion gains a +1 circumstance bonus to AC as a magical shield protects them. After casting you gain the reaction "Life Block" to reduce any damage the target would take by upto 30, and you lose hp equal to half the damage blocked. Target still takes any additional affects such as poison. After using this reaction you cant cast this spell for 10 minutes. | R29: Target eidolon or minion gains a +1 circumstance bonus to AC as a magical shield protects them. After casting you gain the reaction "Life Block" to reduce any damage the target would take by upto 30, and you lose hp equal to half the damage blocked. Target still takes any additional affects such as poison. After using this reaction you cant cast this spell for 10 minutes. | S29: Target eidolon or minion gains a +1 circumstance bonus to AC as a magical shield protects them. After casting you gain the reaction "Life Block" to reduce any damage the target would take by upto 40, and you lose hp equal to half the damage blocked. Target still takes any additional affects such as poison. After using this reaction you cant cast this spell for 10 minutes. | T29: Target eidolon or minion gains a +1 circumstance bonus to AC as a magical shield protects them. After casting you gain the reaction "Life Block" to reduce any damage the target would take by upto 40, and you lose hp equal to half the damage blocked. Target still takes any additional affects such as poison. After using this reaction you cant cast this spell for 10 minutes. | U29: Target eidolon or minion gains a +1 circumstance bonus to AC as a magical shield protects them. After casting you gain the reaction "Life Block" to reduce any damage the target would take by upto 50, and you lose hp equal to half the damage blocked. Target still takes any additional affects such as poison. After using this reaction you cant cast this spell for 10 minutes. | V29: Target eidolon or minion gains a +1 circumstance bonus to AC as a magical shield protects them. After casting you gain the reaction "Life Block" to reduce any damage the target would take by upto 50, and you lose hp equal to half the damage blocked. Target still takes any additional affects such as poison. After using this reaction you cant cast this spell for 10 minutes. | W29: arcane, divine, occult, primal | X29: Secrets of Magic
A30: Puff of Poison | B30: =Spells!$S$4 -> 1 | C30: C | D30: Evo | E30: Y | F30: ='Character Sheet'!$C$9 | G30: S,V | H30: 5ft | I30: 1 creature | J30: Basic Fortitude | K30: Instant | L30: C | M30: Breathing out poison breath the target takes [Spellcasting Mod] poison damage and 2 persistent damage. Successful save is half damage and persistent damage. Critical failure results in double intial and persistant damage. | N30: Breathing out poison breath the target takes [Spellcasting Mod] poison damage and 2 persistent damage. Successful save is half damage and persistent damage. Critical failure results in double intial and persistant damage. | O30: Breathing out poison breath the target takes 1d8+[Mod] poison damage and 3 persistent damage. Successful save is half damage and persistent damage. Critical failure results in double intial and persistant damage. | P30: Breathing out poison breath the target takes 1d8+[Mod] poison damage and 3 persistent damage. Successful save is half damage and persistent damage. Critical failure results in double intial and persistant damage. | Q30: Breathing out poison breath the target takes 2d8+[Mod] poison damage and 4 persistent damage. Successful save is half damage and persistent damage. Critical failure results in double intial and persistant damage. | R30: Breathing out poison breath the target takes 2d8+[Mod] poison damage and 4 persistent damage. Successful save is half damage and persistent damage. Critical failure results in double intial and persistant damage. | S30: Breathing out poison breath the target takes 3d8+[Mod] poison damage and 5 persistent damage. Successful save is half damage and persistent damage. Critical failure results in double intial and persistant damage. | T30: Breathing out poison breath the target takes 3d8+[Mod] poison damage and 5 persistent damage. Successful save is half damage and persistent damage. Critical failure results in double intial and persistant damage. | U30: Breathing out poison breath the target takes 4d8+[Mod] poison damage and 6 persistent damage. Successful save is half damage and persistent damage. Critical failure results in double intial and persistant damage. | V30: Breathing out poison breath the target takes 4d8+[Mod] poison damage and 6 persistent damage. Successful save is half damage and persistent damage. Critical failure results in double intial and persistant damage. | W30: arcane, primal | X30: Secrets of Magic
A31: Ray of Frost | B31: =Spells!$S$4 -> 1 | C31: C | D31: Evo | E31: Y | F31: ='Character Sheet'!$C$9 | G31: S,V | H31: 120ft | I31: 1 creature | J31: Attack | K31: Instant | L31: C | M31: Spray a blast of ice that deals 1d4+[Mod] cold damage. On a Critical hit target takes double damage and their speed is lowered by 10 for 1 round | N31: Spray a blast of ice that deals 2d4+[Mod] cold damage. On a Critical hit target takes double damage and their speed is lowered by 10 for 1 round | O31: Spray a blast of ice that deals 3d4+[Mod] cold damage. On a Critical hit target takes double damage and their speed is lowered by 10 for 1 round | P31: Spray a blast of ice that deals 4d4+[Mod] cold damage. On a Critical hit target takes double damage and their speed is lowered by 10 for 1 round | Q31: Spray a blast of ice that deals 5d4+[Mod] cold damage. On a Critical hit target takes double damage and their speed is lowered by 10 for 1 round | R31: Spray a blast of ice that deals 6d4+[Mod] cold damage. On a Critical hit target takes double damage and their speed is lowered by 10 for 1 round | S31: Spray a blast of ice that deals 7d4+[Mod] cold damage. On a Critical hit target takes double damage and their speed is lowered by 10 for 1 round | T31: Spray a blast of ice that deals 8d4+[Mod] cold damage. On a Critical hit target takes double damage and their speed is lowered by 10 for 1 round | U31: Spray a blast of ice that deals 9d4+[Mod] cold damage. On a Critical hit target takes double damage and their speed is lowered by 10 for 1 round | V31: Spray a blast of ice that deals 10d4+[Mod] cold damage. On a Critical hit target takes double damage and their speed is lowered by 10 for 1 round | W31: arcane, primal | X31: Core
A32: Read Aura | B32: =Spells!$S$4 -> 1 | C32: C | D32: Div | E32: Y | F32: 1min | G32: S,V | H32: 30ft | I32: 1 object | J32: N/A | K32: Instant | L32: C | M32: Opening your mind you can tell if the item is magical, and if it is you learn its school of magic. The object only shows up as illusion if the level is lower than the level Read Aura was cast at. | N32: Opening your mind you can tell if the item is magical, and if it is you learn its school of magic. The object only shows up as illusion if the level is lower than the level Read Aura was cast at. | O32: Opening your mind you can tell if upto 10 items are magical, and if so you learn its school of magic. The object only shows up as illusion if the level is lower than the level Read Aura was cast at. | P32: Opening your mind you can tell if upto 10 items are magical, and if so you learn its school of magic. The object only shows up as illusion if the level is lower than the level Read Aura was cast at. | Q32: Opening your mind you can tell if upto 10 items are magical, and if so you learn its school of magic. The object only shows up as illusion if the level is lower than the level Read Aura was cast at. | R32: Opening your mind you can tell if upto any number of items are magical, and if so you learn its school of magic. The object only shows up as illusion if the level is lower than the level Read Aura was cast at. | S32: Opening your mind you can tell if upto any number of items are magical, and if so you learn its school of magic. The object only shows up as illusion if the level is lower than the level Read Aura was cast at. | T32: Opening your mind you can tell if upto any number of items are magical, and if so you learn its school of magic. The object only shows up as illusion if the level is lower than the level Read Aura was cast at. | U32: Opening your mind you can tell if upto any number of items are magical, and if so you learn its school of magic. The object only shows up as illusion if the level is lower than the level Read Aura was cast at. | V32: Opening your mind you can tell if upto any number of items are magical, and if so you learn its school of magic. The object only shows up as illusion if the level is lower than the level Read Aura was cast at. | W32: arcane, divine, occult, primal | X32: Core
A33: Read the Air | B33: =Spells!$S$4 -> 1 | C33: C | D33: Div | E33: N | F33: ='Character Sheet'!$C$9 | G33: S,V | H33: Self | I33: N/A | J33: Socety | K33: 1 min | L33: C | M33: Understanding your situation you are able to Recall Knowledge using Society to gain information and change your subconcious to better take advantage of this. Gain a +1 status bonus to your next Diplomacy check to Make an Impression. | N33: Understanding your situation you are able to Recall Knowledge using Society to gain information and change your subconcious to better take advantage of this. Gain a +1 status bonus to your next Diplomacy check to Make an Impression. | O33: Understanding your situation you are able to Recall Knowledge using Society to gain information and change your subconcious to better take advantage of this. Gain a +1 status bonus to your next Diplomacy check to Make an Impression. | P33: Understanding your situation you are able to Recall Knowledge using Society to gain information and change your subconcious to better take advantage of this. Gain a +1 status bonus to your next Diplomacy check to Make an Impression. | Q33: Understanding your situation you are able to Recall Knowledge using Society to gain information and change your subconcious to better take advantage of this. Gain a +1 status bonus to your next Diplomacy check to Make an Impression. | R33: Understanding your situation you are able to Recall Knowledge using Society to gain information and change your subconcious to better take advantage of this. Gain a +1 status bonus to your next Diplomacy check to Make an Impression. | S33: Understanding your situation you are able to Recall Knowledge using Society to gain information and change your subconcious to better take advantage of this. Gain a +1 status bonus to your next Diplomacy check to Make an Impression. | T33: Understanding your situation you are able to Recall Knowledge using Society to gain information and change your subconcious to better take advantage of this. Gain a +1 status bonus to your next Diplomacy check to Make an Impression. | U33: Understanding your situation you are able to Recall Knowledge using Society to gain information and change your subconcious to better take advantage of this. Gain a +1 status bonus to your next Diplomacy check to Make an Impression. | V33: Understanding your situation you are able to Recall Knowledge using Society to gain information and change your subconcious to better take advantage of this. Gain a +1 status bonus to your next Diplomacy check to Make an Impression. | W33: divine, occult | X33: Secrets of Magic
A34: Scatter Scree | B34: =Spells!$S$4 -> 1 | C34: C | D34: Evo | E34: Y | F34: ='Character Sheet'!$C$9 | G34: S,V | H34: 30ft | I34: 10ft line | J34: Basic Reflex | K34: 1 min | L34: C | M34: Evoke nearby rocks to destroy terrain. Any creature within area takes 1d4+[Mod] bludgeoning damage, and area becomes difficult terrain for the duration. Second casting removes previous effects instantly. | N34: Evoke nearby rocks to destroy terrain. Any creature within area takes 2d4+[Mod] bludgeoning damage, and area becomes difficult terrain for the duration. Second casting removes previous effects instantly. | O34: Evoke nearby rocks to destroy terrain. Any creature within area takes 3d4+[Mod] bludgeoning damage, and area becomes difficult terrain for the duration. Second casting removes previous effects instantly. | P34: Evoke nearby rocks to destroy terrain. Any creature within area takes 4d4+[Mod] bludgeoning damage, and area becomes difficult terrain for the duration. Second casting removes previous effects instantly. | Q34: Evoke nearby rocks to destroy terrain. Any creature within area takes 5d4+[Mod] bludgeoning damage, and area becomes difficult terrain for the duration. Second casting removes previous effects instantly. | R34: Evoke nearby rocks to destroy terrain. Any creature within area takes 6d4+[Mod] bludgeoning damage, and area becomes difficult terrain for the duration. Second casting removes previous effects instantly. | S34: Evoke nearby rocks to destroy terrain. Any creature within area takes 7d4+[Mod] bludgeoning damage, and area becomes difficult terrain for the duration. Second casting removes previous effects instantly. | T34: Evoke nearby rocks to destroy terrain. Any creature within area takes 8d4+[Mod] bludgeoning damage, and area becomes difficult terrain for the duration. Second casting removes previous effects instantly. | U34: Evoke nearby rocks to destroy terrain. Any creature within area takes 9d4+[Mod] bludgeoning damage, and area becomes difficult terrain for the duration. Second casting removes previous effects instantly. | V34: Evoke nearby rocks to destroy terrain. Any creature within area takes 10d4+[Mod] bludgeoning damage, and area becomes difficult terrain for the duration. Second casting removes previous effects instantly. | W34: arcane, primal | X34: Secrets of Magic
A35: Shield | B35: =Spells!$S$4 -> 1 | C35: C | D35: Abj | E35: Y | F35: ='Character Sheet'!$B$9 | G35: V | H35: Self | I35: N/A | J35: N/A | K35: 1 round | L35: C | M35: You create and raise a magical shield, gaining a +1 circumstance bonus to your AC. You gain the Shield Block reaction with a hardness of 5 that can be used against magic missle. Once cast the spell can not be cast again for 10 minutes | N35: You create and raise a magical shield, gaining a +1 circumstance bonus to your AC. You gain the Shield Block reaction with a hardness of 5 that can be used against magic missle. Once cast the spell can not be cast again for 10 minutes | O35: You create and raise a magical shield, gaining a +1 circumstance bonus to your AC. You gain the Shield Block reaction with a hardness of 10 that can be used against magic missle. Once cast the spell can not be cast again for 10 minutes | P35: You create and raise a magical shield, gaining a +1 circumstance bonus to your AC. You gain the Shield Block reaction with a hardness of 10 that can be used against magic missle. Once cast the spell can not be cast again for 10 minutes | Q35: You create and raise a magical shield, gaining a +1 circumstance bonus to your AC. You gain the Shield Block reaction with a hardness of 15 that can be used against magic missle. Once cast the spell can not be cast again for 10 minutes | R35: You create and raise a magical shield, gaining a +1 circumstance bonus to your AC. You gain the Shield Block reaction with a hardness of 15 that can be used against magic missle. Once cast the spell can not be cast again for 10 minutes | S35: You create and raise a magical shield, gaining a +1 circumstance bonus to your AC. You gain the Shield Block reaction with a hardness of 20 that can be used against magic missle. Once cast the spell can not be cast again for 10 minutes | T35: You create and raise a magical shield, gaining a +1 circumstance bonus to your AC. You gain the Shield Block reaction with a hardness of 20 that can be used against magic missle. Once cast the spell can not be cast again for 10 minutes | U35: You create and raise a magical shield, gaining a +1 circumstance bonus to your AC. You gain the Shield Block reaction with a hardness of 25 that can be used against magic missle. Once cast the spell can not be cast again for 10 minutes | V35: You create and raise a magical shield, gaining a +1 circumstance bonus to your AC. You gain the Shield Block reaction with a hardness of 25 that can be used against magic missle. Once cast the spell can not be cast again for 10 minutes | W35: arcane, divine, occult | X35: Core
A36: Sigil | B36: =Spells!$S$4 -> 1 | C36: C | D36: Tran | E36: Y | F36: ='Character Sheet'!$C$9 | G36: S,V | H36: Touch | I36: Creature or object | J36: N/A | K36: varies | L36: C | M36: Create a unique magical mark 1 square inch in size. The mark can be switched between visible and invisible with an action, and removed by anyone with 5 minutes of work. Will naturally fade away over the course of 1 week. | N36: Create a unique magical mark 1 square inch in size. The mark can be switched between visible and invisible with an action, and removed by anyone with 5 minutes of work. Will naturally fade away over the course of 1 week. | O36: Create a unique magical mark 1 square inch in size. The mark can be switched between visible and invisible with an action, and removed by anyone with 5 minutes of work. Will naturally fade away over the course of 1 month. | P36: Create a unique magical mark 1 square inch in size. The mark can be switched between visible and invisible with an action, and removed by anyone with 5 minutes of work. Will naturally fade away over the course of 1 month. | Q36: Create a unique magical mark 1 square inch in size. The mark can be switched between visible and invisible with an action, and removed by anyone with 5 minutes of work. Will naturally fade away over the course of 1 year. | R36: Create a unique magical mark 1 square inch in size. The mark can be switched between visible and invisible with an action, and removed by anyone with 5 minutes of work. Will naturally fade away over the course of 1 year. | S36: Create a unique magical mark 1 square inch in size. The mark can be switched between visible and invisible with an action, and removed by anyone with 5 minutes of work. The mark will never naturally fade away or deteriate. | T36: Create a unique magical mark 1 square inch in size. The mark can be switched between visible and invisible with an action, and removed by anyone with 5 minutes of work. The mark will never naturally fade away or deteriate. | U36: Create a unique magical mark 1 square inch in size. The mark can be switched between visible and invisible with an action, and removed by anyone with 5 minutes of work. The mark will never naturally fade away or deteriate. | V36: Create a unique magical mark 1 square inch in size. The mark can be switched between visible and invisible with an action, and removed by anyone with 5 minutes of work. The mark will never naturally fade away or deteriate. | W36: arcane, divine, occult, primal | X36: Core
A37: Spout | B37: =Spells!$S$4 -> 1 | C37: C | D37: Evo | E37: Y | F37: ='Character Sheet'!$C$9 | G37: S,V | H37: 30ft | I37: 5ft Cube | J37: Basic Reflex | K37: Instant | L37: C | M37: Create a blast of water. Any creature in its area will take 1d4+[Mod]. Spell's area becomes a 5ft burst if cast over a pound or creek. | N37: Create a blast of water. Any creature in its area will take 2d4+[Mod]. Spell's area becomes a 5ft burst if cast over a pound or creek. | O37: Create a blast of water. Any creature in its area will take 3d4+[Mod]. Spell's area becomes a 5ft burst if cast over a pound or creek. | P37: Create a blast of water. Any creature in its area will take 4d4+[Mod]. Spell's area becomes a 5ft burst if cast over a pound or creek. | Q37: Create a blast of water. Any creature in its area will take 5d4+[Mod]. Spell's area becomes a 5ft burst if cast over a pound or creek. | R37: Create a blast of water. Any creature in its area will take 6d4+[Mod]. Spell's area becomes a 5ft burst if cast over a pound or creek. | S37: Create a blast of water. Any creature in its area will take 7d4+[Mod]. Spell's area becomes a 5ft burst if cast over a pound or creek. | T37: Create a blast of water. Any creature in its area will take 8d4+[Mod]. Spell's area becomes a 5ft burst if cast over a pound or creek. | U37: Create a blast of water. Any creature in its area will take 9d4+[Mod]. Spell's area becomes a 5ft burst if cast over a pound or creek. | V37: Create a blast of water. Any creature in its area will take 10d4+[Mod]. Spell's area becomes a 5ft burst if cast over a pound or creek. | W37: arcane, primal | X37: Secrets of Magic
A38: Stabilize | B38: =Spells!$S$4 -> 1 | C38: C | D38: Nec | E38: N | F38: ='Character Sheet'!$C$9 | G38: S,V | H38: 30ft | I38: 1 dying creature | J38: N/A | K38: Instant | L38: C | M38: Target creature loses the dying condition as positive energy courses through them. They remain at 0hp. | N38: Target creature loses the dying condition as positive energy courses through them. They remain at 0hp. | O38: Target creature loses the dying condition as positive energy courses through them. They remain at 0hp. | P38: Target creature loses the dying condition as positive energy courses through them. They remain at 0hp. | Q38: Target creature loses the dying condition as positive energy courses through them. They remain at 0hp. | R38: Target creature loses the dying condition as positive energy courses through them. They remain at 0hp. | S38: Target creature loses the dying condition as positive energy courses through them. They remain at 0hp. | T38: Target creature loses the dying condition as positive energy courses through them. They remain at 0hp. | U38: Target creature loses the dying condition as positive energy courses through them. They remain at 0hp. | V38: Target creature loses the dying condition as positive energy courses through them. They remain at 0hp. | W38: divine, primal | X38: Core
A39: Summon Instrument | B39: =Spells!$S$4 -> 1 | C39: C | D39: Con | E39: Y | F39: ='Character Sheet'!$E$9 | G39: M,S,V | H39: Self | I39: N/A | J39: N/A | K39: 1 hour | L39: C | M39: Summon a handheld musical instrument that only plays for you for the duration. A second casting causes the first to disappear. | N39: Summon a handheld musical instrument that only plays for you for the duration. A second casting causes the first to disappear. | O39: Summon a handheld musical instrument that only plays for you for the duration. A second casting causes the first to disappear. | P39: Summon a handheld musical instrument that only plays for you for the duration. A second casting causes the first to disappear. | Q39: Summon a virtuoso handheld musical instrument that only plays for you for the duration. A second casting causes the first to disappear. | R39: Summon a virtuoso handheld musical instrument that only plays for you for the duration. A second casting causes the first to disappear. | S39: Summon a virtuoso handheld musical instrument that only plays for you for the duration. A second casting causes the first to disappear. | T39: Summon a virtuoso handheld musical instrument that only plays for you for the duration. A second casting causes the first to disappear. | U39: Summon a virtuoso handheld musical instrument that only plays for you for the duration. A second casting causes the first to disappear. | V39: Summon a virtuoso handheld musical instrument that only plays for you for the duration. A second casting causes the first to disappear. | W39: divine, occult | X39: Advanced Player's Guide
A40: Tame | B40: =Spells!$S$4 -> 1 | C40: C | D40: Ench | E40: Y | F40: ='Character Sheet'!$C$9 | G40: S,V | H40: 10ft | I40: 1 domestic animal | J40: Will | K40: 1 min | L40: C | M40: By being kind and confident you are able to increase the target's attitude by 1 step (such as unfriendly to neutral) for the duration. Afterwards target becomes immune for 1 day. Only works on animals that are at least semi tamed or domesticated (such as feral dogs but not wolves). | N40: By being kind and confident you are able to increase the target's attitude by 1 step (such as unfriendly to neutral) for the duration. Afterwards target becomes immune for 1 day. Only works on animals that are at least semi tamed or domesticated (such as feral dogs but not wolves). | O40: By being kind and confident you are able to increase the target's attitude by 1 step (such as unfriendly to neutral) for 10 minutes. Afterwards target becomes immune for 1 day. Only works on animals that are at least semi tamed or domesticated (such as feral dogs but not wolves). | P40: By being kind and confident you are able to increase the target's attitude by 1 step (such as unfriendly to neutral) for 10 minutes. Afterwards target becomes immune for 1 day. Only works on animals that are at least semi tamed or domesticated (such as feral dogs but not wolves). | Q40: By being kind and confident you are able to increase the target's attitude by 1 step (such as unfriendly to neutral) for 10 minutes. Afterwards target becomes immune for 1 day. Only works on animals that are at least semi tamed or domesticated (such as feral dogs but not wolves). | R40: By being kind and confident you are able to increase the target's attitude by 1 step (such as unfriendly to neutral) for 1 hour. Afterwards target becomes immune for 1 day. Only works on animals that are at least semi tamed or domesticated (such as feral dogs but not wolves). | S40: By being kind and confident you are able to increase the target's attitude by 1 step (such as unfriendly to neutral) for 1 hour. Afterwards target becomes immune for 1 day. Only works on animals that are at least semi tamed or domesticated (such as feral dogs but not wolves). | T40: By being kind and confident you are able to increase the target's attitude by 1 step (such as unfriendly to neutral) for 1 hour. Afterwards target becomes immune for 1 day. Only works on animals that are at least semi tamed or domesticated (such as feral dogs but not wolves). | U40: By being kind and confident you are able to increase the target's attitude by 1 step (such as unfriendly to neutral) for 1 hour. Afterwards target becomes immune for 1 day. Only works on animals that are at least semi tamed or domesticated (such as feral dogs but not wolves). | V40: By being kind and confident you are able to increase the target's attitude by 1 step (such as unfriendly to neutral) for 1 hour. Afterwards target becomes immune for 1 day. Only works on animals that are at least semi tamed or domesticated (such as feral dogs but not wolves). | W40: occult, primal | X40: Secrets of Magic
A41: Tanglefoot | B41: =Spells!$S$4 -> 1 | C41: C | D41: Con | E41: Y | F41: ='Character Sheet'!$C$9 | G41: S,V | H41: 30ft | I41: 1 creature | J41: Attack | K41: 1 round | L41: C | M41: A vine covered in sticky sap appears to attack the target, binding them. On successful hit target's speed is reduced by 10ft for 1 round, Escape attempt against spell DC to remove penalty. On Critical success results in target being immobilized in addition to previous affects. | N41: A vine covered in sticky sap appears to attack the target, binding them. On successful hit target's speed is reduced by 10ft for 2 rounds, Escape attempt against spell DC to remove penalty. On Critical success results in target being immobilized in addition to previous affects. | O41: A vine covered in sticky sap appears to attack the target, binding them. On successful hit target's speed is reduced by 10ft for 2 rounds, Escape attempt against spell DC to remove penalty. On Critical success results in target being immobilized in addition to previous affects. | P41: A vine covered in sticky sap appears to attack the target, binding them. On successful hit target's speed is reduced by 10ft for 1 minute, Escape attempt against spell DC to remove penalty. On Critical success results in target being immobilized in addition to previous affects. | Q41: A vine covered in sticky sap appears to attack the target, binding them. On successful hit target's speed is reduced by 10ft for 1 minute, Escape attempt against spell DC to remove penalty. On Critical success results in target being immobilized in addition to previous affects. | R41: A vine covered in sticky sap appears to attack the target, binding them. On successful hit target's speed is reduced by 10ft for 1 minute, Escape attempt against spell DC to remove penalty. On Critical success results in target being immobilized in addition to previous affects. | S41: A vine covered in sticky sap appears to attack the target, binding them. On successful hit target's speed is reduced by 10ft for 1 minute, Escape attempt against spell DC to remove penalty. On Critical success results in target being immobilized in addition to previous affects. | T41: A vine covered in sticky sap appears to attack the target, binding them. On successful hit target's speed is reduced by 10ft for 1 minute, Escape attempt against spell DC to remove penalty. On Critical success results in target being immobilized in addition to previous affects. | U41: A vine covered in sticky sap appears to attack the target, binding them. On successful hit target's speed is reduced by 10ft for 1 minute, Escape attempt against spell DC to remove penalty. On Critical success results in target being immobilized in addition to previous affects. | V41: A vine covered in sticky sap appears to attack the target, binding them. On successful hit target's speed is reduced by 10ft for 1 minute, Escape attempt against spell DC to remove penalty. On Critical success results in target being immobilized in addition to previous affects. | W41: arcane, primal | X41: Core
A42: Telekinetic Projectile | B42: =Spells!$S$4 -> 1 | C42: C | D42: Evo | E42: Y | F42: ='Character Sheet'!$C$9 | G42: S,V | H42: 30ft | I42: 1 creature | J42: Attack | K42: Instant | L42: C | M42: Hurl an object of 1 bulk or less. On hit deal 1d6+[Mod] bludgeoning, percing, or slashing damage based on object hurled. | N42: Hurl an object of 1 bulk or less. On hit deal 2d6+[Mod] bludgeoning, percing, or slashing damage based on object hurled. | O42: Hurl an object of 1 bulk or less. On hit deal 3d6+[Mod] bludgeoning, percing, or slashing damage based on object hurled. | P42: Hurl an object of 1 bulk or less. On hit deal 4d6+[Mod] bludgeoning, percing, or slashing damage based on object hurled. | Q42: Hurl an object of 1 bulk or less. On hit deal 5d6+[Mod] bludgeoning, percing, or slashing damage based on object hurled. | R42: Hurl an object of 1 bulk or less. On hit deal 6d6+[Mod] bludgeoning, percing, or slashing damage based on object hurled. | S42: Hurl an object of 1 bulk or less. On hit deal 7d6+[Mod] bludgeoning, percing, or slashing damage based on object hurled. | T42: Hurl an object of 1 bulk or less. On hit deal 8d6+[Mod] bludgeoning, percing, or slashing damage based on object hurled. | U42: Hurl an object of 1 bulk or less. On hit deal 9d6+[Mod] bludgeoning, percing, or slashing damage based on object hurled. | V42: Hurl an object of 1 bulk or less. On hit deal 10d6+[Mod] bludgeoning, percing, or slashing damage based on object hurled. | W42: arcane, occult | X42: Core
A43: Time Sense | B43: =Spells!$S$4 -> 1 | C43: C | D43: Div | E43: N | F43: ='Character Sheet'!$B$9 | G43: V | H43: Self | I43: Self | J43: N/A | K43: 1 round | L43: C | M43: You gain a +1 status bonus to 1 attack, perception check, saving throw, or skill check on the same turn that requires percise timing. You also know exactly what time it is or perfect knowledge of the calander. Trained in Nature allows you to know how long until sunrise and the next solstice. Training in Astronomy Lore results in knowing any predictable astromical will begin and end. | N43: You gain a +1 status bonus to 1 attack, perception check, saving throw, or skill check on the same turn that requires percise timing. You also know exactly what time it is or perfect knowledge of the calander. Trained in Nature allows you to know how long until sunrise and the next solstice. Training in Astronomy Lore results in knowing any predictable astromical will begin and end. | O43: You gain a +1 status bonus to 1 attack, perception check, saving throw, or skill check on the same turn that requires percise timing. You also know exactly what time it is or perfect knowledge of the calander. Trained in Nature allows you to know how long until sunrise and the next solstice. Training in Astronomy Lore results in knowing any predictable astromical will begin and end. | P43: You gain a +1 status bonus to 1 attack, perception check, saving throw, or skill check on the same turn that requires percise timing. You also know exactly what time it is or perfect knowledge of the calander. Trained in Nature allows you to know how long until sunrise and the next solstice. Training in Astronomy Lore results in knowing any predictable astromical will begin and end. | Q43: You gain a +1 status bonus to 1 attack, perception check, saving throw, or skill check on the same turn that requires percise timing. You also know exactly what time it is or perfect knowledge of the calander. Trained in Nature allows you to know how long until sunrise and the next solstice. Training in Astronomy Lore results in knowing any predictable astromical will begin and end. | R43: You gain a +1 status bonus to 1 attack, perception check, saving throw, or skill check on the same turn that requires percise timing. You also know exactly what time it is or perfect knowledge of the calander. Trained in Nature allows you to know how long until sunrise and the next solstice. Training in Astronomy Lore results in knowing any predictable astromical will begin and end. | S43: You gain a +1 status bonus to 1 attack, perception check, saving throw, or skill check on the same turn that requires percise timing. You also know exactly what time it is or perfect knowledge of the calander. Trained in Nature allows you to know how long until sunrise and the next solstice. Training in Astronomy Lore results in knowing any predictable astromical will begin and end. | T43: You gain a +1 status bonus to 1 attack, perception check, saving throw, or skill check on the same turn that requires percise timing. You also know exactly what time it is or perfect knowledge of the calander. Trained in Nature allows you to know how long until sunrise and the next solstice. Training in Astronomy Lore results in knowing any predictable astromical will begin and end. | U43: You gain a +1 status bonus to 1 attack, perception check, saving throw, or skill check on the same turn that requires percise timing. You also know exactly what time it is or perfect knowledge of the calander. Trained in Nature allows you to know how long until sunrise and the next solstice. Training in Astronomy Lore results in knowing any predictable astromical will begin and end. | V43: You gain a +1 status bonus to 1 attack, perception check, saving throw, or skill check on the same turn that requires percise timing. You also know exactly what time it is or perfect knowledge of the calander. Trained in Nature allows you to know how long until sunrise and the next solstice. Training in Astronomy Lore results in knowing any predictable astromical will begin and end. | W43: arcane, occult | X43: Dark Archive
A44: Warp Step | B44: =Spells!$S$4 -> 1 | C44: C | D44: Con | E44: N | F44: ='Character Sheet'!$C$9 | G44: S,V | H44: Self | I44: Self | J44: N/A | K44: Instant | L44: C | M44: Warping the earth benieth your step you gain a +5ft status bonus to your speed for the rest of your turn and can stride twice instantly. Warp Step can be used to Burrow, Climb, Fly, or Swim instead of stride if you have the corresponding movement type. | N44: Warping the earth benieth your step you gain a +5ft status bonus to your speed for the rest of your turn and can stride twice instantly. Warp Step can be used to Burrow, Climb, Fly, or Swim instead of stride if you have the corresponding movement type. | O44: Warping the earth benieth your step you gain a +5ft status bonus to your speed for the rest of your turn and can stride twice instantly. Warp Step can be used to Burrow, Climb, Fly, or Swim instead of stride if you have the corresponding movement type. | P44: Warping the earth benieth your step you gain a +5ft status bonus to your speed for the rest of your turn and can stride twice instantly. Warp Step can be used to Burrow, Climb, Fly, or Swim instead of stride if you have the corresponding movement type. | Q44: Warping the earth benieth your step you gain a +5ft status bonus to your speed for the rest of your turn and can stride twice instantly. Warp Step can be used to Burrow, Climb, Fly, or Swim instead of stride if you have the corresponding movement type. | R44: Warping the earth benieth your step you gain a +5ft status bonus to your speed for the rest of your turn and can stride twice instantly. Warp Step can be used to Burrow, Climb, Fly, or Swim instead of stride if you have the corresponding movement type. | S44: Warping the earth benieth your step you gain a +5ft status bonus to your speed for the rest of your turn and can stride twice instantly. Warp Step can be used to Burrow, Climb, Fly, or Swim instead of stride if you have the corresponding movement type. | T44: Warping the earth benieth your step you gain a +5ft status bonus to your speed for the rest of your turn and can stride twice instantly. Warp Step can be used to Burrow, Climb, Fly, or Swim instead of stride if you have the corresponding movement type. | U44: Warping the earth benieth your step you gain a +5ft status bonus to your speed for the rest of your turn and can stride twice instantly. Warp Step can be used to Burrow, Climb, Fly, or Swim instead of stride if you have the corresponding movement type. | V44: Warping the earth benieth your step you gain a +5ft status bonus to your speed for the rest of your turn and can stride twice instantly. Warp Step can be used to Burrow, Climb, Fly, or Swim instead of stride if you have the corresponding movement type. | W44: arcane, occult | X44: Dark Archive
A45: Wash Your Luck | B45: =Spells!$S$4 -> 1 | C45: C | D45: Abj | E45: N | F45: ='Character Sheet'!$C$9 | G45: S,V | H45: Self | I45: N/A | J45: N/A | K45: 1 min | L45: C | M45: Praying to what ever gods of luck you might believe in you wash yourself of misfortune. Before rolling a check, cancel out a misfortune effect as if by fortune. After doing so you are immune to this spell's effects for 10 mintues. | N45: Praying to what ever gods of luck you might believe in you wash yourself of misfortune. Before rolling a check, cancel out a misfortune effect as if by fortune. After doing so you are immune to this spell's effects for 10 mintues. | O45: Praying to what ever gods of luck you might believe in you wash yourself of misfortune. Before rolling a check, cancel out a misfortune effect as if by fortune. After doing so you are immune to this spell's effects for 10 mintues. | P45: Praying to what ever gods of luck you might believe in you wash yourself of misfortune. Before rolling a check, cancel out a misfortune effect as if by fortune. After doing so you are immune to this spell's effects for 10 mintues. | Q45: Praying to what ever gods of luck you might believe in you wash yourself of misfortune. Before rolling a check, cancel out a misfortune effect as if by fortune. After doing so you are immune to this spell's effects for 10 mintues. | R45: Praying to what ever gods of luck you might believe in you wash yourself of misfortune. Before rolling a check, cancel out a misfortune effect as if by fortune. After doing so you are immune to this spell's effects for 10 mintues. | S45: Praying to what ever gods of luck you might believe in you wash yourself of misfortune. Before rolling a check, cancel out a misfortune effect as if by fortune. After doing so you are immune to this spell's effects for 10 mintues. | T45: Praying to what ever gods of luck you might believe in you wash yourself of misfortune. Before rolling a check, cancel out a misfortune effect as if by fortune. After doing so you are immune to this spell's effects for 10 mintues. | U45: Praying to what ever gods of luck you might believe in you wash yourself of misfortune. Before rolling a check, cancel out a misfortune effect as if by fortune. After doing so you are immune to this spell's effects for 10 mintues. | V45: Praying to what ever gods of luck you might believe in you wash yourself of misfortune. Before rolling a check, cancel out a misfortune effect as if by fortune. After doing so you are immune to this spell's effects for 10 mintues. | W45: divine, occult | X45: Secrets of Magic
A46: Acidic Burst | B46: 1 | C46: C | D46: Evo | E46: Y | F46: ='Character Sheet'!$C$9 | G46: S,V | H46: Self | I46: 5ft burst | J46: Basic Reflex | K46: Instant | L46: S | M46: Create a shell of acid that bursts outward dealing 2d6 acid damage. | N46: Create a shell of acid that bursts outward dealing 4d6 acid damage. | O46: Create a shell of acid that bursts outward dealing 6d6 acid damage. | P46: Create a shell of acid that bursts outward dealing 8d6 acid damage. | Q46: Create a shell of acid that bursts outward dealing 10d6 acid damage. | R46: Create a shell of acid that bursts outward dealing 12d6 acid damage. | S46: Create a shell of acid that bursts outward dealing 14d6 acid damage. | T46: Create a shell of acid that bursts outward dealing 16d6 acid damage. | U46: Create a shell of acid that bursts outward dealing 18d6 acid damage. | V46: Create a shell of acid that bursts outward dealing 20d6 acid damage. | W46: arcane, primal | X46: Gods & Magic
A47: Admonishing Ray | B47: 1 | C47: C | D47: Nec | E47: Y | F47: ='Character Sheet'!$C$9 | G47: S,V | H47: 60ft | I47: 1 creature | J47: Attack | K47: Instant | L47: S | M47: A bludgeoning ray that doesnt cause lasting harm. A strong punch or slap that deals 2d6 bluedgeoning damage. | N47: A bludgeoning ray that doesnt cause lasting harm. A strong punch or slap that deals 4d6 bluedgeoning damage. | O47: A bludgeoning ray that doesnt cause lasting harm. A strong punch or slap that deals 6d6 bluedgeoning damage. | P47: A bludgeoning ray that doesnt cause lasting harm. A strong punch or slap that deals 8d6 bluedgeoning damage. | Q47: A bludgeoning ray that doesnt cause lasting harm. A strong punch or slap that deals 10d6 bluedgeoning damage. | R47: A bludgeoning ray that doesnt cause lasting harm. A strong punch or slap that deals 12d6 bluedgeoning damage. | S47: A bludgeoning ray that doesnt cause lasting harm. A strong punch or slap that deals 14d6 bluedgeoning damage. | T47: A bludgeoning ray that doesnt cause lasting harm. A strong punch or slap that deals 16d6 bluedgeoning damage. | U47: A bludgeoning ray that doesnt cause lasting harm. A strong punch or slap that deals 18d6 bluedgeoning damage. | V47: A bludgeoning ray that doesnt cause lasting harm. A strong punch or slap that deals 20d6 bluedgeoning damage. | W47: arcane, divine | X47: #158
A48: Agitate | B48: 1 | C48: C | D48: Ench | E48: Y | F48: ='Character Sheet'!$C$9 | G48: S,V | H48: 30ft | I48: 1 creature | J48: Will | K48: varies | L48: S | M48: Send the target into overdrive, forcing them to Stride, Fly, or Swim at least once on their turn or take 2d8 mental damage. On successful Will save duration lasts 1 round. On failed save duration lasts 2 rounds. On Critical fail duration becomes 4 rounds. | N48: Send the target into overdrive, forcing them to Stride, Fly, or Swim at least once on their turn or take 4d8 mental damage. On successful Will save duration lasts 1 round. On failed save duration lasts 2 rounds. On Critical fail duration becomes 4 rounds. | O48: Send the target into overdrive, forcing them to Stride, Fly, or Swim at least once on their turn or take 6d8 mental damage. On successful Will save duration lasts 1 round. On failed save duration lasts 2 rounds. On Critical fail duration becomes 4 rounds. | P48: Send the target into overdrive, forcing them to Stride, Fly, or Swim at least once on their turn or take 8d8 mental damage. On successful Will save duration lasts 1 round. On failed save duration lasts 2 rounds. On Critical fail duration becomes 4 rounds. | Q48: Send the target into overdrive, forcing them to Stride, Fly, or Swim at least once on their turn or take 10d8 mental damage. On successful Will save duration lasts 1 round. On failed save duration lasts 2 rounds. On Critical fail duration becomes 4 rounds. | R48: Send the target into overdrive, forcing them to Stride, Fly, or Swim at least once on their turn or take 12d8 mental damage. On successful Will save duration lasts 1 round. On failed save duration lasts 2 rounds. On Critical fail duration becomes 4 rounds1. | S48: Send the target into overdrive, forcing them to Stride, Fly, or Swim at least once on their turn or take 14d8 mental damage. On successful Will save duration lasts 1 round. On failed save duration lasts 2 rounds. On Critical fail duration becomes 4 rounds. | T48: Send the target into overdrive, forcing them to Stride, Fly, or Swim at least once on their turn or take 16d8 mental damage. On successful Will save duration lasts 1 round. On failed save duration lasts 2 rounds. On Critical fail duration becomes 4 rounds. | U48: Send the target into overdrive, forcing them to Stride, Fly, or Swim at least once on their turn or take 18d8 mental damage. On successful Will save duration lasts 1 round. On failed save duration lasts 2 rounds. On Critical fail duration becomes 4 rounds. | V48: Send the target into overdrive, forcing them to Stride, Fly, or Swim at least once on their turn or take 20d8 mental damage. On successful Will save duration lasts 1 round. On failed save duration lasts 2 rounds. On Critical fail duration becomes 4 rounds. | W48: arcane, occult | X48: Gods & Magic
